Workbook

Sheet Sell CTW
J1: =SUM(J3:J3219) -> 3296 | K1: =SUM(K3:K3219) -> 2681168 | L1: =SUM(L3:L3219) -> 570532.5 | M1: =SUM(M3:M3219) -> 2089594 | N1: =SUM(N3:N3219) -> 2089934
A2: Month | B2: วันที่ | C2: BA | D2: เลขที่คำสั่งซื้อ | E2: เลขที่ใบเสร็จ | F2: รายการ | G2: Barcode | H2: Grand | I2: Size | J2: จำนวน | K2: ราคา | L2: ส่วนลด | M2: รวม | N2: ยอดชำระ | O2: ช่องทางชำระ | P2: Date | Q2: Time | R2: UID | S2: หมายเหตุ | T2: Nation
A3: Nov-25 | B3: 45982 | C3: Pure, Jom | D3: 1763665444492552897 | E3: 202500000000030 | F3: Make Way50 ml. | G3: {=IF(F3<>"",INDEX(tb_MainDatabase[Barcode],MATCH(F3,tb_MainDatabase[Link],0)),"")} -> 8857128012020 | H3: {=IF(F3<>"",INDEX(tb_MainDatabase[Grand],MATCH(F3,tb_MainDatabase[Link],0)),"")} -> EDP | I3: {=IF(F3<>"",INDEX(tb_MainDatabase[Size],MATCH(F3,tb_MainDatabase[Link],0)),"")} -> 50 ml. | J3: 1 | K3: {=IF(F3<>"",INDEX(tb_MainDatabase[ราคา],MATCH(F3,tb_MainDatabase[Link],0)),"")*J3} -> 1890 | L3: 500 | M3: =K3-(L3*J3) -> 1390 | N3: =SUMIF($D$3:D3219,R3,$M$3:M3219) -> 10340 | O3: K Shop Credit Card | P3: 45982 | Q3: 0.44930556 | R3: =IF(COUNTIF(D$3:D3, D3)>1, 0, D3) -> 1763665444492552897
A4: Nov-25 | B4: 45982 | C4: Pure, Jom | D4: 1763665444492552897 | E4: 202500000000030 | F4: Make Way30 ml. | G4: {=IF(F4<>"",INDEX(tb_MainDatabase[Barcode],MATCH(F4,tb_MainDatabase[Link],0)),"")} -> 8857128012024 | H4: {=IF(F4<>"",INDEX(tb_MainDatabase[Grand],MATCH(F4,tb_MainDatabase[Link],0)),"")} -> EDP | I4: {=IF(F4<>"",INDEX(tb_MainDatabase[Size],MATCH(F4,tb_MainDatabase[Link],0)),"")} -> 30 ml. | J4: 1 | K4: {=IF(F4<>"",INDEX(tb_MainDatabase[ราคา],MATCH(F4,tb_MainDatabase[Link],0)),"")*J4} -> 1290 | L4: 300 | M4: =K4-(L4*J4) -> 990 | N4: =SUMIF($D$3:D3220,R4,$M$3:M3220) -> 0 | R4: =IF(COUNTIF(D$3:D4, D4)>1, 0, D4) -> 0
A5: Nov-25 | B5: 45982 | C5: Pure, Jom | D5: 1763665444492552897 | E5: 202500000000030 | F5: Sparkling Mandarin50 ml. | G5: {=IF(F5<>"",INDEX(tb_MainDatabase[Barcode],MATCH(F5,tb_MainDatabase[Link],0)),"")} -> 8857128011713 | H5: {=IF(F5<>"",INDEX(tb_MainDatabase[Grand],MATCH(F5,tb_MainDatabase[Link],0)),"")} -> EDP+ | I5: {=IF(F5<>"",INDEX(tb_MainDatabase[Size],MATCH(F5,tb_MainDatabase[Link],0)),"")} -> 50 ml. | J5: 2 | K5: {=IF(F5<>"",INDEX(tb_MainDatabase[ราคา],MATCH(F5,tb_MainDatabase[Link],0)),"")*J5} -> 5780 | L5: 600 | M5: =K5-(L5*J5) -> 4580 | N5: =SUMIF($D$3:D3221,R5,$M$3:M3221) -> 0 | R5: =IF(COUNTIF(D$3:D5, D5)>1, 0, D5) -> 0
A6: Nov-25 | B6: 45982 | C6: Pure, Jom | D6: 1763665444492552897 | E6: 202500000000030 | F6: Sparkling Mandarin30 ml. | G6: {=IF(F6<>"",INDEX(tb_MainDatabase[Barcode],MATCH(F6,tb_MainDatabase[Link],0)),"")} -> 8857128012010 | H6: {=IF(F6<>"",INDEX(tb_MainDatabase[Grand],MATCH(F6,tb_MainDatabase[Link],0)),"")} -> EDP+ | I6: {=IF(F6<>"",INDEX(tb_MainDatabase[Size],MATCH(F6,tb_MainDatabase[Link],0)),"")} -> 30 ml. | J6: 2 | K6: {=IF(F6<>"",INDEX(tb_MainDatabase[ราคา],MATCH(F6,tb_MainDatabase[Link],0)),"")*J6} -> 3780 | L6: 200 | M6: =K6-(L6*J6) -> 3380 | N6: =SUMIF($D$3:D3222,R6,$M$3:M3222) -> 0 | R6: =IF(COUNTIF(D$3:D6, D6)>1, 0, D6) -> 0
A7: Nov-25 | B7: 45982 | C7: Pure, Jom | D7: 1763665444492552897 | E7: 202500000000030 | F7: Tumbler CYOC (Dark Blue)Dark Blue | G7: {=IF(F7<>"",INDEX(tb_MainDatabase[Barcode],MATCH(F7,tb_MainDatabase[Link],0)),"")} -> 8857128012131 | H7: {=IF(F7<>"",INDEX(tb_MainDatabase[Grand],MATCH(F7,tb_MainDatabase[Link],0)),"")} -> Tumbler | I7: {=IF(F7<>"",INDEX(tb_MainDatabase[Size],MATCH(F7,tb_MainDatabase[Link],0)),"")} -> Dark Blue | J7: 1 | K7: {=IF(F7<>"",INDEX(tb_MainDatabase[ราคา],MATCH(F7,tb_MainDatabase[Link],0)),"")*J7} -> 0 | M7: =K7-(L7*J7) -> 0 | N7: =SUMIF($D$3:D3223,R7,$M$3:M3223) -> 0 | R7: =IF(COUNTIF(D$3:D7, D7)>1, 0, D7) -> 0
A8: Nov-25 | B8: 45982 | C8: Pure, Jom | D8: 1763665444492552897 | E8: 202500000000030 | F8: Cloth BAG CYOCSize M | G8: {=IF(F8<>"",INDEX(tb_MainDatabase[Barcode],MATCH(F8,tb_MainDatabase[Link],0)),"")} -> 8857128012132 | H8: {=IF(F8<>"",INDEX(tb_MainDatabase[Grand],MATCH(F8,tb_MainDatabase[Link],0)),"")} -> Cloth | I8: {=IF(F8<>"",INDEX(tb_MainDatabase[Size],MATCH(F8,tb_MainDatabase[Link],0)),"")} -> Size M | J8: 1 | K8: {=IF(F8<>"",INDEX(tb_MainDatabase[ราคา],MATCH(F8,tb_MainDatabase[Link],0)),"")*J8} -> 0 | M8: =K8-(L8*J8) -> 0 | N8: =SUMIF($D$3:D3224,R8,$M$3:M3224) -> 0 | R8: =IF(COUNTIF(D$3:D8, D8)>1, 0, D8) -> 0
A9: Nov-25 | B9: 45982 | C9: Pure, Jom | D9: 1763665444492552897 | E9: 202500000000030 | F9: Buoyant4 ml. | G9: {=IF(F9<>"",INDEX(tb_MainDatabase[Barcode],MATCH(F9,tb_MainDatabase[Link],0)),"")} -> 8857128012078 | H9: {=IF(F9<>"",INDEX(tb_MainDatabase[Grand],MATCH(F9,tb_MainDatabase[Link],0)),"")} -> EDP | I9: {=IF(F9<>"",INDEX(tb_MainDatabase[Size],MATCH(F9,tb_MainDatabase[Link],0)),"")} -> 4 ml. | J9: 1 | K9: {=IF(F9<>"",INDEX(tb_MainDatabase[ราคา],MATCH(F9,tb_MainDatabase[Link],0)),"")*J9} -> 179 | L9: 179 | M9: =K9-(L9*J9) -> 0 | N9: =SUMIF($D$3:D3225,R9,$M$3:M3225) -> 0 | R9: =IF(COUNTIF(D$3:D9, D9)>1, 0, D9) -> 0
A10: Nov-25 | B10: 45982 | C10: Pure, Jom | D10: 1763665444492552897 | E10: 202500000000030 | F10: Senorita4 ml. | G10: {=IF(F10<>"",INDEX(tb_MainDatabase[Barcode],MATCH(F10,tb_MainDatabase[Link],0)),"")} -> 8857128012040 | H10: {=IF(F10<>"",INDEX(tb_MainDatabase[Grand],MATCH(F10,tb_MainDatabase[Link],0)),"")} -> EDP | I10: {=IF(F10<>"",INDEX(tb_MainDatabase[Size],MATCH(F10,tb_MainDatabase[Link],0)),"")} -> 4 ml. | J10: 1 | K10: {=IF(F10<>"",INDEX(tb_MainDatabase[ราคา],MATCH(F10,tb_MainDatabase[Link],0)),"")*J10} -> 179 | L10: 179 | M10: =K10-(L10*J10) -> 0 | N10: =SUMIF($D$3:D3226,R10,$M$3:M3226) -> 0 | R10: =IF(COUNTIF(D$3:D10, D10)>1, 0, D10) -> 0
A11: Nov-25 | B11: 45982 | C11: Pure, Jom | D11: 1763696917196248249 | E11: 202500000000031 | F11: La Belle50 ml. | G11: {=IF(F11<>"",INDEX(tb_MainDatabase[Barcode],MATCH(F11,tb_MainDatabase[Link],0)),"")} -> 8857128011058 | H11: {=IF(F11<>"",INDEX(tb_MainDatabase[Grand],MATCH(F11,tb_MainDatabase[Link],0)),"")} -> EDP | I11: {=IF(F11<>"",INDEX(tb_MainDatabase[Size],MATCH(F11,tb_MainDatabase[Link],0)),"")} -> 50 ml. | J11: 2 | K11: {=IF(F11<>"",INDEX(tb_MainDatabase[ราคา],MATCH(F11,tb_MainDatabase[Link],0)),"")*J11} -> 3780 | L11: 500 | M11: =K11-(L11*J11) -> 2780 | N11: =SUMIF($D$3:D3227,R11,$M$3:M3227) -> 8340 | O11: K Shop Credit Card | P11: 45982 | Q11: 0.45833333 | R11: =IF(COUNTIF(D$3:D11, D11)>1, 0, D11) -> 1763696917196248249
A12: Nov-25 | B12: 45982 | C12: Pure, Jom | D12: 1763696917196248249 | E12: 202500000000031 | F12: Senorita50 ml. | G12: {=IF(F12<>"",INDEX(tb_MainDatabase[Barcode],MATCH(F12,tb_MainDatabase[Link],0)),"")} -> 8857128011171 | H12: {=IF(F12<>"",INDEX(tb_MainDatabase[Grand],MATCH(F12,tb_MainDatabase[Link],0)),"")} -> EDP | I12: {=IF(F12<>"",INDEX(tb_MainDatabase[Size],MATCH(F12,tb_MainDatabase[Link],0)),"")} -> 50 ml. | J12: 2 | K12: {=IF(F12<>"",INDEX(tb_MainDatabase[ราคา],MATCH(F12,tb_MainDatabase[Link],0)),"")*J12} -> 3780 | L12: 500 | M12: =K12-(L12*J12) -> 2780 | N12: =SUMIF($D$3:D3228,R12,$M$3:M3228) -> 0 | R12: =IF(COUNTIF(D$3:D12, D12)>1, 0, D12) -> 0
A13: Nov-25 | B13: 45982 | C13: Pure, Jom | D13: 1763696917196248249 | E13: 202500000000031 | F13: Voyage50 ml. | G13: {=IF(F13<>"",INDEX(tb_MainDatabase[Barcode],MATCH(F13,tb_MainDatabase[Link],0)),"")} -> 8857128012019 | H13: {=IF(F13<>"",INDEX(tb_MainDatabase[Grand],MATCH(F13,tb_MainDatabase[Link],0)),"")} -> EDP | I13: {=IF(F13<>"",INDEX(tb_MainDatabase[Size],MATCH(F13,tb_MainDatabase[Link],0)),"")} -> 50 ml. | J13: 2 | K13: {=IF(F13<>"",INDEX(tb_MainDatabase[ราคา],MATCH(F13,tb_MainDatabase[Link],0)),"")*J13} -> 3780 | L13: 500 | M13: =K13-(L13*J13) -> 2780 | N13: =SUMIF($D$3:D3229,R13,$M$3:M3229) -> 0 | R13: =IF(COUNTIF(D$3:D13, D13)>1, 0, D13) -> 0
A14: Nov-25 | B14: 45982 | C14: Pure, Jom | D14: 1763696917196248249 | E14: 202500000000031 | F14: Senorita4 ml. | G14: {=IF(F14<>"",INDEX(tb_MainDatabase[Barcode],MATCH(F14,tb_MainDatabase[Link],0)),"")} -> 8857128012040 | H14: {=IF(F14<>"",INDEX(tb_MainDatabase[Grand],MATCH(F14,tb_MainDatabase[Link],0)),"")} -> EDP | I14: {=IF(F14<>"",INDEX(tb_MainDatabase[Size],MATCH(F14,tb_MainDatabase[Link],0)),"")} -> 4 ml. | J14: 1 | K14: {=IF(F14<>"",INDEX(tb_MainDatabase[ราคา],MATCH(F14,tb_MainDatabase[Link],0)),"")*J14} -> 179 | L14: 179 | M14: =K14-(L14*J14) -> 0 | N14: =SUMIF($D$3:D3230,R14,$M$3:M3230) -> 0 | R14: =IF(COUNTIF(D$3:D14, D14)>1, 0, D14) -> 0
A15: Nov-25 | B15: 45982 | C15: Pure, Jom | D15: 1763696917196248249 | E15: 202500000000031 | F15: Buoyant4 ml. | G15: {=IF(F15<>"",INDEX(tb_MainDatabase[Barcode],MATCH(F15,tb_MainDatabase[Link],0)),"")} -> 8857128012078 | H15: {=IF(F15<>"",INDEX(tb_MainDatabase[Grand],MATCH(F15,tb_MainDatabase[Link],0)),"")} -> EDP | I15: {=IF(F15<>"",INDEX(tb_MainDatabase[Size],MATCH(F15,tb_MainDatabase[Link],0)),"")} -> 4 ml. | J15: 1 | K15: {=IF(F15<>"",INDEX(tb_MainDatabase[ราคา],MATCH(F15,tb_MainDatabase[Link],0)),"")*J15} -> 179 | L15: 179 | M15: =K15-(L15*J15) -> 0 | N15: =SUMIF($D$3:D3231,R15,$M$3:M3231) -> 0 | R15: =IF(COUNTIF(D$3:D15, D15)>1, 0, D15) -> 0
A16: Nov-25 | B16: 45982 | C16: Pure, Jom | D16: 1763696917196248249 | E16: 202500000000031 | F16: Cloth BAG CYOCSize M | G16: {=IF(F16<>"",INDEX(tb_MainDatabase[Barcode],MATCH(F16,tb_MainDatabase[Link],0)),"")} -> 8857128012132 | H16: {=IF(F16<>"",INDEX(tb_MainDatabase[Grand],MATCH(F16,tb_MainDatabase[Link],0)),"")} -> Cloth | I16: {=IF(F16<>"",INDEX(tb_MainDatabase[Size],MATCH(F16,tb_MainDatabase[Link],0)),"")} -> Size M | J16: 1 | K16: {=IF(F16<>"",INDEX(tb_MainDatabase[ราคา],MATCH(F16,tb_MainDatabase[Link],0)),"")*J16} -> 0 | M16: =K16-(L16*J16) -> 0 | N16: =SUMIF($D$3:D3232,R16,$M$3:M3232) -> 0 | R16: =IF(COUNTIF(D$3:D16, D16)>1, 0, D16) -> 0
A17: Nov-25 | B17: 45982 | C17: Pure, Jom | D17: 1763696917196248249 | E17: 202500000000031 | F17: Tumbler CYOC (Dark Blue)Dark Blue | G17: {=IF(F17<>"",INDEX(tb_MainDatabase[Barcode],MATCH(F17,tb_MainDatabase[Link],0)),"")} -> 8857128012131 | H17: {=IF(F17<>"",INDEX(tb_MainDatabase[Grand],MATCH(F17,tb_MainDatabase[Link],0)),"")} -> Tumbler | I17: {=IF(F17<>"",INDEX(tb_MainDatabase[Size],MATCH(F17,tb_MainDatabase[Link],0)),"")} -> Dark Blue | J17: 1 | K17: {=IF(F17<>"",INDEX(tb_MainDatabase[ราคา],MATCH(F17,tb_MainDatabase[Link],0)),"")*J17} -> 0 | M17: =K17-(L17*J17) -> 0 | N17: =SUMIF($D$3:D3233,R17,$M$3:M3233) -> 0 | R17: =IF(COUNTIF(D$3:D17, D17)>1, 0, D17) -> 0
A18: Nov-25 | B18: 45982 | C18: Pure, Jom | D18: 1763698140402109979 | E18: 202500000000032 | F18: Voyage50 ml. | G18: {=IF(F18<>"",INDEX(tb_MainDatabase[Barcode],MATCH(F18,tb_MainDatabase[Link],0)),"")} -> 8857128012019 | H18: {=IF(F18<>"",INDEX(tb_MainDatabase[Grand],MATCH(F18,tb_MainDatabase[Link],0)),"")} -> EDP | I18: {=IF(F18<>"",INDEX(tb_MainDatabase[Size],MATCH(F18,tb_MainDatabase[Link],0)),"")} -> 50 ml. | J18: 2 | K18: {=IF(F18<>"",INDEX(tb_MainDatabase[ราคา],MATCH(F18,tb_MainDatabase[Link],0)),"")*J18} -> 3780 | L18: 500 | M18: =K18-(L18*J18) -> 2780 | N18: =SUMIF($D$3:D3234,R18,$M$3:M3234) -> 5560 | O18: K Shop Credit Card | P18: 45982 | Q18: 0.46527778 | R18: =IF(COUNTIF(D$3:D18, D18)>1, 0, D18) -> 1763698140402109979
A19: Nov-25 | B19: 45982 | C19: Pure, Jom | D19: 1763698140402109979 | E19: 202500000000032 | F19: La Belle50 ml. | G19: {=IF(F19<>"",INDEX(tb_MainDatabase[Barcode],MATCH(F19,tb_MainDatabase[Link],0)),"")} -> 8857128011058 | H19: {=IF(F19<>"",INDEX(tb_MainDatabase[Grand],MATCH(F19,tb_MainDatabase[Link],0)),"")} -> EDP | I19: {=IF(F19<>"",INDEX(tb_MainDatabase[Size],MATCH(F19,tb_MainDatabase[Link],0)),"")} -> 50 ml. | J19: 2 | K19: {=IF(F19<>"",INDEX(tb_MainDatabase[ราคา],MATCH(F19,tb_MainDatabase[Link],0)),"")*J19} -> 3780 | L19: 500 | M19: =K19-(L19*J19) -> 2780 | N19: =SUMIF($D$3:D3235,R19,$M$3:M3235) -> 0 | R19: =IF(COUNTIF(D$3:D19, D19)>1, 0, D19) -> 0
A20: Nov-25 | B20: 45982 | C20: Pure, Jom | D20: 1763698140402109979 | E20: 202500000000032 | F20: Senorita4 ml. | G20: {=IF(F20<>"",INDEX(tb_MainDatabase[Barcode],MATCH(F20,tb_MainDatabase[Link],0)),"")} -> 8857128012040 | H20: {=IF(F20<>"",INDEX(tb_MainDatabase[Grand],MATCH(F20,tb_MainDatabase[Link],0)),"")} -> EDP | I20: {=IF(F20<>"",INDEX(tb_MainDatabase[Size],MATCH(F20,tb_MainDatabase[Link],0)),"")} -> 4 ml. | J20: 1 | K20: {=IF(F20<>"",INDEX(tb_MainDatabase[ราคา],MATCH(F20,tb_MainDatabase[Link],0)),"")*J20} -> 179 | L20: 179 | M20: =K20-(L20*J20) -> 0 | N20: =SUMIF($D$3:D3236,R20,$M$3:M3236) -> 0 | R20: =IF(COUNTIF(D$3:D20, D20)>1, 0, D20) -> 0
A21: Nov-25 | B21: 45982 | C21: Pure, Jom | D21: 1763698140402109979 | E21: 202500000000032 | F21: Buoyant4 ml. | G21: {=IF(F21<>"",INDEX(tb_MainDatabase[Barcode],MATCH(F21,tb_MainDatabase[Link],0)),"")} -> 8857128012078 | H21: {=IF(F21<>"",INDEX(tb_MainDatabase[Grand],MATCH(F21,tb_MainDatabase[Link],0)),"")} -> EDP | I21: {=IF(F21<>"",INDEX(tb_MainDatabase[Size],MATCH(F21,tb_MainDatabase[Link],0)),"")} -> 4 ml. | J21: 1 | K21: {=IF(F21<>"",INDEX(tb_MainDatabase[ราคา],MATCH(F21,tb_MainDatabase[Link],0)),"")*J21} -> 179 | L21: 179 | M21: =K21-(L21*J21) -> 0 | N21: =SUMIF($D$3:D3237,R21,$M$3:M3237) -> 0 | R21: =IF(COUNTIF(D$3:D21, D21)>1, 0, D21) -> 0
A22: Nov-25 | B22: 45982 | C22: Pure, Jom | D22: 1763698140402109979 | E22: 202500000000032 | F22: Cloth BAG CYOCSize M | G22: {=IF(F22<>"",INDEX(tb_MainDatabase[Barcode],MATCH(F22,tb_MainDatabase[Link],0)),"")} -> 8857128012132 | H22: {=IF(F22<>"",INDEX(tb_MainDatabase[Grand],MATCH(F22,tb_MainDatabase[Link],0)),"")} -> Cloth | I22: {=IF(F22<>"",INDEX(tb_MainDatabase[Size],MATCH(F22,tb_MainDatabase[Link],0)),"")} -> Size M | J22: 1 | K22: {=IF(F22<>"",INDEX(tb_MainDatabase[ราคา],MATCH(F22,tb_MainDatabase[Link],0)),"")*J22} -> 0 | M22: =K22-(L22*J22) -> 0 | N22: =SUMIF($D$3:D3238,R22,$M$3:M3238) -> 0 | R22: =IF(COUNTIF(D$3:D22, D22)>1, 0, D22) -> 0
A23: Nov-25 | B23: 45982 | C23: Pure, Jom | D23: 1763698140402109979 | E23: 202500000000032 | F23: Tumbler CYOC (Dark Blue)Dark Blue | G23: {=IF(F23<>"",INDEX(tb_MainDatabase[Barcode],MATCH(F23,tb_MainDatabase[Link],0)),"")} -> 8857128012131 | H23: {=IF(F23<>"",INDEX(tb_MainDatabase[Grand],MATCH(F23,tb_MainDatabase[Link],0)),"")} -> Tumbler | I23: {=IF(F23<>"",INDEX(tb_MainDatabase[Size],MATCH(F23,tb_MainDatabase[Link],0)),"")} -> Dark Blue | J23: 1 | K23: {=IF(F23<>"",INDEX(tb_MainDatabase[ราคา],MATCH(F23,tb_MainDatabase[Link],0)),"")*J23} -> 0 | M23: =K23-(L23*J23) -> 0 | N23: =SUMIF($D$3:D3239,R23,$M$3:M3239) -> 0 | R23: =IF(COUNTIF(D$3:D23, D23)>1, 0, D23) -> 0
A24: Nov-25 | B24: 45982 | C24: Pure, Jom | D24: 1763723255137677400 | E24: 202500000000033 | F24: La Belle10 ml. | G24: {=IF(F24<>"",INDEX(tb_MainDatabase[Barcode],MATCH(F24,tb_MainDatabase[Link],0)),"")} -> 8857128012034 | H24: {=IF(F24<>"",INDEX(tb_MainDatabase[Grand],MATCH(F24,tb_MainDatabase[Link],0)),"")} -> EDP | I24: {=IF(F24<>"",INDEX(tb_MainDatabase[Size],MATCH(F24,tb_MainDatabase[Link],0)),"")} -> 10 ml. | J24: 1 | K24: {=IF(F24<>"",INDEX(tb_MainDatabase[ราคา],MATCH(F24,tb_MainDatabase[Link],0)),"")*J24} -> 450 | L24: 100 | M24: =K24-(L24*J24) -> 350 | N24: =SUMIF($D$3:D3240,R24,$M$3:M3240) -> 350 | O24: Cash | P24: 45982 | R24: =IF(COUNTIF(D$3:D24, D24)>1, 0, D24) -> 1763723255137677400
A25: Nov-25 | B25: 45982 | C25: Pure, Jom | D25: 1763723391005795009 | E25: 202500000000034 | F25: La Belle30 ml. | G25: {=IF(F25<>"",INDEX(tb_MainDatabase[Barcode],MATCH(F25,tb_MainDatabase[Link],0)),"")} -> 8857128011904 | H25: {=IF(F25<>"",INDEX(tb_MainDatabase[Grand],MATCH(F25,tb_MainDatabase[Link],0)),"")} -> EDP | I25: {=IF(F25<>"",INDEX(tb_MainDatabase[Size],MATCH(F25,tb_MainDatabase[Link],0)),"")} -> 30 ml. | J25: 1 | K25: {=IF(F25<>"",INDEX(tb_MainDatabase[ราคา],MATCH(F25,tb_MainDatabase[Link],0)),"")*J25} -> 1290 | L25: 300 | M25: =K25-(L25*J25) -> 990 | N25: =SUMIF($D$3:D3241,R25,$M$3:M3241) -> 990 | O25: K Shop | P25: 45982 | Q25: 0.75694444 | R25: =IF(COUNTIF(D$3:D25, D25)>1, 0, D25) -> 1763723391005795009
A26: Nov-25 | B26: 45982 | C26: Pure, Jom | D26: 1763723391005795009 | E26: 202500000000034 | F26: Senorita4 ml. | G26: {=IF(F26<>"",INDEX(tb_MainDatabase[Barcode],MATCH(F26,tb_MainDatabase[Link],0)),"")} -> 8857128012040 | H26: {=IF(F26<>"",INDEX(tb_MainDatabase[Grand],MATCH(F26,tb_MainDatabase[Link],0)),"")} -> EDP | I26: {=IF(F26<>"",INDEX(tb_MainDatabase[Size],MATCH(F26,tb_MainDatabase[Link],0)),"")} -> 4 ml. | J26: 1 | K26: {=IF(F26<>"",INDEX(tb_MainDatabase[ราคา],MATCH(F26,tb_MainDatabase[Link],0)),"")*J26} -> 179 | L26: 179 | M26: =K26-(L26*J26) -> 0 | N26: =SUMIF($D$3:D3242,R26,$M$3:M3242) -> 0 | R26: =IF(COUNTIF(D$3:D26, D26)>1, 0, D26) -> 0
A27: Nov-25 | B27: 45982 | C27: Pure, Jom | D27: 1763725916681766418 | E27: 202500000000035 | F27: Persist50 ml. | G27: {=IF(F27<>"",INDEX(tb_MainDatabase[Barcode],MATCH(F27,tb_MainDatabase[Link],0)),"")} -> 8857128011041 | H27: {=IF(F27<>"",INDEX(tb_MainDatabase[Grand],MATCH(F27,tb_MainDatabase[Link],0)),"")} -> EDP | I27: {=IF(F27<>"",INDEX(tb_MainDatabase[Size],MATCH(F27,tb_MainDatabase[Link],0)),"")} -> 50 ml. | J27: 1 | K27: {=IF(F27<>"",INDEX(tb_MainDatabase[ราคา],MATCH(F27,tb_MainDatabase[Link],0)),"")*J27} -> 1890 | L27: 500 | M27: =K27-(L27*J27) -> 1390 | N27: =SUMIF($D$3:D3243,R27,$M$3:M3243) -> 2780 | O27: K Shop Credit Card | P27: 45982 | Q27: 0.79930556 | R27: =IF(COUNTIF(D$3:D27, D27)>1, 0, D27) -> 1763725916681766418
A28: Nov-25 | B28: 45982 | C28: Pure, Jom | D28: 1763725916681766418 | E28: 202500000000035 | F28: Zeus50 ml. | G28: {=IF(F28<>"",INDEX(tb_MainDatabase[Barcode],MATCH(F28,tb_MainDatabase[Link],0)),"")} -> 8857128011027 | H28: {=IF(F28<>"",INDEX(tb_MainDatabase[Grand],MATCH(F28,tb_MainDatabase[Link],0)),"")} -> EDP | I28: {=IF(F28<>"",INDEX(tb_MainDatabase[Size],MATCH(F28,tb_MainDatabase[Link],0)),"")} -> 50 ml. | J28: 1 | K28: {=IF(F28<>"",INDEX(tb_MainDatabase[ราคา],MATCH(F28,tb_MainDatabase[Link],0)),"")*J28} -> 1890 | L28: 500 | M28: =K28-(L28*J28) -> 1390 | N28: =SUMIF($D$3:D3244,R28,$M$3:M3244) -> 0 | R28: =IF(COUNTIF(D$3:D28, D28)>1, 0, D28) -> 0
A29: Nov-25 | B29: 45982 | C29: Pure, Jom | D29: 1763725916681766418 | E29: 202500000000035 | F29: La Belle4 ml. | G29: {=IF(F29<>"",INDEX(tb_MainDatabase[Barcode],MATCH(F29,tb_MainDatabase[Link],0)),"")} -> 8857128012016 | H29: {=IF(F29<>"",INDEX(tb_MainDatabase[Grand],MATCH(F29,tb_MainDatabase[Link],0)),"")} -> EDP | I29: {=IF(F29<>"",INDEX(tb_MainDatabase[Size],MATCH(F29,tb_MainDatabase[Link],0)),"")} -> 4 ml. | J29: 1 | K29: {=IF(F29<>"",INDEX(tb_MainDatabase[ราคา],MATCH(F29,tb_MainDatabase[Link],0)),"")*J29} -> 179 | L29: 179 | M29: =K29-(L29*J29) -> 0 | N29: =SUMIF($D$3:D3245,R29,$M$3:M3245) -> 0 | R29: =IF(COUNTIF(D$3:D29, D29)>1, 0, D29) -> 0
A30: Nov-25 | B30: 45982 | C30: Pure, Jom | D30: 1763725916681766418 | E30: 202500000000035 | F30: Never Blue4 ml. | G30: {=IF(F30<>"",INDEX(tb_MainDatabase[Barcode],MATCH(F30,tb_MainDatabase[Link],0)),"")} -> 8857128012036 | H30: {=IF(F30<>"",INDEX(tb_MainDatabase[Grand],MATCH(F30,tb_MainDatabase[Link],0)),"")} -> EDP | I30: {=IF(F30<>"",INDEX(tb_MainDatabase[Size],MATCH(F30,tb_MainDatabase[Link],0)),"")} -> 4 ml. | J30: 1 | K30: {=IF(F30<>"",INDEX(tb_MainDatabase[ราคา],MATCH(F30,tb_MainDatabase[Link],0)),"")*J30} -> 179 | L30: 179 | M30: =K30-(L30*J30) -> 0 | N30: =SUMIF($D$3:D3246,R30,$M$3:M3246) -> 0 | R30: =IF(COUNTIF(D$3:D30, D30)>1, 0, D30) -> 0
A31: Nov-25 | B31: 45982 | C31: Pure, Jom | D31: 1763725916681766418 | E31: 202500000000035 | F31: Tumbler CYOC (White)White | G31: {=IF(F31<>"",INDEX(tb_MainDatabase[Barcode],MATCH(F31,tb_MainDatabase[Link],0)),"")} -> 8857128012130 | H31: {=IF(F31<>"",INDEX(tb_MainDatabase[Grand],MATCH(F31,tb_MainDatabase[Link],0)),"")} -> Tumbler | I31: {=IF(F31<>"",INDEX(tb_MainDatabase[Size],MATCH(F31,tb_MainDatabase[Link],0)),"")} -> White | J31: 1 | K31: {=IF(F31<>"",INDEX(tb_MainDatabase[ราคา],MATCH(F31,tb_MainDatabase[Link],0)),"")*J31} -> 0 | M31: =K31-(L31*J31) -> 0 | N31: =SUMIF($D$3:D3247,R31,$M$3:M3247) -> 0 | R31: =IF(COUNTIF(D$3:D31, D31)>1, 0, D31) -> 0
A32: Nov-25 | B32: 45983 | C32: Note, Jom | D32: 1763729894310594281 | E32: 202500000000036 | F32: La Belle30 ml. | G32: {=IF(F32<>"",INDEX(tb_MainDatabase[Barcode],MATCH(F32,tb_MainDatabase[Link],0)),"")} -> 8857128011904 | H32: {=IF(F32<>"",INDEX(tb_MainDatabase[Grand],MATCH(F32,tb_MainDatabase[Link],0)),"")} -> EDP | I32: {=IF(F32<>"",INDEX(tb_MainDatabase[Size],MATCH(F32,tb_MainDatabase[Link],0)),"")} -> 30 ml. | J32: 1 | K32: {=IF(F32<>"",INDEX(tb_MainDatabase[ราคา],MATCH(F32,tb_MainDatabase[Link],0)),"")*J32} -> 1290 | L32: 300 | M32: =K32-(L32*J32) -> 990 | N32: =SUMIF($D$3:D3248,R32,$M$3:M3248) -> 990 | O32: K Shop Credit Card | P32: 45983 | Q32: 0.45416667 | R32: =IF(COUNTIF(D$3:D32, D32)>1, 0, D32) -> 1763729894310594281
A33: Nov-25 | B33: 45983 | C33: Note, Jom | D33: 1763783729225970189 | E33: 202500000000037 | F33: Zeus50 ml. | G33: {=IF(F33<>"",INDEX(tb_MainDatabase[Barcode],MATCH(F33,tb_MainDatabase[Link],0)),"")} -> 8857128011027 | H33: {=IF(F33<>"",INDEX(tb_MainDatabase[Grand],MATCH(F33,tb_MainDatabase[Link],0)),"")} -> EDP | I33: {=IF(F33<>"",INDEX(tb_MainDatabase[Size],MATCH(F33,tb_MainDatabase[Link],0)),"")} -> 50 ml. | J33: 1 | K33: {=IF(F33<>"",INDEX(tb_MainDatabase[ราคา],MATCH(F33,tb_MainDatabase[Link],0)),"")*J33} -> 1890 | L33: 500 | M33: =K33-(L33*J33) -> 1390 | N33: =SUMIF($D$3:D3249,R33,$M$3:M3249) -> 2780 | O33: Cash | P33: 45983 | R33: =IF(COUNTIF(D$3:D33, D33)>1, 0, D33) -> 1763783729225970189
A34: Nov-25 | B34: 45983 | C34: Note, Jom | D34: 1763783729225970189 | E34: 202500000000037 | F34: Aqua50 ml. | G34: {=IF(F34<>"",INDEX(tb_MainDatabase[Barcode],MATCH(F34,tb_MainDatabase[Link],0)),"")} -> 8857128012018 | H34: {=IF(F34<>"",INDEX(tb_MainDatabase[Grand],MATCH(F34,tb_MainDatabase[Link],0)),"")} -> EDP | I34: {=IF(F34<>"",INDEX(tb_MainDatabase[Size],MATCH(F34,tb_MainDatabase[Link],0)),"")} -> 50 ml. | J34: 1 | K34: {=IF(F34<>"",INDEX(tb_MainDatabase[ราคา],MATCH(F34,tb_MainDatabase[Link],0)),"")*J34} -> 1890 | L34: 500 | M34: =K34-(L34*J34) -> 1390 | N34: =SUMIF($D$3:D3250,R34,$M$3:M3250) -> 0 | R34: =IF(COUNTIF(D$3:D34, D34)>1, 0, D34) -> 0
A35: Nov-25 | B35: 45983 | C35: Note, Jom | D35: 1763783729225970189 | E35: 202500000000037 | F35: Sicilia4 ml. | G35: {=IF(F35<>"",INDEX(tb_MainDatabase[Barcode],MATCH(F35,tb_MainDatabase[Link],0)),"")} -> 8857128012056 | H35: {=IF(F35<>"",INDEX(tb_MainDatabase[Grand],MATCH(F35,tb_MainDatabase[Link],0)),"")} -> EDP | I35: {=IF(F35<>"",INDEX(tb_MainDatabase[Size],MATCH(F35,tb_MainDatabase[Link],0)),"")} -> 4 ml. | J35: 1 | K35: {=IF(F35<>"",INDEX(tb_MainDatabase[ราคา],MATCH(F35,tb_MainDatabase[Link],0)),"")*J35} -> 179 | L35: 179 | M35: =K35-(L35*J35) -> 0 | N35: =SUMIF($D$3:D3251,R35,$M$3:M3251) -> 0 | R35: =IF(COUNTIF(D$3:D35, D35)>1, 0, D35) -> 0
A36: Nov-25 | B36: 45983 | C36: Note, Jom | D36: 1763783729225970189 | E36: 202500000000037 | F36: Tumbler CYOC (White)White | G36: {=IF(F36<>"",INDEX(tb_MainDatabase[Barcode],MATCH(F36,tb_MainDatabase[Link],0)),"")} -> 8857128012130 | H36: {=IF(F36<>"",INDEX(tb_MainDatabase[Grand],MATCH(F36,tb_MainDatabase[Link],0)),"")} -> Tumbler | I36: {=IF(F36<>"",INDEX(tb_MainDatabase[Size],MATCH(F36,tb_MainDatabase[Link],0)),"")} -> White | J36: 1 | K36: {=IF(F36<>"",INDEX(tb_MainDatabase[ราคา],MATCH(F36,tb_MainDatabase[Link],0)),"")*J36} -> 0 | M36: =K36-(L36*J36) -> 0 | N36: =SUMIF($D$3:D3252,R36,$M$3:M3252) -> 0 | R36: =IF(COUNTIF(D$3:D36, D36)>1, 0, D36) -> 0
A37: Nov-25 | B37: 45983 | C37: Note, Jom | D37: 1763790727877590536 | E37: 202500000000038 | F37: Never Blue50 ml. | G37: {=IF(F37<>"",INDEX(tb_MainDatabase[Barcode],MATCH(F37,tb_MainDatabase[Link],0)),"")} -> 8857128011287 | H37: {=IF(F37<>"",INDEX(tb_MainDatabase[Grand],MATCH(F37,tb_MainDatabase[Link],0)),"")} -> EDP | I37: {=IF(F37<>"",INDEX(tb_MainDatabase[Size],MATCH(F37,tb_MainDatabase[Link],0)),"")} -> 50 ml. | J37: 1 | K37: {=IF(F37<>"",INDEX(tb_MainDatabase[ราคา],MATCH(F37,tb_MainDatabase[Link],0)),"")*J37} -> 1890 | L37: 1890 | M37: =K37-(L37*J37) -> 0 | N37: =SUMIF($D$3:D3253,R37,$M$3:M3253) -> 0 | R37: =IF(COUNTIF(D$3:D37, D37)>1, 0, D37) -> 1763790727877590536
A38: Nov-25 | B38: 45983 | C38: Note, Jom | D38: 1763790727877590536 | E38: 202500000000038 | F38: Persist50 ml. | G38: {=IF(F38<>"",INDEX(tb_MainDatabase[Barcode],MATCH(F38,tb_MainDatabase[Link],0)),"")} -> 8857128011041 | H38: {=IF(F38<>"",INDEX(tb_MainDatabase[Grand],MATCH(F38,tb_MainDatabase[Link],0)),"")} -> EDP | I38: {=IF(F38<>"",INDEX(tb_MainDatabase[Size],MATCH(F38,tb_MainDatabase[Link],0)),"")} -> 50 ml. | J38: 1 | K38: {=IF(F38<>"",INDEX(tb_MainDatabase[ราคา],MATCH(F38,tb_MainDatabase[Link],0)),"")*J38} -> 1890 | L38: 1890 | M38: =K38-(L38*J38) -> 0 | N38: =SUMIF($D$3:D3254,R38,$M$3:M3254) -> 0 | R38: =IF(COUNTIF(D$3:D38, D38)>1, 0, D38) -> 0
A39: Nov-25 | B39: 45983 | C39: Note, Jom | D39: 1763799660948781545 | E39: 202500000000039 | F39: Persist50 ml. | G39: {=IF(F39<>"",INDEX(tb_MainDatabase[Barcode],MATCH(F39,tb_MainDatabase[Link],0)),"")} -> 8857128011041 | H39: {=IF(F39<>"",INDEX(tb_MainDatabase[Grand],MATCH(F39,tb_MainDatabase[Link],0)),"")} -> EDP | I39: {=IF(F39<>"",INDEX(tb_MainDatabase[Size],MATCH(F39,tb_MainDatabase[Link],0)),"")} -> 50 ml. | J39: 1 | K39: {=IF(F39<>"",INDEX(tb_MainDatabase[ราคา],MATCH(F39,tb_MainDatabase[Link],0)),"")*J39} -> 1890 | L39: 1890 | M39: =K39-(L39*J39) -> 0 | N39: =SUMIF($D$3:D3255,R39,$M$3:M3255) -> 0 | R39: =IF(COUNTIF(D$3:D39, D39)>1, 0, D39) -> 1763799660948781545
A40: Nov-25 | B40: 45983 | C40: Note, Jom | D40: 1763802160509215883 | E40: 202500000000041 | F40: Eden50 ml. | G40: {=IF(F40<>"",INDEX(tb_MainDatabase[Barcode],MATCH(F40,tb_MainDatabase[Link],0)),"")} -> 8857128011317 | H40: {=IF(F40<>"",INDEX(tb_MainDatabase[Grand],MATCH(F40,tb_MainDatabase[Link],0)),"")} -> EDP | I40: {=IF(F40<>"",INDEX(tb_MainDatabase[Size],MATCH(F40,tb_MainDatabase[Link],0)),"")} -> 50 ml. | J40: 1 | K40: {=IF(F40<>"",INDEX(tb_MainDatabase[ราคา],MATCH(F40,tb_MainDatabase[Link],0)),"")*J40} -> 1890 | L40: 1890 | M40: =K40-(L40*J40) -> 0 | N40: =SUMIF($D$3:D3256,R40,$M$3:M3256) -> 0 | R40: =IF(COUNTIF(D$3:D40, D40)>1, 0, D40) -> 1763802160509215883
A41: Nov-25 | B41: 45983 | C41: Note, Jom | D41: 1763802968002313855 | E41: 202500000000042 | F41: Sicilia50 ml. | G41: {=IF(F41<>"",INDEX(tb_MainDatabase[Barcode],MATCH(F41,tb_MainDatabase[Link],0)),"")} -> 8857128011140 | H41: {=IF(F41<>"",INDEX(tb_MainDatabase[Grand],MATCH(F41,tb_MainDatabase[Link],0)),"")} -> EDP | I41: {=IF(F41<>"",INDEX(tb_MainDatabase[Size],MATCH(F41,tb_MainDatabase[Link],0)),"")} -> 50 ml. | J41: 1 | K41: {=IF(F41<>"",INDEX(tb_MainDatabase[ราคา],MATCH(F41,tb_MainDatabase[Link],0)),"")*J41} -> 1890 | L41: 1890 | M41: =K41-(L41*J41) -> 0 | N41: =SUMIF($D$3:D3257,R41,$M$3:M3257) -> 0 | R41: =IF(COUNTIF(D$3:D41, D41)>1, 0, D41) -> 1763802968002313855
A42: Nov-25 | B42: 45983 | C42: Note, Jom | D42: 1763806808757836115 | E42: 202500000000043 | F42: Never Blue50 ml. | G42: {=IF(F42<>"",INDEX(tb_MainDatabase[Barcode],MATCH(F42,tb_MainDatabase[Link],0)),"")} -> 8857128011287 | H42: {=IF(F42<>"",INDEX(tb_MainDatabase[Grand],MATCH(F42,tb_MainDatabase[Link],0)),"")} -> EDP | I42: {=IF(F42<>"",INDEX(tb_MainDatabase[Size],MATCH(F42,tb_MainDatabase[Link],0)),"")} -> 50 ml. | J42: 1 | K42: {=IF(F42<>"",INDEX(tb_MainDatabase[ราคา],MATCH(F42,tb_MainDatabase[Link],0)),"")*J42} -> 1890 | L42: 1890 | M42: =K42-(L42*J42) -> 0 | N42: =SUMIF($D$3:D3258,R42,$M$3:M3258) -> 0 | R42: =IF(COUNTIF(D$3:D42, D42)>1, 0, D42) -> 1763806808757836115
A43: Nov-25 | B43: 45983 | C43: Note, Jom | D43: 1763807111406262295 | E43: 202500000000044 | F43: Dream Island50 ml. | G43: {=IF(F43<>"",INDEX(tb_MainDatabase[Barcode],MATCH(F43,tb_MainDatabase[Link],0)),"")} -> 8857128011300 | H43: {=IF(F43<>"",INDEX(tb_MainDatabase[Grand],MATCH(F43,tb_MainDatabase[Link],0)),"")} -> EDP | I43: {=IF(F43<>"",INDEX(tb_MainDatabase[Size],MATCH(F43,tb_MainDatabase[Link],0)),"")} -> 50 ml. | J43: 1 | K43: {=IF(F43<>"",INDEX(tb_MainDatabase[ราคา],MATCH(F43,tb_MainDatabase[Link],0)),"")*J43} -> 1890 | L43: 1890 | M43: =K43-(L43*J43) -> 0 | N43: =SUMIF($D$3:D3259,R43,$M$3:M3259) -> 0 | R43: =IF(COUNTIF(D$3:D43, D43)>1, 0, D43) -> 1763807111406262295
A44: Nov-25 | B44: 45983 | C44: Note, Jom | D44: 1763810382604201513 | E44: 202500000000045 | F44: Secret of Peach50 ml. | G44: {=IF(F44<>"",INDEX(tb_MainDatabase[Barcode],MATCH(F44,tb_MainDatabase[Link],0)),"")} -> 8857128011119 | H44: {=IF(F44<>"",INDEX(tb_MainDatabase[Grand],MATCH(F44,tb_MainDatabase[Link],0)),"")} -> EDP | I44: {=IF(F44<>"",INDEX(tb_MainDatabase[Size],MATCH(F44,tb_MainDatabase[Link],0)),"")} -> 50 ml. | J44: 1 | K44: {=IF(F44<>"",INDEX(tb_MainDatabase[ราคา],MATCH(F44,tb_MainDatabase[Link],0)),"")*J44} -> 1890 | L44: 500 | M44: =K44-(L44*J44) -> 1390 | N44: =SUMIF($D$3:D3260,R44,$M$3:M3260) -> 2780 | O44: K Shop | P44: 45983 | Q44: 0.76527778 | R44: =IF(COUNTIF(D$3:D44, D44)>1, 0, D44) -> 1763810382604201513
A45: Nov-25 | B45: 45983 | C45: Note, Jom | D45: 1763810382604201513 | E45: 202500000000045 | F45: Eden50 ml. | G45: {=IF(F45<>"",INDEX(tb_MainDatabase[Barcode],MATCH(F45,tb_MainDatabase[Link],0)),"")} -> 8857128011317 | H45: {=IF(F45<>"",INDEX(tb_MainDatabase[Grand],MATCH(F45,tb_MainDatabase[Link],0)),"")} -> EDP | I45: {=IF(F45<>"",INDEX(tb_MainDatabase[Size],MATCH(F45,tb_MainDatabase[Link],0)),"")} -> 50 ml. | J45: 1 | K45: {=IF(F45<>"",INDEX(tb_MainDatabase[ราคา],MATCH(F45,tb_MainDatabase[Link],0)),"")*J45} -> 1890 | L45: 500 | M45: =K45-(L45*J45) -> 1390 | N45: =SUMIF($D$3:D3261,R45,$M$3:M3261) -> 0 | R45: =IF(COUNTIF(D$3:D45, D45)>1, 0, D45) -> 0
A46: Nov-25 | B46: 45983 | C46: Note, Jom | D46: 1763810382604201513 | E46: 202500000000045 | F46: Tumbler CYOC (White)White | G46: {=IF(F46<>"",INDEX(tb_MainDatabase[Barcode],MATCH(F46,tb_MainDatabase[Link],0)),"")} -> 8857128012130 | H46: {=IF(F46<>"",INDEX(tb_MainDatabase[Grand],MATCH(F46,tb_MainDatabase[Link],0)),"")} -> Tumbler | I46: {=IF(F46<>"",INDEX(tb_MainDatabase[Size],MATCH(F46,tb_MainDatabase[Link],0)),"")} -> White | J46: 1 | K46: {=IF(F46<>"",INDEX(tb_MainDatabase[ราคา],MATCH(F46,tb_MainDatabase[Link],0)),"")*J46} -> 0 | M46: =K46-(L46*J46) -> 0 | N46: =SUMIF($D$3:D3262,R46,$M$3:M3262) -> 0 | R46: =IF(COUNTIF(D$3:D46, D46)>1, 0, D46) -> 0
A47: Nov-25 | B47: 45983 | C47: Note, Jom | D47: 1763810382604201513 | E47: 202500000000045 | F47: Cloth BAG CYOCSize M | G47: {=IF(F47<>"",INDEX(tb_MainDatabase[Barcode],MATCH(F47,tb_MainDatabase[Link],0)),"")} -> 8857128012132 | H47: {=IF(F47<>"",INDEX(tb_MainDatabase[Grand],MATCH(F47,tb_MainDatabase[Link],0)),"")} -> Cloth | I47: {=IF(F47<>"",INDEX(tb_MainDatabase[Size],MATCH(F47,tb_MainDatabase[Link],0)),"")} -> Size M | J47: 1 | K47: {=IF(F47<>"",INDEX(tb_MainDatabase[ราคา],MATCH(F47,tb_MainDatabase[Link],0)),"")*J47} -> 0 | M47: =K47-(L47*J47) -> 0 | N47: =SUMIF($D$3:D3263,R47,$M$3:M3263) -> 0 | R47: =IF(COUNTIF(D$3:D47, D47)>1, 0, D47) -> 0
A48: Nov-25 | B48: 45983 | C48: Note, Jom | D48: 1763812643253162831 | E48: 202500000000046 | F48: Sicilia30 ml. | G48: {=IF(F48<>"",INDEX(tb_MainDatabase[Barcode],MATCH(F48,tb_MainDatabase[Link],0)),"")} -> 8857128011911 | H48: {=IF(F48<>"",INDEX(tb_MainDatabase[Grand],MATCH(F48,tb_MainDatabase[Link],0)),"")} -> EDP | I48: {=IF(F48<>"",INDEX(tb_MainDatabase[Size],MATCH(F48,tb_MainDatabase[Link],0)),"")} -> 30 ml. | J48: 1 | K48: {=IF(F48<>"",INDEX(tb_MainDatabase[ราคา],MATCH(F48,tb_MainDatabase[Link],0)),"")*J48} -> 1290 | L48: 300 | M48: =K48-(L48*J48) -> 990 | N48: =SUMIF($D$3:D3264,R48,$M$3:M3264) -> 990 | O48: Cash | P48: 45983 | R48: =IF(COUNTIF(D$3:D48, D48)>1, 0, D48) -> 1763812643253162831
A49: Nov-25 | B49: 45983 | C49: Note, Jom | D49: 1763812928898240614 | E49: 202500000000047 | F49: Velvet Oud50 ml. | G49: {=IF(F49<>"",INDEX(tb_MainDatabase[Barcode],MATCH(F49,tb_MainDatabase[Link],0)),"")} -> 8857128011522 | H49: {=IF(F49<>"",INDEX(tb_MainDatabase[Grand],MATCH(F49,tb_MainDatabase[Link],0)),"")} -> EDP | I49: {=IF(F49<>"",INDEX(tb_MainDatabase[Size],MATCH(F49,tb_MainDatabase[Link],0)),"")} -> 50 ml. | J49: 1 | K49: {=IF(F49<>"",INDEX(tb_MainDatabase[ราคา],MATCH(F49,tb_MainDatabase[Link],0)),"")*J49} -> 1890 | L49: 500 | M49: =K49-(L49*J49) -> 1390 | N49: =SUMIF($D$3:D3265,R49,$M$3:M3265) -> 1390 | O49: K Shop | P49: 45983 | Q49: 0.83333333 | R49: =IF(COUNTIF(D$3:D49, D49)>1, 0, D49) -> 1763812928898240614
A50: Nov-25 | B50: 45983 | C50: Note, Jom | D50: 1763812928898240614 | E50: 202500000000047 | F50: Senorita4 ml. | G50: {=IF(F50<>"",INDEX(tb_MainDatabase[Barcode],MATCH(F50,tb_MainDatabase[Link],0)),"")} -> 8857128012040 | H50: {=IF(F50<>"",INDEX(tb_MainDatabase[Grand],MATCH(F50,tb_MainDatabase[Link],0)),"")} -> EDP | I50: {=IF(F50<>"",INDEX(tb_MainDatabase[Size],MATCH(F50,tb_MainDatabase[Link],0)),"")} -> 4 ml. | J50: 1 | K50: {=IF(F50<>"",INDEX(tb_MainDatabase[ราคา],MATCH(F50,tb_MainDatabase[Link],0)),"")*J50} -> 179 | L50: 179 | M50: =K50-(L50*J50) -> 0 | N50: =SUMIF($D$3:D3266,R50,$M$3:M3266) -> 0 | R50: =IF(COUNTIF(D$3:D50, D50)>1, 0, D50) -> 0
A51: Nov-25 | B51: 45984 | C51: Note, Jom | D51: 1763869083751892558 | E51: 202500000000048 | F51: Senorita50 ml. | G51: {=IF(F51<>"",INDEX(tb_MainDatabase[Barcode],MATCH(F51,tb_MainDatabase[Link],0)),"")} -> 8857128011171 | H51: {=IF(F51<>"",INDEX(tb_MainDatabase[Grand],MATCH(F51,tb_MainDatabase[Link],0)),"")} -> EDP | I51: {=IF(F51<>"",INDEX(tb_MainDatabase[Size],MATCH(F51,tb_MainDatabase[Link],0)),"")} -> 50 ml. | J51: 1 | K51: {=IF(F51<>"",INDEX(tb_MainDatabase[ราคา],MATCH(F51,tb_MainDatabase[Link],0)),"")*J51} -> 1890 | L51: 1890 | M51: =K51-(L51*J51) -> 0 | N51: =SUMIF($D$3:D3267,R51,$M$3:M3267) -> 0 | R51: =IF(COUNTIF(D$3:D51, D51)>1, 0, D51) -> 1763869083751892558
A52: Nov-25 | B52: 45984 | C52: Note, Jom | D52: 1763883038708874570 | E52: 202500000000049 | F52: Virgin X10 ml. | G52: {=IF(F52<>"",INDEX(tb_MainDatabase[Barcode],MATCH(F52,tb_MainDatabase[Link],0)),"")} -> 8857128012053 | H52: {=IF(F52<>"",INDEX(tb_MainDatabase[Grand],MATCH(F52,tb_MainDatabase[Link],0)),"")} -> EDP | I52: {=IF(F52<>"",INDEX(tb_MainDatabase[Size],MATCH(F52,tb_MainDatabase[Link],0)),"")} -> 10 ml. | J52: 1 | K52: {=IF(F52<>"",INDEX(tb_MainDatabase[ราคา],MATCH(F52,tb_MainDatabase[Link],0)),"")*J52} -> 450 | L52: 100 | M52: =K52-(L52*J52) -> 350 | N52: =SUMIF($D$3:D3268,R52,$M$3:M3268) -> 350 | O52: Cash | R52: =IF(COUNTIF(D$3:D52, D52)>1, 0, D52) -> 1763883038708874570
A53: Nov-25 | B53: 45984 | C53: Note, Jom | D53: 1763884283410106000 | E53: 202500000000050 | F53: La Belle50 ml. | G53: {=IF(F53<>"",INDEX(tb_MainDatabase[Barcode],MATCH(F53,tb_MainDatabase[Link],0)),"")} -> 8857128011058 | H53: {=IF(F53<>"",INDEX(tb_MainDatabase[Grand],MATCH(F53,tb_MainDatabase[Link],0)),"")} -> EDP | I53: {=IF(F53<>"",INDEX(tb_MainDatabase[Size],MATCH(F53,tb_MainDatabase[Link],0)),"")} -> 50 ml. | J53: 1 | K53: {=IF(F53<>"",INDEX(tb_MainDatabase[ราคา],MATCH(F53,tb_MainDatabase[Link],0)),"")*J53} -> 1890 | L53: 1890 | M53: =K53-(L53*J53) -> 0 | N53: =SUMIF($D$3:D3269,R53,$M$3:M3269) -> 0 | R53: =IF(COUNTIF(D$3:D53, D53)>1, 0, D53) -> 1763884283410106000
A54: Nov-25 | B54: 45984 | C54: Note, Jom | D54: 1763891067547785891 | E54: 202500000000051 | F54: Sicilia50 ml. | G54: {=IF(F54<>"",INDEX(tb_MainDatabase[Barcode],MATCH(F54,tb_MainDatabase[Link],0)),"")} -> 8857128011140 | H54: {=IF(F54<>"",INDEX(tb_MainDatabase[Grand],MATCH(F54,tb_MainDatabase[Link],0)),"")} -> EDP | I54: {=IF(F54<>"",INDEX(tb_MainDatabase[Size],MATCH(F54,tb_MainDatabase[Link],0)),"")} -> 50 ml. | J54: 1 | K54: {=IF(F54<>"",INDEX(tb_MainDatabase[ราคา],MATCH(F54,tb_MainDatabase[Link],0)),"")*J54} -> 1890 | L54: 1890 | M54: =K54-(L54*J54) -> 0 | N54: =SUMIF($D$3:D3270,R54,$M$3:M3270) -> 0 | R54: =IF(COUNTIF(D$3:D54, D54)>1, 0, D54) -> 1763891067547785891
A55: Nov-25 | B55: 45984 | C55: Note, Jom | D55: 1763892809736930343 | E55: 202500000000052 | F55: Sicilia50 ml. | G55: {=IF(F55<>"",INDEX(tb_MainDatabase[Barcode],MATCH(F55,tb_MainDatabase[Link],0)),"")} -> 8857128011140 | H55: {=IF(F55<>"",INDEX(tb_MainDatabase[Grand],MATCH(F55,tb_MainDatabase[Link],0)),"")} -> EDP | I55: {=IF(F55<>"",INDEX(tb_MainDatabase[Size],MATCH(F55,tb_MainDatabase[Link],0)),"")} -> 50 ml. | J55: 1 | K55: {=IF(F55<>"",INDEX(tb_MainDatabase[ราคา],MATCH(F55,tb_MainDatabase[Link],0)),"")*J55} -> 1890 | L55: 1890 | M55: =K55-(L55*J55) -> 0 | N55: =SUMIF($D$3:D3271,R55,$M$3:M3271) -> 0 | R55: =IF(COUNTIF(D$3:D55, D55)>1, 0, D55) -> 1763892809736930343
A56: Nov-25 | B56: 45984 | C56: Note, Jom | D56: 1763894693356926533 | E56: 202500000000053 | F56: Shadow De Bacci Light10 ml. | G56: {=IF(F56<>"",INDEX(tb_MainDatabase[Barcode],MATCH(F56,tb_MainDatabase[Link],0)),"")} -> 8857128012093 | H56: {=IF(F56<>"",INDEX(tb_MainDatabase[Grand],MATCH(F56,tb_MainDatabase[Link],0)),"")} -> EDP | I56: {=IF(F56<>"",INDEX(tb_MainDatabase[Size],MATCH(F56,tb_MainDatabase[Link],0)),"")} -> 10 ml. | J56: 1 | K56: {=IF(F56<>"",INDEX(tb_MainDatabase[ราคา],MATCH(F56,tb_MainDatabase[Link],0)),"")*J56} -> 450 | L56: 100 | M56: =K56-(L56*J56) -> 350 | N56: =SUMIF($D$3:D3272,R56,$M$3:M3272) -> 700 | O56: K Shop Credit Card | P56: 45984 | Q56: 0.77291667 | R56: =IF(COUNTIF(D$3:D56, D56)>1, 0, D56) -> 1763894693356926533
A57: Nov-25 | B57: 45984 | C57: Note, Jom | D57: 1763894693356926533 | E57: 202500000000053 | F57: Dionysus X10 ml. | G57: {=IF(F57<>"",INDEX(tb_MainDatabase[Barcode],MATCH(F57,tb_MainDatabase[Link],0)),"")} -> 8857128012087 | H57: {=IF(F57<>"",INDEX(tb_MainDatabase[Grand],MATCH(F57,tb_MainDatabase[Link],0)),"")} -> EDP | I57: {=IF(F57<>"",INDEX(tb_MainDatabase[Size],MATCH(F57,tb_MainDatabase[Link],0)),"")} -> 10 ml. | J57: 1 | K57: {=IF(F57<>"",INDEX(tb_MainDatabase[ราคา],MATCH(F57,tb_MainDatabase[Link],0)),"")*J57} -> 450 | L57: 100 | M57: =K57-(L57*J57) -> 350 | N57: =SUMIF($D$3:D3273,R57,$M$3:M3273) -> 0 | R57: =IF(COUNTIF(D$3:D57, D57)>1, 0, D57) -> 0
A58: Nov-25 | B58: 45988 | C58: Art | D58: 1764230008258999899 | E58: 202500000000055 | F58: Dream Island50 ml. | G58: {=IF(F58<>"",INDEX(tb_MainDatabase[Barcode],MATCH(F58,tb_MainDatabase[Link],0)),"")} -> 8857128011300 | H58: {=IF(F58<>"",INDEX(tb_MainDatabase[Grand],MATCH(F58,tb_MainDatabase[Link],0)),"")} -> EDP | I58: {=IF(F58<>"",INDEX(tb_MainDatabase[Size],MATCH(F58,tb_MainDatabase[Link],0)),"")} -> 50 ml. | J58: 1 | K58: {=IF(F58<>"",INDEX(tb_MainDatabase[ราคา],MATCH(F58,tb_MainDatabase[Link],0)),"")*J58} -> 1890 | L58: 500 | M58: =K58-(L58*J58) -> 1390 | N58: =SUMIF($D$3:D3274,R58,$M$3:M3274) -> 1390 | O58: Cash | R58: =IF(COUNTIF(D$3:D58, D58)>1, 0, D58) -> 1764230008258999899
A59: Nov-25 | B59: 45988 | C59: Art | D59: 1764230294991586025 | E59: 202500000000056 | F59: Dream Island50 ml. | G59: {=IF(F59<>"",INDEX(tb_MainDatabase[Barcode],MATCH(F59,tb_MainDatabase[Link],0)),"")} -> 8857128011300 | H59: {=IF(F59<>"",INDEX(tb_MainDatabase[Grand],MATCH(F59,tb_MainDatabase[Link],0)),"")} -> EDP | I59: {=IF(F59<>"",INDEX(tb_MainDatabase[Size],MATCH(F59,tb_MainDatabase[Link],0)),"")} -> 50 ml. | J59: 1 | K59: {=IF(F59<>"",INDEX(tb_MainDatabase[ราคา],MATCH(F59,tb_MainDatabase[Link],0)),"")*J59} -> 1890 | L59: 500 | M59: =K59-(L59*J59) -> 1390 | N59: =SUMIF($D$3:D3275,R59,$M$3:M3275) -> 1390 | O59: Cash | R59: =IF(COUNTIF(D$3:D59, D59)>1, 0, D59) -> 1764230294991586025
A60: Nov-25 | B60: 45988 | C60: Art | D60: 1764237425691914334 | E60: 202500000000057 | F60: Velvet Oud10 ml. | G60: {=IF(F60<>"",INDEX(tb_MainDatabase[Barcode],MATCH(F60,tb_MainDatabase[Link],0)),"")} -> 8857128012047 | H60: {=IF(F60<>"",INDEX(tb_MainDatabase[Grand],MATCH(F60,tb_MainDatabase[Link],0)),"")} -> EDP | I60: {=IF(F60<>"",INDEX(tb_MainDatabase[Size],MATCH(F60,tb_MainDatabase[Link],0)),"")} -> 10 ml. | J60: 1 | K60: {=IF(F60<>"",INDEX(tb_MainDatabase[ราคา],MATCH(F60,tb_MainDatabase[Link],0)),"")*J60} -> 450 | L60: 100 | M60: =K60-(L60*J60) -> 350 | N60: =SUMIF($D$3:D3276,R60,$M$3:M3276) -> 350 | O60: K Shop | P60: 45988 | Q60: 0.70625 | R60: =IF(COUNTIF(D$3:D60, D60)>1, 0, D60) -> 1764237425691914334
A61: Nov-25 | B61: 45988 | C61: Art | D61: 1764238487380852084 | E61: 202500000000058 | F61: Excalibur (EDP)50 ml. | G61: {=IF(F61<>"",INDEX(tb_MainDatabase[Barcode],MATCH(F61,tb_MainDatabase[Link],0)),"")} -> 8857128011133 | H61: {=IF(F61<>"",INDEX(tb_MainDatabase[Grand],MATCH(F61,tb_MainDatabase[Link],0)),"")} -> EDP | I61: {=IF(F61<>"",INDEX(tb_MainDatabase[Size],MATCH(F61,tb_MainDatabase[Link],0)),"")} -> 50 ml. | J61: 1 | K61: {=IF(F61<>"",INDEX(tb_MainDatabase[ราคา],MATCH(F61,tb_MainDatabase[Link],0)),"")*J61} -> 1890 | L61: 500 | M61: =K61-(L61*J61) -> 1390 | N61: =SUMIF($D$3:D3277,R61,$M$3:M3277) -> 1390 | O61: Cash | R61: =IF(COUNTIF(D$3:D61, D61)>1, 0, D61) -> 1764238487380852084
A62: Nov-25 | B62: 45989 | C62: Note | D62: 1764318318000319648 | E62: 202500000000059 | F62: Dream Island30 ml. | G62: {=IF(F62<>"",INDEX(tb_MainDatabase[Barcode],MATCH(F62,tb_MainDatabase[Link],0)),"")} -> 8857128011874 | H62: {=IF(F62<>"",INDEX(tb_MainDatabase[Grand],MATCH(F62,tb_MainDatabase[Link],0)),"")} -> EDP | I62: {=IF(F62<>"",INDEX(tb_MainDatabase[Size],MATCH(F62,tb_MainDatabase[Link],0)),"")} -> 30 ml. | J62: 1 | K62: {=IF(F62<>"",INDEX(tb_MainDatabase[ราคา],MATCH(F62,tb_MainDatabase[Link],0)),"")*J62} -> 1290 | L62: 300 | M62: =K62-(L62*J62) -> 990 | N62: =SUMIF($D$3:D3278,R62,$M$3:M3278) -> 990 | O62: Cash | R62: =IF(COUNTIF(D$3:D62, D62)>1, 0, D62) -> 1764318318000319648
A63: Nov-25 | B63: 45989 | C63: Note | D63: 1764326959945828424 | E63: 202500000000060 | F63: Vivid10 ml. | G63: {=IF(F63<>"",INDEX(tb_MainDatabase[Barcode],MATCH(F63,tb_MainDatabase[Link],0)),"")} -> 8857128012060 | H63: {=IF(F63<>"",INDEX(tb_MainDatabase[Grand],MATCH(F63,tb_MainDatabase[Link],0)),"")} -> EDP | I63: {=IF(F63<>"",INDEX(tb_MainDatabase[Size],MATCH(F63,tb_MainDatabase[Link],0)),"")} -> 10 ml. | J63: 1 | K63: {=IF(F63<>"",INDEX(tb_MainDatabase[ราคา],MATCH(F63,tb_MainDatabase[Link],0)),"")*J63} -> 450 | L63: 100 | M63: =K63-(L63*J63) -> 350 | N63: =SUMIF($D$3:D3279,R63,$M$3:M3279) -> 350 | O63: K Shop | P63: 45989 | Q63: 0.74166667 | R63: =IF(COUNTIF(D$3:D63, D63)>1, 0, D63) -> 1764326959945828424
A64: Nov-25 | B64: 45989 | C64: Note | D64: 1764340722685432661 | E64: 202500000000061 | F64: Sparkling Mandarin10 ml. | G64: {=IF(F64<>"",INDEX(tb_MainDatabase[Barcode],MATCH(F64,tb_MainDatabase[Link],0)),"")} -> 8857128012108 | H64: {=IF(F64<>"",INDEX(tb_MainDatabase[Grand],MATCH(F64,tb_MainDatabase[Link],0)),"")} -> EDP+ | I64: {=IF(F64<>"",INDEX(tb_MainDatabase[Size],MATCH(F64,tb_MainDatabase[Link],0)),"")} -> 10 ml. | J64: 1 | K64: {=IF(F64<>"",INDEX(tb_MainDatabase[ราคา],MATCH(F64,tb_MainDatabase[Link],0)),"")*J64} -> 650 | L64: 100 | M64: =K64-(L64*J64) -> 550 | N64: =SUMIF($D$3:D3280,R64,$M$3:M3280) -> 550 | O64: Cash | R64: =IF(COUNTIF(D$3:D64, D64)>1, 0, D64) -> 1764340722685432661
A65: Nov-25 | B65: 45990 | C65: Pure, Jom | D65: 1764388253563460775 | E65: 202500000000062 | F65: La Belle10 ml. | G65: {=IF(F65<>"",INDEX(tb_MainDatabase[Barcode],MATCH(F65,tb_MainDatabase[Link],0)),"")} -> 8857128012034 | H65: {=IF(F65<>"",INDEX(tb_MainDatabase[Grand],MATCH(F65,tb_MainDatabase[Link],0)),"")} -> EDP | I65: {=IF(F65<>"",INDEX(tb_MainDatabase[Size],MATCH(F65,tb_MainDatabase[Link],0)),"")} -> 10 ml. | J65: 1 | K65: {=IF(F65<>"",INDEX(tb_MainDatabase[ราคา],MATCH(F65,tb_MainDatabase[Link],0)),"")*J65} -> 450 | L65: 100 | M65: =K65-(L65*J65) -> 350 | N65: =SUMIF($D$3:D3281,R65,$M$3:M3281) -> 350 | O65: Cash | R65: =IF(COUNTIF(D$3:D65, D65)>1, 0, D65) -> 1764388253563460775
A66: Nov-25 | B66: 45990 | C66: Pure, Jom | D66: 1764397086039319702 | E66: 202500000000063 | F66: Sicilia10 ml. | G66: {=IF(F66<>"",INDEX(tb_MainDatabase[Barcode],MATCH(F66,tb_MainDatabase[Link],0)),"")} -> 8857128012055 | H66: {=IF(F66<>"",INDEX(tb_MainDatabase[Grand],MATCH(F66,tb_MainDatabase[Link],0)),"")} -> EDP | I66: {=IF(F66<>"",INDEX(tb_MainDatabase[Size],MATCH(F66,tb_MainDatabase[Link],0)),"")} -> 10 ml. | J66: 2 | K66: {=IF(F66<>"",INDEX(tb_MainDatabase[ราคา],MATCH(F66,tb_MainDatabase[Link],0)),"")*J66} -> 900 | L66: 100 | M66: =K66-(L66*J66) -> 700 | N66: =SUMIF($D$3:D3282,R66,$M$3:M3282) -> 1400 | O66: Cash | R66: =IF(COUNTIF(D$3:D66, D66)>1, 0, D66) -> 1764397086039319702
A67: Nov-25 | B67: 45990 | C67: Pure, Jom | D67: 1764397086039319702 | E67: 202500000000063 | F67: Persist10 ml. | G67: {=IF(F67<>"",INDEX(tb_MainDatabase[Barcode],MATCH(F67,tb_MainDatabase[Link],0)),"")} -> 8857128012042 | H67: {=IF(F67<>"",INDEX(tb_MainDatabase[Grand],MATCH(F67,tb_MainDatabase[Link],0)),"")} -> EDP | I67: {=IF(F67<>"",INDEX(tb_MainDatabase[Size],MATCH(F67,tb_MainDatabase[Link],0)),"")} -> 10 ml. | J67: 2 | K67: {=IF(F67<>"",INDEX(tb_MainDatabase[ราคา],MATCH(F67,tb_MainDatabase[Link],0)),"")*J67} -> 900 | L67: 100 | M67: =K67-(L67*J67) -> 700 | N67: =SUMIF($D$3:D3283,R67,$M$3:M3283) -> 0 | R67: =IF(COUNTIF(D$3:D67, D67)>1, 0, D67) -> 0
A68: Nov-25 | B68: 45990 | C68: Pure, Jom | D68: 1764398689587450364 | E68: 202500000000064 | F68: Vivid50 ml. | G68: {=IF(F68<>"",INDEX(tb_MainDatabase[Barcode],MATCH(F68,tb_MainDatabase[Link],0)),"")} -> 8857128011065 | H68: {=IF(F68<>"",INDEX(tb_MainDatabase[Grand],MATCH(F68,tb_MainDatabase[Link],0)),"")} -> EDP | I68: {=IF(F68<>"",INDEX(tb_MainDatabase[Size],MATCH(F68,tb_MainDatabase[Link],0)),"")} -> 50 ml. | J68: 1 | K68: {=IF(F68<>"",INDEX(tb_MainDatabase[ราคา],MATCH(F68,tb_MainDatabase[Link],0)),"")*J68} -> 1890 | L68: 500 | M68: =K68-(L68*J68) -> 1390 | N68: =SUMIF($D$3:D3284,R68,$M$3:M3284) -> 1740 | O68: K Shop | P68: 45990 | Q68: 0.57291667 | R68: =IF(COUNTIF(D$3:D68, D68)>1, 0, D68) -> 1764398689587450364
A69: Nov-25 | B69: 45990 | C69: Pure, Jom | D69: 1764398689587450364 | E69: 202500000000064 | F69: Excalibur (EDP)10 ml. | G69: {=IF(F69<>"",INDEX(tb_MainDatabase[Barcode],MATCH(F69,tb_MainDatabase[Link],0)),"")} -> 8857128012062 | H69: {=IF(F69<>"",INDEX(tb_MainDatabase[Grand],MATCH(F69,tb_MainDatabase[Link],0)),"")} -> EDP | I69: {=IF(F69<>"",INDEX(tb_MainDatabase[Size],MATCH(F69,tb_MainDatabase[Link],0)),"")} -> 10 ml. | J69: 1 | K69: {=IF(F69<>"",INDEX(tb_MainDatabase[ราคา],MATCH(F69,tb_MainDatabase[Link],0)),"")*J69} -> 450 | L69: 100 | M69: =K69-(L69*J69) -> 350 | N69: =SUMIF($D$3:D3285,R69,$M$3:M3285) -> 0 | R69: =IF(COUNTIF(D$3:D69, D69)>1, 0, D69) -> 0
A70: Nov-25 | B70: 45990 | C70: Pure, Jom | D70: 1764399121016707263 | E70: 202500000000065 | F70: La Belle10 ml. | G70: {=IF(F70<>"",INDEX(tb_MainDatabase[Barcode],MATCH(F70,tb_MainDatabase[Link],0)),"")} -> 8857128012034 | H70: {=IF(F70<>"",INDEX(tb_MainDatabase[Grand],MATCH(F70,tb_MainDatabase[Link],0)),"")} -> EDP | I70: {=IF(F70<>"",INDEX(tb_MainDatabase[Size],MATCH(F70,tb_MainDatabase[Link],0)),"")} -> 10 ml. | J70: 1 | K70: {=IF(F70<>"",INDEX(tb_MainDatabase[ราคา],MATCH(F70,tb_MainDatabase[Link],0)),"")*J70} -> 450 | L70: 100 | M70: =K70-(L70*J70) -> 350 | N70: =SUMIF($D$3:D3286,R70,$M$3:M3286) -> 350 | O70: K Shop | P70: 45990 | Q70: 0.57777778 | R70: =IF(COUNTIF(D$3:D70, D70)>1, 0, D70) -> 1764399121016707263
A71: Nov-25 | B71: 45990 | C71: Pure, Jom | D71: 1764402402207556688 | E71: 202500000000066 | F71: Blackest Black30 ml. | G71: {=IF(F71<>"",INDEX(tb_MainDatabase[Barcode],MATCH(F71,tb_MainDatabase[Link],0)),"")} -> 8857128012005 | H71: {=IF(F71<>"",INDEX(tb_MainDatabase[Grand],MATCH(F71,tb_MainDatabase[Link],0)),"")} -> EDP+ | I71: {=IF(F71<>"",INDEX(tb_MainDatabase[Size],MATCH(F71,tb_MainDatabase[Link],0)),"")} -> 30 ml. | J71: 1 | K71: {=IF(F71<>"",INDEX(tb_MainDatabase[ราคา],MATCH(F71,tb_MainDatabase[Link],0)),"")*J71} -> 1890 | L71: 200 | M71: =K71-(L71*J71) -> 1690 | N71: =SUMIF($D$3:D3287,R71,$M$3:M3287) -> 1690 | O71: K Shop | P71: 45990 | Q71: 0.61736111 | R71: =IF(COUNTIF(D$3:D71, D71)>1, 0, D71) -> 1764402402207556688
A72: Nov-25 | B72: 45990 | C72: Pure, Jom | D72: 1764404995826997065 | E72: 202500000000067 | F72: Velvet Oud50 ml. | G72: {=IF(F72<>"",INDEX(tb_MainDatabase[Barcode],MATCH(F72,tb_MainDatabase[Link],0)),"")} -> 8857128011522 | H72: {=IF(F72<>"",INDEX(tb_MainDatabase[Grand],MATCH(F72,tb_MainDatabase[Link],0)),"")} -> EDP | I72: {=IF(F72<>"",INDEX(tb_MainDatabase[Size],MATCH(F72,tb_MainDatabase[Link],0)),"")} -> 50 ml. | J72: 1 | K72: {=IF(F72<>"",INDEX(tb_MainDatabase[ราคา],MATCH(F72,tb_MainDatabase[Link],0)),"")*J72} -> 1890 | L72: 500 | M72: =K72-(L72*J72) -> 1390 | N72: =SUMIF($D$3:D3288,R72,$M$3:M3288) -> 2780 | O72: K Shop Credit Card | P72: 45990 | Q72: 0.63958333 | R72: =IF(COUNTIF(D$3:D72, D72)>1, 0, D72) -> 1764404995826997065
A73: Nov-25 | B73: 45990 | C73: Pure, Jom | D73: 1764404995826997065 | E73: 202500000000067 | F73: Senorita50 ml. | G73: {=IF(F73<>"",INDEX(tb_MainDatabase[Barcode],MATCH(F73,tb_MainDatabase[Link],0)),"")} -> 8857128011171 | H73: {=IF(F73<>"",INDEX(tb_MainDatabase[Grand],MATCH(F73,tb_MainDatabase[Link],0)),"")} -> EDP | I73: {=IF(F73<>"",INDEX(tb_MainDatabase[Size],MATCH(F73,tb_MainDatabase[Link],0)),"")} -> 50 ml. | J73: 1 | K73: {=IF(F73<>"",INDEX(tb_MainDatabase[ราคา],MATCH(F73,tb_MainDatabase[Link],0)),"")*J73} -> 1890 | L73: 500 | M73: =K73-(L73*J73) -> 1390 | N73: =SUMIF($D$3:D3289,R73,$M$3:M3289) -> 0 | R73: =IF(COUNTIF(D$3:D73, D73)>1, 0, D73) -> 0
A74: Nov-25 | B74: 45990 | C74: Pure, Jom | D74: 1764404995826997065 | E74: 202500000000067 | F74: Sicilia4 ml. | G74: {=IF(F74<>"",INDEX(tb_MainDatabase[Barcode],MATCH(F74,tb_MainDatabase[Link],0)),"")} -> 8857128012056 | H74: {=IF(F74<>"",INDEX(tb_MainDatabase[Grand],MATCH(F74,tb_MainDatabase[Link],0)),"")} -> EDP | I74: {=IF(F74<>"",INDEX(tb_MainDatabase[Size],MATCH(F74,tb_MainDatabase[Link],0)),"")} -> 4 ml. | J74: 1 | K74: {=IF(F74<>"",INDEX(tb_MainDatabase[ราคา],MATCH(F74,tb_MainDatabase[Link],0)),"")*J74} -> 179 | L74: 179 | M74: =K74-(L74*J74) -> 0 | N74: =SUMIF($D$3:D3290,R74,$M$3:M3290) -> 0 | R74: =IF(COUNTIF(D$3:D74, D74)>1, 0, D74) -> 0
A75: Nov-25 | B75: 45990 | C75: Pure, Jom | D75: 1764404995826997065 | E75: 202500000000067 | F75: Tumbler CYOC (White)White | G75: {=IF(F75<>"",INDEX(tb_MainDatabase[Barcode],MATCH(F75,tb_MainDatabase[Link],0)),"")} -> 8857128012130 | H75: {=IF(F75<>"",INDEX(tb_MainDatabase[Grand],MATCH(F75,tb_MainDatabase[Link],0)),"")} -> Tumbler | I75: {=IF(F75<>"",INDEX(tb_MainDatabase[Size],MATCH(F75,tb_MainDatabase[Link],0)),"")} -> White | J75: 1 | K75: {=IF(F75<>"",INDEX(tb_MainDatabase[ราคา],MATCH(F75,tb_MainDatabase[Link],0)),"")*J75} -> 0 | M75: =K75-(L75*J75) -> 0 | N75: =SUMIF($D$3:D3291,R75,$M$3:M3291) -> 0 | R75: =IF(COUNTIF(D$3:D75, D75)>1, 0, D75) -> 0
A76: Nov-25 | B76: 45990 | C76: Pure, Jom | D76: 1764404995826997065 | E76: 202500000000067 | F76: Cloth BAG CYOCSize M | G76: {=IF(F76<>"",INDEX(tb_MainDatabase[Barcode],MATCH(F76,tb_MainDatabase[Link],0)),"")} -> 8857128012132 | H76: {=IF(F76<>"",INDEX(tb_MainDatabase[Grand],MATCH(F76,tb_MainDatabase[Link],0)),"")} -> Cloth | I76: {=IF(F76<>"",INDEX(tb_MainDatabase[Size],MATCH(F76,tb_MainDatabase[Link],0)),"")} -> Size M | J76: 1 | K76: {=IF(F76<>"",INDEX(tb_MainDatabase[ราคา],MATCH(F76,tb_MainDatabase[Link],0)),"")*J76} -> 0 | M76: =K76-(L76*J76) -> 0 | N76: =SUMIF($D$3:D3292,R76,$M$3:M3292) -> 0 | R76: =IF(COUNTIF(D$3:D76, D76)>1, 0, D76) -> 0
A77: Nov-25 | B77: 45990 | C77: Pure, Jom | D77: 1764406266946844441 | E77: 202500000000068 | F77: Aqua50 ml. | G77: {=IF(F77<>"",INDEX(tb_MainDatabase[Barcode],MATCH(F77,tb_MainDatabase[Link],0)),"")} -> 8857128012018 | H77: {=IF(F77<>"",INDEX(tb_MainDatabase[Grand],MATCH(F77,tb_MainDatabase[Link],0)),"")} -> EDP | I77: {=IF(F77<>"",INDEX(tb_MainDatabase[Size],MATCH(F77,tb_MainDatabase[Link],0)),"")} -> 50 ml. | J77: 1 | K77: {=IF(F77<>"",INDEX(tb_MainDatabase[ราคา],MATCH(F77,tb_MainDatabase[Link],0)),"")*J77} -> 1890 | L77: 500 | M77: =K77-(L77*J77) -> 1390 | N77: =SUMIF($D$3:D3293,R77,$M$3:M3293) -> 2090 | O77: Cash | R77: =IF(COUNTIF(D$3:D77, D77)>1, 0, D77) -> 1764406266946844441
A78: Nov-25 | B78: 45990 | C78: Pure, Jom | D78: 1764406266946844441 | E78: 202500000000068 | F78: La Belle10 ml. | G78: {=IF(F78<>"",INDEX(tb_MainDatabase[Barcode],MATCH(F78,tb_MainDatabase[Link],0)),"")} -> 8857128012034 | H78: {=IF(F78<>"",INDEX(tb_MainDatabase[Grand],MATCH(F78,tb_MainDatabase[Link],0)),"")} -> EDP | I78: {=IF(F78<>"",INDEX(tb_MainDatabase[Size],MATCH(F78,tb_MainDatabase[Link],0)),"")} -> 10 ml. | J78: 1 | K78: {=IF(F78<>"",INDEX(tb_MainDatabase[ราคา],MATCH(F78,tb_MainDatabase[Link],0)),"")*J78} -> 450 | L78: 100 | M78: =K78-(L78*J78) -> 350 | N78: =SUMIF($D$3:D3294,R78,$M$3:M3294) -> 0 | R78: =IF(COUNTIF(D$3:D78, D78)>1, 0, D78) -> 0
A79: Nov-25 | B79: 45990 | C79: Pure, Jom | D79: 1764406266946844441 | E79: 202500000000068 | F79: Secret of Peach10 ml. | G79: {=IF(F79<>"",INDEX(tb_MainDatabase[Barcode],MATCH(F79,tb_MainDatabase[Link],0)),"")} -> 8857128012037 | H79: {=IF(F79<>"",INDEX(tb_MainDatabase[Grand],MATCH(F79,tb_MainDatabase[Link],0)),"")} -> EDP | I79: {=IF(F79<>"",INDEX(tb_MainDatabase[Size],MATCH(F79,tb_MainDatabase[Link],0)),"")} -> 10 ml. | J79: 1 | K79: {=IF(F79<>"",INDEX(tb_MainDatabase[ราคา],MATCH(F79,tb_MainDatabase[Link],0)),"")*J79} -> 450 | L79: 100 | M79: =K79-(L79*J79) -> 350 | N79: =SUMIF($D$3:D3295,R79,$M$3:M3295) -> 0 | R79: =IF(COUNTIF(D$3:D79, D79)>1, 0, D79) -> 0
A80: Nov-25 | B80: 45990 | C80: Pure, Jom | D80: 1764406266946844441 | E80: 202500000000068 | F80: Cloth BAG CYOCSize M | G80: {=IF(F80<>"",INDEX(tb_MainDatabase[Barcode],MATCH(F80,tb_MainDatabase[Link],0)),"")} -> 8857128012132 | H80: {=IF(F80<>"",INDEX(tb_MainDatabase[Grand],MATCH(F80,tb_MainDatabase[Link],0)),"")} -> Cloth | I80: {=IF(F80<>"",INDEX(tb_MainDatabase[Size],MATCH(F80,tb_MainDatabase[Link],0)),"")} -> Size M | J80: 1 | K80: {=IF(F80<>"",INDEX(tb_MainDatabase[ราคา],MATCH(F80,tb_MainDatabase[Link],0)),"")*J80} -> 0 | M80: =K80-(L80*J80) -> 0 | N80: =SUMIF($D$3:D3296,R80,$M$3:M3296) -> 0 | R80: =IF(COUNTIF(D$3:D80, D80)>1, 0, D80) -> 0
A81: Nov-25 | B81: 45990 | C81: Pure, Jom | D81: 1764406918276883884 | E81: 202500000000069 | F81: Aqua50 ml. | G81: {=IF(F81<>"",INDEX(tb_MainDatabase[Barcode],MATCH(F81,tb_MainDatabase[Link],0)),"")} -> 8857128012018 | H81: {=IF(F81<>"",INDEX(tb_MainDatabase[Grand],MATCH(F81,tb_MainDatabase[Link],0)),"")} -> EDP | I81: {=IF(F81<>"",INDEX(tb_MainDatabase[Size],MATCH(F81,tb_MainDatabase[Link],0)),"")} -> 50 ml. | J81: 1 | K81: {=IF(F81<>"",INDEX(tb_MainDatabase[ราคา],MATCH(F81,tb_MainDatabase[Link],0)),"")*J81} -> 1890 | L81: 500 | M81: =K81-(L81*J81) -> 1390 | N81: =SUMIF($D$3:D3297,R81,$M$3:M3297) -> 1390 | O81: Cash | R81: =IF(COUNTIF(D$3:D81, D81)>1, 0, D81) -> 1764406918276883884
A82: Nov-25 | B82: 45990 | C82: Pure, Jom | D82: 1764411942432717171 | E82: 202500000000070 | F82: Gambling34+3550 ml. | G82: {=IF(F82<>"",INDEX(tb_MainDatabase[Barcode],MATCH(F82,tb_MainDatabase[Link],0)),"")} -> 8857128011591 | H82: {=IF(F82<>"",INDEX(tb_MainDatabase[Grand],MATCH(F82,tb_MainDatabase[Link],0)),"")} -> PARFUM | I82: {=IF(F82<>"",INDEX(tb_MainDatabase[Size],MATCH(F82,tb_MainDatabase[Link],0)),"")} -> 50 ml. | J82: 1 | K82: {=IF(F82<>"",INDEX(tb_MainDatabase[ราคา],MATCH(F82,tb_MainDatabase[Link],0)),"")*J82} -> 3040 | L82: 450 | M82: =K82-(L82*J82) -> 2590 | N82: =SUMIF($D$3:D3298,R82,$M$3:M3298) -> 2590 | O82: K Shop Credit Card | P82: 45990 | Q82: 0.72638889 | R82: =IF(COUNTIF(D$3:D82, D82)>1, 0, D82) -> 1764411942432717171
A83: Nov-25 | B83: 45990 | C83: Pure, Jom | D83: 1764411942432717171 | E83: 202500000000070 | F83: Never Blue4 ml. | G83: {=IF(F83<>"",INDEX(tb_MainDatabase[Barcode],MATCH(F83,tb_MainDatabase[Link],0)),"")} -> 8857128012036 | H83: {=IF(F83<>"",INDEX(tb_MainDatabase[Grand],MATCH(F83,tb_MainDatabase[Link],0)),"")} -> EDP | I83: {=IF(F83<>"",INDEX(tb_MainDatabase[Size],MATCH(F83,tb_MainDatabase[Link],0)),"")} -> 4 ml. | J83: 1 | K83: {=IF(F83<>"",INDEX(tb_MainDatabase[ราคา],MATCH(F83,tb_MainDatabase[Link],0)),"")*J83} -> 179 | L83: 179 | M83: =K83-(L83*J83) -> 0 | N83: =SUMIF($D$3:D3299,R83,$M$3:M3299) -> 0 | R83: =IF(COUNTIF(D$3:D83, D83)>1, 0, D83) -> 0
A84: Nov-25 | B84: 45990 | C84: Pure, Jom | D84: 1764411942432717171 | E84: 202500000000070 | F84: Cloth BAG CYOCSize M | G84: {=IF(F84<>"",INDEX(tb_MainDatabase[Barcode],MATCH(F84,tb_MainDatabase[Link],0)),"")} -> 8857128012132 | H84: {=IF(F84<>"",INDEX(tb_MainDatabase[Grand],MATCH(F84,tb_MainDatabase[Link],0)),"")} -> Cloth | I84: {=IF(F84<>"",INDEX(tb_MainDatabase[Size],MATCH(F84,tb_MainDatabase[Link],0)),"")} -> Size M | J84: 1 | K84: {=IF(F84<>"",INDEX(tb_MainDatabase[ราคา],MATCH(F84,tb_MainDatabase[Link],0)),"")*J84} -> 0 | M84: =K84-(L84*J84) -> 0 | N84: =SUMIF($D$3:D3300,R84,$M$3:M3300) -> 0 | R84: =IF(COUNTIF(D$3:D84, D84)>1, 0, D84) -> 0
A85: Nov-25 | B85: 45990 | C85: Pure, Jom | D85: 1764411942432717171 | E85: 202500000000070 | F85: Tumbler CYOC (Dark Blue)Dark Blue | G85: {=IF(F85<>"",INDEX(tb_MainDatabase[Barcode],MATCH(F85,tb_MainDatabase[Link],0)),"")} -> 8857128012131 | H85: {=IF(F85<>"",INDEX(tb_MainDatabase[Grand],MATCH(F85,tb_MainDatabase[Link],0)),"")} -> Tumbler | I85: {=IF(F85<>"",INDEX(tb_MainDatabase[Size],MATCH(F85,tb_MainDatabase[Link],0)),"")} -> Dark Blue | J85: 1 | K85: {=IF(F85<>"",INDEX(tb_MainDatabase[ราคา],MATCH(F85,tb_MainDatabase[Link],0)),"")*J85} -> 0 | M85: =K85-(L85*J85) -> 0 | N85: =SUMIF($D$3:D3301,R85,$M$3:M3301) -> 0 | R85: =IF(COUNTIF(D$3:D85, D85)>1, 0, D85) -> 0
A86: Nov-25 | B86: 45990 | C86: Pure, Jom | D86: 1764414366203994028 | E86: 202500000000071 | F86: Aqua50 ml. | G86: {=IF(F86<>"",INDEX(tb_MainDatabase[Barcode],MATCH(F86,tb_MainDatabase[Link],0)),"")} -> 8857128012018 | H86: {=IF(F86<>"",INDEX(tb_MainDatabase[Grand],MATCH(F86,tb_MainDatabase[Link],0)),"")} -> EDP | I86: {=IF(F86<>"",INDEX(tb_MainDatabase[Size],MATCH(F86,tb_MainDatabase[Link],0)),"")} -> 50 ml. | J86: 1 | K86: {=IF(F86<>"",INDEX(tb_MainDatabase[ราคา],MATCH(F86,tb_MainDatabase[Link],0)),"")*J86} -> 1890 | L86: 500 | M86: =K86-(L86*J86) -> 1390 | N86: =SUMIF($D$3:D3302,R86,$M$3:M3302) -> 1390 | O86: K Shop Credit Card | P86: 45990 | Q86: 0.75416667 | R86: =IF(COUNTIF(D$3:D86, D86)>1, 0, D86) -> 1764414366203994028
A87: Nov-25 | B87: 45990 | C87: Pure, Jom | D87: 1764415666661323356 | E87: 202500000000072 | F87: Velvet Oud30 ml. | G87: {=IF(F87<>"",INDEX(tb_MainDatabase[Barcode],MATCH(F87,tb_MainDatabase[Link],0)),"")} -> 8857128012048 | H87: {=IF(F87<>"",INDEX(tb_MainDatabase[Grand],MATCH(F87,tb_MainDatabase[Link],0)),"")} -> EDP | I87: {=IF(F87<>"",INDEX(tb_MainDatabase[Size],MATCH(F87,tb_MainDatabase[Link],0)),"")} -> 30 ml. | J87: 1 | K87: {=IF(F87<>"",INDEX(tb_MainDatabase[ราคา],MATCH(F87,tb_MainDatabase[Link],0)),"")*J87} -> 1290 | L87: 300 | M87: =K87-(L87*J87) -> 990 | N87: =SUMIF($D$3:D3303,R87,$M$3:M3303) -> 990 | O87: Cash | R87: =IF(COUNTIF(D$3:D87, D87)>1, 0, D87) -> 1764415666661323356
A88: Nov-25 | B88: 45991 | C88: Note, Jom | D88: 1764477798591579988 | E88: 202500000000073 | F88: Never Blue10 ml. | G88: {=IF(F88<>"",INDEX(tb_MainDatabase[Barcode],MATCH(F88,tb_MainDatabase[Link],0)),"")} -> 8857128012035 | H88: {=IF(F88<>"",INDEX(tb_MainDatabase[Grand],MATCH(F88,tb_MainDatabase[Link],0)),"")} -> EDP | I88: {=IF(F88<>"",INDEX(tb_MainDatabase[Size],MATCH(F88,tb_MainDatabase[Link],0)),"")} -> 10 ml. | J88: 1 | K88: {=IF(F88<>"",INDEX(tb_MainDatabase[ราคา],MATCH(F88,tb_MainDatabase[Link],0)),"")*J88} -> 450 | L88: 100 | M88: =K88-(L88*J88) -> 350 | N88: =SUMIF($D$3:D3304,R88,$M$3:M3304) -> 700 | O88: Cash | R88: =IF(COUNTIF(D$3:D88, D88)>1, 0, D88) -> 1764477798591579988
A89: Nov-25 | B89: 45991 | C89: Note, Jom | D89: 1764477798591579988 | E89: 202500000000073 | F89: Persist10 ml. | G89: {=IF(F89<>"",INDEX(tb_MainDatabase[Barcode],MATCH(F89,tb_MainDatabase[Link],0)),"")} -> 8857128012042 | H89: {=IF(F89<>"",INDEX(tb_MainDatabase[Grand],MATCH(F89,tb_MainDatabase[Link],0)),"")} -> EDP | I89: {=IF(F89<>"",INDEX(tb_MainDatabase[Size],MATCH(F89,tb_MainDatabase[Link],0)),"")} -> 10 ml. | J89: 1 | K89: {=IF(F89<>"",INDEX(tb_MainDatabase[ราคา],MATCH(F89,tb_MainDatabase[Link],0)),"")*J89} -> 450 | L89: 100 | M89: =K89-(L89*J89) -> 350 | N89: =SUMIF($D$3:D3305,R89,$M$3:M3305) -> 0 | R89: =IF(COUNTIF(D$3:D89, D89)>1, 0, D89) -> 0
A90: Nov-25 | B90: 45991 | C90: Note, Jom | D90: 1764486131037281361 | E90: 202500000000074 | F90: Secret of Peach10 ml. | G90: {=IF(F90<>"",INDEX(tb_MainDatabase[Barcode],MATCH(F90,tb_MainDatabase[Link],0)),"")} -> 8857128012037 | H90: {=IF(F90<>"",INDEX(tb_MainDatabase[Grand],MATCH(F90,tb_MainDatabase[Link],0)),"")} -> EDP | I90: {=IF(F90<>"",INDEX(tb_MainDatabase[Size],MATCH(F90,tb_MainDatabase[Link],0)),"")} -> 10 ml. | J90: 1 | K90: {=IF(F90<>"",INDEX(tb_MainDatabase[ราคา],MATCH(F90,tb_MainDatabase[Link],0)),"")*J90} -> 450 | L90: 100 | M90: =K90-(L90*J90) -> 350 | N90: =SUMIF($D$3:D3306,R90,$M$3:M3306) -> 350 | O90: Cash | R90: =IF(COUNTIF(D$3:D90, D90)>1, 0, D90) -> 1764486131037281361
A91: Nov-25 | B91: 45991 | C91: Note, Jom | D91: 1764500422764584323 | E91: 202500000000075 | F91: Dream Island50 ml. | G91: {=IF(F91<>"",INDEX(tb_MainDatabase[Barcode],MATCH(F91,tb_MainDatabase[Link],0)),"")} -> 8857128011300 | H91: {=IF(F91<>"",INDEX(tb_MainDatabase[Grand],MATCH(F91,tb_MainDatabase[Link],0)),"")} -> EDP | I91: {=IF(F91<>"",INDEX(tb_MainDatabase[Size],MATCH(F91,tb_MainDatabase[Link],0)),"")} -> 50 ml. | J91: 1 | K91: {=IF(F91<>"",INDEX(tb_MainDatabase[ราคา],MATCH(F91,tb_MainDatabase[Link],0)),"")*J91} -> 1890 | L91: 500 | M91: =K91-(L91*J91) -> 1390 | N91: =SUMIF($D$3:D3307,R91,$M$3:M3307) -> 1390 | O91: K Shop | P91: 45991 | Q91: 0.75069444 | R91: =IF(COUNTIF(D$3:D91, D91)>1, 0, D91) -> 1764500422764584323
A92: Nov-25 | B92: 45991 | C92: Note, Jom | D92: 1764502280937700237 | E92: 202500000000076 | F92: La Belle50 ml. | G92: {=IF(F92<>"",INDEX(tb_MainDatabase[Barcode],MATCH(F92,tb_MainDatabase[Link],0)),"")} -> 8857128011058 | H92: {=IF(F92<>"",INDEX(tb_MainDatabase[Grand],MATCH(F92,tb_MainDatabase[Link],0)),"")} -> EDP | I92: {=IF(F92<>"",INDEX(tb_MainDatabase[Size],MATCH(F92,tb_MainDatabase[Link],0)),"")} -> 50 ml. | J92: 1 | K92: {=IF(F92<>"",INDEX(tb_MainDatabase[ราคา],MATCH(F92,tb_MainDatabase[Link],0)),"")*J92} -> 1890 | L92: 500 | M92: =K92-(L92*J92) -> 1390 | N92: =SUMIF($D$3:D3308,R92,$M$3:M3308) -> 1390 | O92: K Shop | P92: 45991 | Q92: 0.77152778 | R92: =IF(COUNTIF(D$3:D92, D92)>1, 0, D92) -> 1764502280937700237
A93: Nov-25 | B93: 45991 | C93: Note, Jom | D93: 1764509115918935794 | E93: 202500000000077 | F93: Excalibur (EDP)10 ml. | G93: {=IF(F93<>"",INDEX(tb_MainDatabase[Barcode],MATCH(F93,tb_MainDatabase[Link],0)),"")} -> 8857128012062 | H93: {=IF(F93<>"",INDEX(tb_MainDatabase[Grand],MATCH(F93,tb_MainDatabase[Link],0)),"")} -> EDP | I93: {=IF(F93<>"",INDEX(tb_MainDatabase[Size],MATCH(F93,tb_MainDatabase[Link],0)),"")} -> 10 ml. | J93: 1 | K93: {=IF(F93<>"",INDEX(tb_MainDatabase[ราคา],MATCH(F93,tb_MainDatabase[Link],0)),"")*J93} -> 450 | L93: 100 | M93: =K93-(L93*J93) -> 350 | N93: =SUMIF($D$3:D3309,R93,$M$3:M3309) -> 350 | O93: K Shop | P93: 45991 | Q93: 0.85069444 | R93: =IF(COUNTIF(D$3:D93, D93)>1, 0, D93) -> 1764509115918935794
A94: Dec-25 | B94: 45992 | C94: Art | D94: 1764565123058620670 | E94: 202500000000078 | F94: Dionysus X50 ml. | G94: {=IF(F94<>"",INDEX(tb_MainDatabase[Barcode],MATCH(F94,tb_MainDatabase[Link],0)),"")} -> 8857128011331 | H94: {=IF(F94<>"",INDEX(tb_MainDatabase[Grand],MATCH(F94,tb_MainDatabase[Link],0)),"")} -> EDP | I94: {=IF(F94<>"",INDEX(tb_MainDatabase[Size],MATCH(F94,tb_MainDatabase[Link],0)),"")} -> 50 ml. | J94: 1 | K94: {=IF(F94<>"",INDEX(tb_MainDatabase[ราคา],MATCH(F94,tb_MainDatabase[Link],0)),"")*J94} -> 1890 | L94: 500 | M94: =K94-(L94*J94) -> 1390 | N94: =SUMIF($D$3:D3310,R94,$M$3:M3310) -> 2780 | O94: Cash | R94: =IF(COUNTIF(D$3:D94, D94)>1, 0, D94) -> 1764565123058620670
A95: Dec-25 | B95: 45992 | C95: Art | D95: 1764565123058620670 | E95: 202500000000078 | F95: Persist50 ml. | G95: {=IF(F95<>"",INDEX(tb_MainDatabase[Barcode],MATCH(F95,tb_MainDatabase[Link],0)),"")} -> 8857128011041 | H95: {=IF(F95<>"",INDEX(tb_MainDatabase[Grand],MATCH(F95,tb_MainDatabase[Link],0)),"")} -> EDP | I95: {=IF(F95<>"",INDEX(tb_MainDatabase[Size],MATCH(F95,tb_MainDatabase[Link],0)),"")} -> 50 ml. | J95: 1 | K95: {=IF(F95<>"",INDEX(tb_MainDatabase[ราคา],MATCH(F95,tb_MainDatabase[Link],0)),"")*J95} -> 1890 | L95: 500 | M95: =K95-(L95*J95) -> 1390 | N95: =SUMIF($D$3:D3311,R95,$M$3:M3311) -> 0 | R95: =IF(COUNTIF(D$3:D95, D95)>1, 0, D95) -> 0
A96: Dec-25 | B96: 45992 | C96: Art | D96: 1764565123058620670 | E96: 202500000000078 | F96: La Belle4 ml. | G96: {=IF(F96<>"",INDEX(tb_MainDatabase[Barcode],MATCH(F96,tb_MainDatabase[Link],0)),"")} -> 8857128012016 | H96: {=IF(F96<>"",INDEX(tb_MainDatabase[Grand],MATCH(F96,tb_MainDatabase[Link],0)),"")} -> EDP | I96: {=IF(F96<>"",INDEX(tb_MainDatabase[Size],MATCH(F96,tb_MainDatabase[Link],0)),"")} -> 4 ml. | J96: 1 | K96: {=IF(F96<>"",INDEX(tb_MainDatabase[ราคา],MATCH(F96,tb_MainDatabase[Link],0)),"")*J96} -> 179 | L96: 179 | M96: =K96-(L96*J96) -> 0 | N96: =SUMIF($D$3:D3312,R96,$M$3:M3312) -> 0 | R96: =IF(COUNTIF(D$3:D96, D96)>1, 0, D96) -> 0
A97: Dec-25 | B97: 45993 | C97: Pure | D97: 1764653235473305651 | E97: 202500000000079 | F97: Secret of Peach10 ml. | G97: {=IF(F97<>"",INDEX(tb_MainDatabase[Barcode],MATCH(F97,tb_MainDatabase[Link],0)),"")} -> 8857128012037 | H97: {=IF(F97<>"",INDEX(tb_MainDatabase[Grand],MATCH(F97,tb_MainDatabase[Link],0)),"")} -> EDP | I97: {=IF(F97<>"",INDEX(tb_MainDatabase[Size],MATCH(F97,tb_MainDatabase[Link],0)),"")} -> 10 ml. | J97: 1 | K97: {=IF(F97<>"",INDEX(tb_MainDatabase[ราคา],MATCH(F97,tb_MainDatabase[Link],0)),"")*J97} -> 450 | L97: 100 | M97: =K97-(L97*J97) -> 350 | N97: =SUMIF($D$3:D3313,R97,$M$3:M3313) -> 350 | O97: Cash | R97: =IF(COUNTIF(D$3:D97, D97)>1, 0, D97) -> 1764653235473305651
A98: Dec-25 | B98: 45993 | C98: Pure | D98: 1764662747237764537 | E98: 202500000000080 | F98: Hercules30 ml. | G98: {=IF(F98<>"",INDEX(tb_MainDatabase[Barcode],MATCH(F98,tb_MainDatabase[Link],0)),"")} -> 8857128011737 | H98: {=IF(F98<>"",INDEX(tb_MainDatabase[Grand],MATCH(F98,tb_MainDatabase[Link],0)),"")} -> EDP | I98: {=IF(F98<>"",INDEX(tb_MainDatabase[Size],MATCH(F98,tb_MainDatabase[Link],0)),"")} -> 30 ml. | J98: 1 | K98: {=IF(F98<>"",INDEX(tb_MainDatabase[ราคา],MATCH(F98,tb_MainDatabase[Link],0)),"")*J98} -> 1290 | L98: 300 | M98: =K98-(L98*J98) -> 990 | N98: =SUMIF($D$3:D3314,R98,$M$3:M3314) -> 990 | O98: EDC Credit Card | P98: 45993 | Q98: 0.62916667 | R98: =IF(COUNTIF(D$3:D98, D98)>1, 0, D98) -> 1764662747237764537
A99: Dec-25 | B99: 45994 | C99: Note | D99: 1764741456033809900 | E99: 202500000000081 | F99: Beyond10 ml. | G99: {=IF(F99<>"",INDEX(tb_MainDatabase[Barcode],MATCH(F99,tb_MainDatabase[Link],0)),"")} -> 8857128012032 | H99: {=IF(F99<>"",INDEX(tb_MainDatabase[Grand],MATCH(F99,tb_MainDatabase[Link],0)),"")} -> EDP | I99: {=IF(F99<>"",INDEX(tb_MainDatabase[Size],MATCH(F99,tb_MainDatabase[Link],0)),"")} -> 10 ml. | J99: 1 | K99: {=IF(F99<>"",INDEX(tb_MainDatabase[ราคา],MATCH(F99,tb_MainDatabase[Link],0)),"")*J99} -> 450 | L99: 100 | M99: =K99-(L99*J99) -> 350 | N99: =SUMIF($D$3:D3315,R99,$M$3:M3315) -> 350 | O99: EDC Credit Card | P99: 45994 | Q99: 0.54027778 | R99: =IF(COUNTIF(D$3:D99, D99)>1, 0, D99) -> 1764741456033809900
A100: Dec-25 | B100: 45994 | C100: Note | D100: 1764742636663220052 | E100: 202500000000082 | F100: Gambling34+3550 ml. | G100: {=IF(F100<>"",INDEX(tb_MainDatabase[Barcode],MATCH(F100,tb_MainDatabase[Link],0)),"")} -> 8857128011591 | H100: {=IF(F100<>"",INDEX(tb_MainDatabase[Grand],MATCH(F100,tb_MainDatabase[Link],0)),"")} -> PARFUM | I100: {=IF(F100<>"",INDEX(tb_MainDatabase[Size],MATCH(F100,tb_MainDatabase[Link],0)),"")} -> 50 ml. | J100: 1 | K100: {=IF(F100<>"",INDEX(tb_MainDatabase[ราคา],MATCH(F100,tb_MainDatabase[Link],0)),"")*J100} -> 3040 | L100: 450 | M100: =K100-(L100*J100) -> 2590 | N100: =SUMIF($D$3:D3316,R100,$M$3:M3316) -> 2590 | O100: EDC Credit Card | P100: 45994 | Q100: 0.55555556 | R100: =IF(COUNTIF(D$3:D100, D100)>1, 0, D100) -> 1764742636663220052
...

Sheet Sell EVENT SCS
J1: =SUM(J3:J184) -> 171 | K1: =SUM(K3:K184) -> 152390 | L1: =SUM(L3:L184) -> 31450 | M1: =SUM(M3:M184) -> 119940 | N1: =SUM(N3:N184) -> 119940
A2: Month | B2: วันที่ | C2: BA | D2: เลขที่คำสั่งซื้อ | E2: เลขที่ใบเสร็จ | F2: รายการ | G2: Barcode | H2: Grand | I2: Size | J2: จำนวน | K2: ราคา | L2: ส่วนลด | M2: รวม | N2: ยอดชำระ | O2: ช่องทางชำระ | P2: Date | Q2: Time | R2: UID | S2: หมายเหตุ | T2: Nation
A3: Jul-26 | B3: 46212 | C3: Jom, Beam | D3: EVSCS20260709001 | F3: Secret of Peach30 ml. | G3: {=IF(F3<>"",INDEX(tb_MainDatabase[Barcode],MATCH(F3,tb_MainDatabase[Link],0)),"")} -> 8857128011850 | H3: {=IF(F3<>"",INDEX(tb_MainDatabase[Grand],MATCH(F3,tb_MainDatabase[Link],0)),"")} -> EDP | I3: {=IF(F3<>"",INDEX(tb_MainDatabase[Size],MATCH(F3,tb_MainDatabase[Link],0)),"")} -> 30 ml. | J3: 1 | K3: {=IF(F3<>"",INDEX(tb_MainDatabase[ราคา],MATCH(F3,tb_MainDatabase[Link],0)),"")*J3} -> 1290 | L3: 300 | M3: =K3-(L3*J3) -> 990 | N3: =SUMIF($D$3:D184,R3,$M$3:M184) -> 990 | O3: K Shop | P3: 46212 | Q3: 0.53055556 | R3: =IF(COUNTIF(D$3:D3, D3)>1, 0, D3) -> EVSCS20260709001 | T3: Thai
A4: Jul-26 | B4: 46212 | C4: Jom, Beam | D4: EVSCS20260709002 | F4: Never Blue30 ml. | G4: {=IF(F4<>"",INDEX(tb_MainDatabase[Barcode],MATCH(F4,tb_MainDatabase[Link],0)),"")} -> 8857128011836 | H4: {=IF(F4<>"",INDEX(tb_MainDatabase[Grand],MATCH(F4,tb_MainDatabase[Link],0)),"")} -> EDP | I4: {=IF(F4<>"",INDEX(tb_MainDatabase[Size],MATCH(F4,tb_MainDatabase[Link],0)),"")} -> 30 ml. | J4: 1 | K4: {=IF(F4<>"",INDEX(tb_MainDatabase[ราคา],MATCH(F4,tb_MainDatabase[Link],0)),"")*J4} -> 1290 | L4: 300 | M4: =K4-(L4*J4) -> 990 | N4: =SUMIF($D$3:D185,R4,$M$3:M185) -> 990 | O4: K Shop | P4: 46214 | Q4: 0.65694444 | R4: =IF(COUNTIF(D$3:D4, D4)>1, 0, D4) -> EVSCS20260709002 | T4: Foreign
A5: Jul-26 | B5: 46212 | C5: Jom, Beam | D5: EVSCS20260709003 | F5: Aqua30 ml. | G5: {=IF(F5<>"",INDEX(tb_MainDatabase[Barcode],MATCH(F5,tb_MainDatabase[Link],0)),"")} -> 8857128012022 | H5: {=IF(F5<>"",INDEX(tb_MainDatabase[Grand],MATCH(F5,tb_MainDatabase[Link],0)),"")} -> EDP | I5: {=IF(F5<>"",INDEX(tb_MainDatabase[Size],MATCH(F5,tb_MainDatabase[Link],0)),"")} -> 30 ml. | J5: 1 | K5: {=IF(F5<>"",INDEX(tb_MainDatabase[ราคา],MATCH(F5,tb_MainDatabase[Link],0)),"")*J5} -> 1290 | L5: 300 | M5: =K5-(L5*J5) -> 990 | N5: =SUMIF($D$3:D186,R5,$M$3:M186) -> 990 | O5: K Shop | P5: 46212 | Q5: 0.63263889 | R5: =IF(COUNTIF(D$3:D5, D5)>1, 0, D5) -> EVSCS20260709003 | T5: Foreign
A6: Jul-26 | B6: 46212 | C6: Jom, Beam | D6: EVSCS20260709004 | F6: Secret of Peach30 ml. | G6: {=IF(F6<>"",INDEX(tb_MainDatabase[Barcode],MATCH(F6,tb_MainDatabase[Link],0)),"")} -> 8857128011850 | H6: {=IF(F6<>"",INDEX(tb_MainDatabase[Grand],MATCH(F6,tb_MainDatabase[Link],0)),"")} -> EDP | I6: {=IF(F6<>"",INDEX(tb_MainDatabase[Size],MATCH(F6,tb_MainDatabase[Link],0)),"")} -> 30 ml. | J6: 1 | K6: {=IF(F6<>"",INDEX(tb_MainDatabase[ราคา],MATCH(F6,tb_MainDatabase[Link],0)),"")*J6} -> 1290 | L6: 300 | M6: =K6-(L6*J6) -> 990 | N6: =SUMIF($D$3:D187,R6,$M$3:M187) -> 990 | O6: K Shop | P6: 46212 | Q6: 0.67013889 | R6: =IF(COUNTIF(D$3:D6, D6)>1, 0, D6) -> EVSCS20260709004 | T6: Thai
A7: Jul-26 | B7: 46212 | C7: Jom, Beam | D7: EVSCS20260709005 | F7: Dream Island10 ml. | G7: {=IF(F7<>"",INDEX(tb_MainDatabase[Barcode],MATCH(F7,tb_MainDatabase[Link],0)),"")} -> 8857128012030 | H7: {=IF(F7<>"",INDEX(tb_MainDatabase[Grand],MATCH(F7,tb_MainDatabase[Link],0)),"")} -> EDP | I7: {=IF(F7<>"",INDEX(tb_MainDatabase[Size],MATCH(F7,tb_MainDatabase[Link],0)),"")} -> 10 ml. | J7: 1 | K7: {=IF(F7<>"",INDEX(tb_MainDatabase[ราคา],MATCH(F7,tb_MainDatabase[Link],0)),"")*J7} -> 450 | L7: 100 | M7: =K7-(L7*J7) -> 350 | N7: =SUMIF($D$3:D188,R7,$M$3:M188) -> 350 | O7: K Shop | P7: 46212 | Q7: 0.73125 | R7: =IF(COUNTIF(D$3:D7, D7)>1, 0, D7) -> EVSCS20260709005 | T7: Thai
A8: Jul-26 | B8: 46212 | C8: Jom, Beam | D8: EVSCS20260709006 | F8: Secret of Peach50 ml. | G8: {=IF(F8<>"",INDEX(tb_MainDatabase[Barcode],MATCH(F8,tb_MainDatabase[Link],0)),"")} -> 8857128011119 | H8: {=IF(F8<>"",INDEX(tb_MainDatabase[Grand],MATCH(F8,tb_MainDatabase[Link],0)),"")} -> EDP | I8: {=IF(F8<>"",INDEX(tb_MainDatabase[Size],MATCH(F8,tb_MainDatabase[Link],0)),"")} -> 50 ml. | J8: 1 | K8: {=IF(F8<>"",INDEX(tb_MainDatabase[ราคา],MATCH(F8,tb_MainDatabase[Link],0)),"")*J8} -> 1890 | L8: 400 | M8: =K8-(L8*J8) -> 1490 | N8: =SUMIF($D$3:D189,R8,$M$3:M189) -> 1490 | O8: K Shop | P8: 46212 | Q8: 0.77847222 | R8: =IF(COUNTIF(D$3:D8, D8)>1, 0, D8) -> EVSCS20260709006 | T8: Thai
A9: Jul-26 | B9: 46212 | C9: Jom, Beam | D9: EVSCS20260709007 | F9: Zeus10 ml. | G9: {=IF(F9<>"",INDEX(tb_MainDatabase[Barcode],MATCH(F9,tb_MainDatabase[Link],0)),"")} -> 8857128012041 | H9: {=IF(F9<>"",INDEX(tb_MainDatabase[Grand],MATCH(F9,tb_MainDatabase[Link],0)),"")} -> EDP | I9: {=IF(F9<>"",INDEX(tb_MainDatabase[Size],MATCH(F9,tb_MainDatabase[Link],0)),"")} -> 10 ml. | J9: 1 | K9: {=IF(F9<>"",INDEX(tb_MainDatabase[ราคา],MATCH(F9,tb_MainDatabase[Link],0)),"")*J9} -> 450 | L9: 100 | M9: =K9-(L9*J9) -> 350 | N9: =SUMIF($D$3:D190,R9,$M$3:M190) -> 350 | O9: K Shop | P9: 46212 | Q9: 0.74722222 | R9: =IF(COUNTIF(D$3:D9, D9)>1, 0, D9) -> EVSCS20260709007 | T9: Thai
A10: Jul-26 | B10: 46212 | C10: Jom, Beam | D10: EVSCS20260709008 | F10: Secret of Peach50 ml. | G10: {=IF(F10<>"",INDEX(tb_MainDatabase[Barcode],MATCH(F10,tb_MainDatabase[Link],0)),"")} -> 8857128011119 | H10: {=IF(F10<>"",INDEX(tb_MainDatabase[Grand],MATCH(F10,tb_MainDatabase[Link],0)),"")} -> EDP | I10: {=IF(F10<>"",INDEX(tb_MainDatabase[Size],MATCH(F10,tb_MainDatabase[Link],0)),"")} -> 50 ml. | J10: 1 | K10: {=IF(F10<>"",INDEX(tb_MainDatabase[ราคา],MATCH(F10,tb_MainDatabase[Link],0)),"")*J10} -> 1890 | L10: 400 | M10: =K10-(L10*J10) -> 1490 | N10: =SUMIF($D$3:D191,R10,$M$3:M191) -> 1840 | O10: K Shop | P10: 46212 | Q10: 0.81597222 | R10: =IF(COUNTIF(D$3:D10, D10)>1, 0, D10) -> EVSCS20260709008 | T10: Thai
A11: Jul-26 | B11: 46212 | C11: Jom, Beam | D11: EVSCS20260709008 | F11: Senorita10 ml. | G11: {=IF(F11<>"",INDEX(tb_MainDatabase[Barcode],MATCH(F11,tb_MainDatabase[Link],0)),"")} -> 8857128012039 | H11: {=IF(F11<>"",INDEX(tb_MainDatabase[Grand],MATCH(F11,tb_MainDatabase[Link],0)),"")} -> EDP | I11: {=IF(F11<>"",INDEX(tb_MainDatabase[Size],MATCH(F11,tb_MainDatabase[Link],0)),"")} -> 10 ml. | J11: 1 | K11: {=IF(F11<>"",INDEX(tb_MainDatabase[ราคา],MATCH(F11,tb_MainDatabase[Link],0)),"")*J11} -> 450 | L11: 100 | M11: =K11-(L11*J11) -> 350 | N11: =SUMIF($D$3:D192,R11,$M$3:M192) -> 0 | R11: =IF(COUNTIF(D$3:D11, D11)>1, 0, D11) -> 0
A12: Jul-26 | B12: 46212 | C12: Jom, Beam | D12: EVSCS20260709009 | F12: Voyage10 ml. | G12: {=IF(F12<>"",INDEX(tb_MainDatabase[Barcode],MATCH(F12,tb_MainDatabase[Link],0)),"")} -> 8857128012027 | H12: {=IF(F12<>"",INDEX(tb_MainDatabase[Grand],MATCH(F12,tb_MainDatabase[Link],0)),"")} -> EDP | I12: {=IF(F12<>"",INDEX(tb_MainDatabase[Size],MATCH(F12,tb_MainDatabase[Link],0)),"")} -> 10 ml. | J12: 1 | K12: {=IF(F12<>"",INDEX(tb_MainDatabase[ราคา],MATCH(F12,tb_MainDatabase[Link],0)),"")*J12} -> 450 | L12: 100 | M12: =K12-(L12*J12) -> 350 | N12: =SUMIF($D$3:D193,R12,$M$3:M193) -> 350 | O12: K Shop | P12: 46212 | Q12: 0.81805556 | R12: =IF(COUNTIF(D$3:D12, D12)>1, 0, D12) -> EVSCS20260709009 | T12: Thai
A13: Jul-26 | B13: 46212 | C13: Jom, Beam | D13: EVSCS20260709010 | F13: Nouveau10 ml. | G13: {=IF(F13<>"",INDEX(tb_MainDatabase[Barcode],MATCH(F13,tb_MainDatabase[Link],0)),"")} -> 8857128012170 | H13: {=IF(F13<>"",INDEX(tb_MainDatabase[Grand],MATCH(F13,tb_MainDatabase[Link],0)),"")} -> EDP | I13: {=IF(F13<>"",INDEX(tb_MainDatabase[Size],MATCH(F13,tb_MainDatabase[Link],0)),"")} -> 10 ml. | J13: 1 | K13: {=IF(F13<>"",INDEX(tb_MainDatabase[ราคา],MATCH(F13,tb_MainDatabase[Link],0)),"")*J13} -> 450 | L13: 100 | M13: =K13-(L13*J13) -> 350 | N13: =SUMIF($D$3:D194,R13,$M$3:M194) -> 350 | O13: K Shop | P13: 46212 | Q13: 0.82638889 | R13: =IF(COUNTIF(D$3:D13, D13)>1, 0, D13) -> EVSCS20260709010 | T13: Thai
A14: Jul-26 | B14: 46213 | C14: Jom, Beam | D14: EVSCS20260710001 | F14: Senorita10 ml. | G14: {=IF(F14<>"",INDEX(tb_MainDatabase[Barcode],MATCH(F14,tb_MainDatabase[Link],0)),"")} -> 8857128012039 | H14: {=IF(F14<>"",INDEX(tb_MainDatabase[Grand],MATCH(F14,tb_MainDatabase[Link],0)),"")} -> EDP | I14: {=IF(F14<>"",INDEX(tb_MainDatabase[Size],MATCH(F14,tb_MainDatabase[Link],0)),"")} -> 10 ml. | J14: 1 | K14: {=IF(F14<>"",INDEX(tb_MainDatabase[ราคา],MATCH(F14,tb_MainDatabase[Link],0)),"")*J14} -> 450 | L14: 100 | M14: =K14-(L14*J14) -> 350 | N14: =SUMIF($D$3:D195,R14,$M$3:M195) -> 350 | O14: K Shop | P14: 46213 | Q14: 0.54861111 | R14: =IF(COUNTIF(D$3:D14, D14)>1, 0, D14) -> EVSCS20260710001 | T14: Thai
A15: Jul-26 | B15: 46213 | C15: Jom, Beam | D15: EVSCS20260710002 | F15: Secret of Peach30 ml. | G15: {=IF(F15<>"",INDEX(tb_MainDatabase[Barcode],MATCH(F15,tb_MainDatabase[Link],0)),"")} -> 8857128011850 | H15: {=IF(F15<>"",INDEX(tb_MainDatabase[Grand],MATCH(F15,tb_MainDatabase[Link],0)),"")} -> EDP | I15: {=IF(F15<>"",INDEX(tb_MainDatabase[Size],MATCH(F15,tb_MainDatabase[Link],0)),"")} -> 30 ml. | J15: 1 | K15: {=IF(F15<>"",INDEX(tb_MainDatabase[ราคา],MATCH(F15,tb_MainDatabase[Link],0)),"")*J15} -> 1290 | L15: 300 | M15: =K15-(L15*J15) -> 990 | N15: =SUMIF($D$3:D196,R15,$M$3:M196) -> 990 | O15: K Shop | P15: 46213 | Q15: 0.54930556 | R15: =IF(COUNTIF(D$3:D15, D15)>1, 0, D15) -> EVSCS20260710002 | T15: Thai
A16: Jul-26 | B16: 46213 | C16: Jom, Beam | D16: EVSCS20260710003 | F16: Legend of Oud10 ml. | G16: {=IF(F16<>"",INDEX(tb_MainDatabase[Barcode],MATCH(F16,tb_MainDatabase[Link],0)),"")} -> 8857128012110 | H16: {=IF(F16<>"",INDEX(tb_MainDatabase[Grand],MATCH(F16,tb_MainDatabase[Link],0)),"")} -> EDP+ | I16: {=IF(F16<>"",INDEX(tb_MainDatabase[Size],MATCH(F16,tb_MainDatabase[Link],0)),"")} -> 10 ml. | J16: 1 | K16: {=IF(F16<>"",INDEX(tb_MainDatabase[ราคา],MATCH(F16,tb_MainDatabase[Link],0)),"")*J16} -> 650 | L16: 100 | M16: =K16-(L16*J16) -> 550 | N16: =SUMIF($D$3:D197,R16,$M$3:M197) -> 550 | O16: K Shop | P16: 46213 | Q16: 0.64791667 | R16: =IF(COUNTIF(D$3:D16, D16)>1, 0, D16) -> EVSCS20260710003 | T16: Thai
A17: Jul-26 | B17: 46213 | C17: Jom, Beam | D17: EVSCS20260710004 | F17: Passion30 ml. | G17: {=IF(F17<>"",INDEX(tb_MainDatabase[Barcode],MATCH(F17,tb_MainDatabase[Link],0)),"")} -> 8857128012156 | H17: {=IF(F17<>"",INDEX(tb_MainDatabase[Grand],MATCH(F17,tb_MainDatabase[Link],0)),"")} -> EDP | I17: {=IF(F17<>"",INDEX(tb_MainDatabase[Size],MATCH(F17,tb_MainDatabase[Link],0)),"")} -> 30 ml. | J17: 1 | K17: {=IF(F17<>"",INDEX(tb_MainDatabase[ราคา],MATCH(F17,tb_MainDatabase[Link],0)),"")*J17} -> 1290 | L17: 300 | M17: =K17-(L17*J17) -> 990 | N17: =SUMIF($D$3:D198,R17,$M$3:M198) -> 990 | O17: K Shop Credit Card | P17: 46213 | Q17: 0.73263889 | R17: =IF(COUNTIF(D$3:D17, D17)>1, 0, D17) -> EVSCS20260710004 | T17: Thai
A18: Jul-26 | B18: 46213 | C18: Jom, Beam | D18: EVSCS20260710005 | F18: Dream Island10 ml. | G18: {=IF(F18<>"",INDEX(tb_MainDatabase[Barcode],MATCH(F18,tb_MainDatabase[Link],0)),"")} -> 8857128012030 | H18: {=IF(F18<>"",INDEX(tb_MainDatabase[Grand],MATCH(F18,tb_MainDatabase[Link],0)),"")} -> EDP | I18: {=IF(F18<>"",INDEX(tb_MainDatabase[Size],MATCH(F18,tb_MainDatabase[Link],0)),"")} -> 10 ml. | J18: 1 | K18: {=IF(F18<>"",INDEX(tb_MainDatabase[ราคา],MATCH(F18,tb_MainDatabase[Link],0)),"")*J18} -> 450 | L18: 100 | M18: =K18-(L18*J18) -> 350 | N18: =SUMIF($D$3:D199,R18,$M$3:M199) -> 350 | O18: K Shop | P18: 46213 | Q18: 0.73819444 | R18: =IF(COUNTIF(D$3:D18, D18)>1, 0, D18) -> EVSCS20260710005 | T18: Thai
A19: Jul-26 | B19: 46213 | C19: Jom, Beam | D19: EVSCS20260710006 | F19: Rosarine10 ml. | G19: {=IF(F19<>"",INDEX(tb_MainDatabase[Barcode],MATCH(F19,tb_MainDatabase[Link],0)),"")} -> 8857128012160 | H19: {=IF(F19<>"",INDEX(tb_MainDatabase[Grand],MATCH(F19,tb_MainDatabase[Link],0)),"")} -> EDP | I19: {=IF(F19<>"",INDEX(tb_MainDatabase[Size],MATCH(F19,tb_MainDatabase[Link],0)),"")} -> 10 ml. | J19: 1 | K19: {=IF(F19<>"",INDEX(tb_MainDatabase[ราคา],MATCH(F19,tb_MainDatabase[Link],0)),"")*J19} -> 450 | L19: 100 | M19: =K19-(L19*J19) -> 350 | N19: =SUMIF($D$3:D200,R19,$M$3:M200) -> 350 | O19: K Shop | P19: 46213 | Q19: 0.82777778 | R19: =IF(COUNTIF(D$3:D19, D19)>1, 0, D19) -> EVSCS20260710006 | T19: Thai
A20: Jul-26 | B20: 46214 | C20: Aries, Chris | D20: EVSCS20260711001 | F20: Angel10 ml. | G20: {=IF(F20<>"",INDEX(tb_MainDatabase[Barcode],MATCH(F20,tb_MainDatabase[Link],0)),"")} -> 8857128012166 | H20: {=IF(F20<>"",INDEX(tb_MainDatabase[Grand],MATCH(F20,tb_MainDatabase[Link],0)),"")} -> EDP | I20: {=IF(F20<>"",INDEX(tb_MainDatabase[Size],MATCH(F20,tb_MainDatabase[Link],0)),"")} -> 10 ml. | J20: 1 | K20: {=IF(F20<>"",INDEX(tb_MainDatabase[ราคา],MATCH(F20,tb_MainDatabase[Link],0)),"")*J20} -> 450 | L20: 100 | M20: =K20-(L20*J20) -> 350 | N20: =SUMIF($D$3:D201,R20,$M$3:M201) -> 350 | O20: K Shop | P20: 46214 | Q20: 0.51041667 | R20: =IF(COUNTIF(D$3:D20, D20)>1, 0, D20) -> EVSCS20260711001 | T20: Thai
A21: Jul-26 | B21: 46214 | C21: Aries, Chris | D21: EVSCS20260711002 | F21: Angel10 ml. | G21: {=IF(F21<>"",INDEX(tb_MainDatabase[Barcode],MATCH(F21,tb_MainDatabase[Link],0)),"")} -> 8857128012166 | H21: {=IF(F21<>"",INDEX(tb_MainDatabase[Grand],MATCH(F21,tb_MainDatabase[Link],0)),"")} -> EDP | I21: {=IF(F21<>"",INDEX(tb_MainDatabase[Size],MATCH(F21,tb_MainDatabase[Link],0)),"")} -> 10 ml. | J21: 1 | K21: {=IF(F21<>"",INDEX(tb_MainDatabase[ราคา],MATCH(F21,tb_MainDatabase[Link],0)),"")*J21} -> 450 | L21: 100 | M21: =K21-(L21*J21) -> 350 | N21: =SUMIF($D$3:D202,R21,$M$3:M202) -> 350 | O21: K Shop | P21: 46214 | Q21: 0.58472222 | R21: =IF(COUNTIF(D$3:D21, D21)>1, 0, D21) -> EVSCS20260711002 | T21: Thai
A22: Jul-26 | B22: 46214 | C22: Aries, Chris | D22: EVSCS20260711003 | F22: Rosarine50 ml. | G22: {=IF(F22<>"",INDEX(tb_MainDatabase[Barcode],MATCH(F22,tb_MainDatabase[Link],0)),"")} -> 8857128011621 | H22: {=IF(F22<>"",INDEX(tb_MainDatabase[Grand],MATCH(F22,tb_MainDatabase[Link],0)),"")} -> EDP | I22: {=IF(F22<>"",INDEX(tb_MainDatabase[Size],MATCH(F22,tb_MainDatabase[Link],0)),"")} -> 50 ml. | J22: 1 | K22: {=IF(F22<>"",INDEX(tb_MainDatabase[ราคา],MATCH(F22,tb_MainDatabase[Link],0)),"")*J22} -> 1890 | L22: 400 | M22: =K22-(L22*J22) -> 1490 | N22: =SUMIF($D$3:D203,R22,$M$3:M203) -> 1490 | O22: K Shop | P22: 46214 | Q22: 0.62291667 | R22: =IF(COUNTIF(D$3:D22, D22)>1, 0, D22) -> EVSCS20260711003 | T22: Thai
A23: Jul-26 | B23: 46214 | C23: Aries, Chris | D23: EVSCS20260711004 | F23: Rosarine10 ml. | G23: {=IF(F23<>"",INDEX(tb_MainDatabase[Barcode],MATCH(F23,tb_MainDatabase[Link],0)),"")} -> 8857128012160 | H23: {=IF(F23<>"",INDEX(tb_MainDatabase[Grand],MATCH(F23,tb_MainDatabase[Link],0)),"")} -> EDP | I23: {=IF(F23<>"",INDEX(tb_MainDatabase[Size],MATCH(F23,tb_MainDatabase[Link],0)),"")} -> 10 ml. | J23: 1 | K23: {=IF(F23<>"",INDEX(tb_MainDatabase[ราคา],MATCH(F23,tb_MainDatabase[Link],0)),"")*J23} -> 450 | L23: 100 | M23: =K23-(L23*J23) -> 350 | N23: =SUMIF($D$3:D204,R23,$M$3:M204) -> 350 | O23: K Shop | P23: 46214 | Q23: 0.63402778 | R23: =IF(COUNTIF(D$3:D23, D23)>1, 0, D23) -> EVSCS20260711004 | T23: Thai
... A25: Jul-26 | B25: 46214 | C25: Aries, Chris | D25: EVSCS20260711006 | F25: Aqua10 ml. | G25: {=IF(F25<>"",INDEX(tb_MainDatabase[Barcode],MATCH(F25,tb_MainDatabase[Link],0)),"")} -> 8857128012026 | H25: {=IF(F25<>"",INDEX(tb_MainDatabase[Grand],MATCH(F25,tb_MainDatabase[Link],0)),"")} -> EDP | I25: {=IF(F25<>"",INDEX(tb_MainDatabase[Size],MATCH(F25,tb_MainDatabase[Link],0)),"")} -> 10 ml. | J25: 1 | K25: {=IF(F25<>"",INDEX(tb_MainDatabase[ราคา],MATCH(F25,tb_MainDatabase[Link],0)),"")*J25} -> 450 | L25: 100 | M25: =K25-(L25*J25) -> 350 | N25: =SUMIF($D$3:D206,R25,$M$3:M206) -> 700 | O25: K Shop | P25: 46214 | Q25: 0.64513889 | R25: =IF(COUNTIF(D$3:D25, D25)>1, 0, D25) -> EVSCS20260711006 | T25: Thai
A26: Jul-26 | B26: 46214 | C26: Aries, Chris | D26: EVSCS20260711006 | F26: La Belle10 ml. | G26: {=IF(F26<>"",INDEX(tb_MainDatabase[Barcode],MATCH(F26,tb_MainDatabase[Link],0)),"")} -> 8857128012034 | H26: {=IF(F26<>"",INDEX(tb_MainDatabase[Grand],MATCH(F26,tb_MainDatabase[Link],0)),"")} -> EDP | I26: {=IF(F26<>"",INDEX(tb_MainDatabase[Size],MATCH(F26,tb_MainDatabase[Link],0)),"")} -> 10 ml. | J26: 1 | K26: {=IF(F26<>"",INDEX(tb_MainDatabase[ราคา],MATCH(F26,tb_MainDatabase[Link],0)),"")*J26} -> 450 | L26: 100 | M26: =K26-(L26*J26) -> 350 | N26: =SUMIF($D$3:D207,R26,$M$3:M207) -> 0 | R26: =IF(COUNTIF(D$3:D26, D26)>1, 0, D26) -> 0
A27: Jul-26 | B27: 46214 | C27: Aries, Chris | D27: EVSCS20260711007 | F27: Aqua10 ml. | G27: {=IF(F27<>"",INDEX(tb_MainDatabase[Barcode],MATCH(F27,tb_MainDatabase[Link],0)),"")} -> 8857128012026 | H27: {=IF(F27<>"",INDEX(tb_MainDatabase[Grand],MATCH(F27,tb_MainDatabase[Link],0)),"")} -> EDP | I27: {=IF(F27<>"",INDEX(tb_MainDatabase[Size],MATCH(F27,tb_MainDatabase[Link],0)),"")} -> 10 ml. | J27: 1 | K27: {=IF(F27<>"",INDEX(tb_MainDatabase[ราคา],MATCH(F27,tb_MainDatabase[Link],0)),"")*J27} -> 450 | L27: 100 | M27: =K27-(L27*J27) -> 350 | N27: =SUMIF($D$3:D208,R27,$M$3:M208) -> 350 | O27: K Shop | P27: 46214 | Q27: 0.66180556 | R27: =IF(COUNTIF(D$3:D27, D27)>1, 0, D27) -> EVSCS20260711007 | T27: Thai
A28: Jul-26 | B28: 46214 | C28: Aries, Chris | D28: EVSCS20260711008 | F28: Aqua30 ml. | G28: {=IF(F28<>"",INDEX(tb_MainDatabase[Barcode],MATCH(F28,tb_MainDatabase[Link],0)),"")} -> 8857128012022 | H28: {=IF(F28<>"",INDEX(tb_MainDatabase[Grand],MATCH(F28,tb_MainDatabase[Link],0)),"")} -> EDP | I28: {=IF(F28<>"",INDEX(tb_MainDatabase[Size],MATCH(F28,tb_MainDatabase[Link],0)),"")} -> 30 ml. | J28: 1 | K28: {=IF(F28<>"",INDEX(tb_MainDatabase[ราคา],MATCH(F28,tb_MainDatabase[Link],0)),"")*J28} -> 1290 | L28: 300 | M28: =K28-(L28*J28) -> 990 | N28: =SUMIF($D$3:D209,R28,$M$3:M209) -> 990 | O28: K Shop Credit Card | P28: 46214 | Q28: 0.66805556 | R28: =IF(COUNTIF(D$3:D28, D28)>1, 0, D28) -> EVSCS20260711008 | T28: Thai
A29: Jul-26 | B29: 46214 | C29: Aries, Chris | D29: EVSCS20260711009 | F29: La Belle10 ml. | G29: {=IF(F29<>"",INDEX(tb_MainDatabase[Barcode],MATCH(F29,tb_MainDatabase[Link],0)),"")} -> 8857128012034 | H29: {=IF(F29<>"",INDEX(tb_MainDatabase[Grand],MATCH(F29,tb_MainDatabase[Link],0)),"")} -> EDP | I29: {=IF(F29<>"",INDEX(tb_MainDatabase[Size],MATCH(F29,tb_MainDatabase[Link],0)),"")} -> 10 ml. | J29: 1 | K29: {=IF(F29<>"",INDEX(tb_MainDatabase[ราคา],MATCH(F29,tb_MainDatabase[Link],0)),"")*J29} -> 450 | L29: 100 | M29: =K29-(L29*J29) -> 350 | N29: =SUMIF($D$3:D210,R29,$M$3:M210) -> 350 | O29: K Shop | P29: 46214 | Q29: 0.68194444 | R29: =IF(COUNTIF(D$3:D29, D29)>1, 0, D29) -> EVSCS20260711009 | T29: Thai
A30: Jul-26 | B30: 46214 | C30: Aries, Chris | D30: EVSCS20260711010 | F30: Rosarine10 ml. | G30: {=IF(F30<>"",INDEX(tb_MainDatabase[Barcode],MATCH(F30,tb_MainDatabase[Link],0)),"")} -> 8857128012160 | H30: {=IF(F30<>"",INDEX(tb_MainDatabase[Grand],MATCH(F30,tb_MainDatabase[Link],0)),"")} -> EDP | I30: {=IF(F30<>"",INDEX(tb_MainDatabase[Size],MATCH(F30,tb_MainDatabase[Link],0)),"")} -> 10 ml. | J30: 1 | K30: {=IF(F30<>"",INDEX(tb_MainDatabase[ราคา],MATCH(F30,tb_MainDatabase[Link],0)),"")*J30} -> 450 | L30: 100 | M30: =K30-(L30*J30) -> 350 | N30: =SUMIF($D$3:D211,R30,$M$3:M211) -> 350 | O30: K Shop | P30: 46214 | Q30: 0.68680556 | R30: =IF(COUNTIF(D$3:D30, D30)>1, 0, D30) -> EVSCS20260711010 | T30: Thai
A31: Jul-26 | B31: 46214 | C31: Aries, Chris | D31: EVSCS20260711011 | F31: Gambling34+3510 ml. | G31: {=IF(F31<>"",INDEX(tb_MainDatabase[Barcode],MATCH(F31,tb_MainDatabase[Link],0)),"")} -> 8857128012103 | H31: {=IF(F31<>"",INDEX(tb_MainDatabase[Grand],MATCH(F31,tb_MainDatabase[Link],0)),"")} -> PARFUM | I31: {=IF(F31<>"",INDEX(tb_MainDatabase[Size],MATCH(F31,tb_MainDatabase[Link],0)),"")} -> 10 ml. | J31: 1 | K31: {=IF(F31<>"",INDEX(tb_MainDatabase[ราคา],MATCH(F31,tb_MainDatabase[Link],0)),"")*J31} -> 850 | L31: 100 | M31: =K31-(L31*J31) -> 750 | N31: =SUMIF($D$3:D212,R31,$M$3:M212) -> 2140 | O31: K Shop | P31: 46214 | Q31: 0.67847222 | R31: =IF(COUNTIF(D$3:D31, D31)>1, 0, D31) -> EVSCS20260711011 | T31: Foreign
A32: Jul-26 | B32: 46214 | C32: Aries, Chris | D32: EVSCS20260711011 | F32: Blackest Black30 ml. | G32: {=IF(F32<>"",INDEX(tb_MainDatabase[Barcode],MATCH(F32,tb_MainDatabase[Link],0)),"")} -> 8857128012005 | H32: {=IF(F32<>"",INDEX(tb_MainDatabase[Grand],MATCH(F32,tb_MainDatabase[Link],0)),"")} -> EDP+ | I32: {=IF(F32<>"",INDEX(tb_MainDatabase[Size],MATCH(F32,tb_MainDatabase[Link],0)),"")} -> 30 ml. | J32: 1 | K32: {=IF(F32<>"",INDEX(tb_MainDatabase[ราคา],MATCH(F32,tb_MainDatabase[Link],0)),"")*J32} -> 1890 | L32: 500 | M32: =K32-(L32*J32) -> 1390 | N32: =SUMIF($D$3:D213,R32,$M$3:M213) -> 0 | R32: =IF(COUNTIF(D$3:D32, D32)>1, 0, D32) -> 0
A33: Jul-26 | B33: 46214 | C33: Aries, Chris | D33: EVSCS20260711012 | F33: Secret of Peach30 ml. | G33: {=IF(F33<>"",INDEX(tb_MainDatabase[Barcode],MATCH(F33,tb_MainDatabase[Link],0)),"")} -> 8857128011850 | H33: {=IF(F33<>"",INDEX(tb_MainDatabase[Grand],MATCH(F33,tb_MainDatabase[Link],0)),"")} -> EDP | I33: {=IF(F33<>"",INDEX(tb_MainDatabase[Size],MATCH(F33,tb_MainDatabase[Link],0)),"")} -> 30 ml. | J33: 1 | K33: {=IF(F33<>"",INDEX(tb_MainDatabase[ราคา],MATCH(F33,tb_MainDatabase[Link],0)),"")*J33} -> 1290 | L33: 300 | M33: =K33-(L33*J33) -> 990 | N33: =SUMIF($D$3:D214,R33,$M$3:M214) -> 990 | O33: K Shop | P33: 46214 | Q33: 0.70902778 | R33: =IF(COUNTIF(D$3:D33, D33)>1, 0, D33) -> EVSCS20260711012 | T33: Thai
A34: Jul-26 | B34: 46214 | C34: Aries, Chris | D34: EVSCS20260711013 | F34: Sparkling Mandarin10 ml. | G34: {=IF(F34<>"",INDEX(tb_MainDatabase[Barcode],MATCH(F34,tb_MainDatabase[Link],0)),"")} -> 8857128012108 | H34: {=IF(F34<>"",INDEX(tb_MainDatabase[Grand],MATCH(F34,tb_MainDatabase[Link],0)),"")} -> EDP+ | I34: {=IF(F34<>"",INDEX(tb_MainDatabase[Size],MATCH(F34,tb_MainDatabase[Link],0)),"")} -> 10 ml. | J34: 1 | K34: {=IF(F34<>"",INDEX(tb_MainDatabase[ราคา],MATCH(F34,tb_MainDatabase[Link],0)),"")*J34} -> 650 | L34: 100 | M34: =K34-(L34*J34) -> 550 | N34: =SUMIF($D$3:D215,R34,$M$3:M215) -> 550 | O34: K Shop | P34: 46214 | Q34: 0.71944444 | R34: =IF(COUNTIF(D$3:D34, D34)>1, 0, D34) -> EVSCS20260711013 | T34: Thai
A35: Jul-26 | B35: 46214 | C35: Aries, Chris | D35: EVSCS20260711014 | F35: Rosarine50 ml. | G35: {=IF(F35<>"",INDEX(tb_MainDatabase[Barcode],MATCH(F35,tb_MainDatabase[Link],0)),"")} -> 8857128011621 | H35: {=IF(F35<>"",INDEX(tb_MainDatabase[Grand],MATCH(F35,tb_MainDatabase[Link],0)),"")} -> EDP | I35: {=IF(F35<>"",INDEX(tb_MainDatabase[Size],MATCH(F35,tb_MainDatabase[Link],0)),"")} -> 50 ml. | J35: 1 | K35: {=IF(F35<>"",INDEX(tb_MainDatabase[ราคา],MATCH(F35,tb_MainDatabase[Link],0)),"")*J35} -> 1890 | L35: 400 | M35: =K35-(L35*J35) -> 1490 | N35: =SUMIF($D$3:D216,R35,$M$3:M216) -> 2980 | O35: K Shop | P35: 46214 | Q35: 0.73333333 | R35: =IF(COUNTIF(D$3:D35, D35)>1, 0, D35) -> EVSCS20260711014 | T35: Thai
A36: Jul-26 | B36: 46214 | C36: Aries, Chris | D36: EVSCS20260711014 | F36: La Belle50 ml. | G36: {=IF(F36<>"",INDEX(tb_MainDatabase[Barcode],MATCH(F36,tb_MainDatabase[Link],0)),"")} -> 8857128011058 | H36: {=IF(F36<>"",INDEX(tb_MainDatabase[Grand],MATCH(F36,tb_MainDatabase[Link],0)),"")} -> EDP | I36: {=IF(F36<>"",INDEX(tb_MainDatabase[Size],MATCH(F36,tb_MainDatabase[Link],0)),"")} -> 50 ml. | J36: 1 | K36: {=IF(F36<>"",INDEX(tb_MainDatabase[ราคา],MATCH(F36,tb_MainDatabase[Link],0)),"")*J36} -> 1890 | L36: 400 | M36: =K36-(L36*J36) -> 1490 | N36: =SUMIF($D$3:D217,R36,$M$3:M217) -> 0 | R36: =IF(COUNTIF(D$3:D36, D36)>1, 0, D36) -> 0
A37: Jul-26 | B37: 46214 | C37: Aries, Chris | D37: EVSCS20260711015 | F37: Dream Island10 ml. | G37: {=IF(F37<>"",INDEX(tb_MainDatabase[Barcode],MATCH(F37,tb_MainDatabase[Link],0)),"")} -> 8857128012030 | H37: {=IF(F37<>"",INDEX(tb_MainDatabase[Grand],MATCH(F37,tb_MainDatabase[Link],0)),"")} -> EDP | I37: {=IF(F37<>"",INDEX(tb_MainDatabase[Size],MATCH(F37,tb_MainDatabase[Link],0)),"")} -> 10 ml. | J37: 1 | K37: {=IF(F37<>"",INDEX(tb_MainDatabase[ราคา],MATCH(F37,tb_MainDatabase[Link],0)),"")*J37} -> 450 | L37: 100 | M37: =K37-(L37*J37) -> 350 | N37: =SUMIF($D$3:D218,R37,$M$3:M218) -> 350 | O37: K Shop | P37: 46214 | Q37: 0.77569444 | R37: =IF(COUNTIF(D$3:D37, D37)>1, 0, D37) -> EVSCS20260711015 | T37: Thai
A38: Jul-26 | B38: 46214 | C38: Aries, Chris | D38: EVSCS20260711016 | F38: Never Blue50 ml. | G38: {=IF(F38<>"",INDEX(tb_MainDatabase[Barcode],MATCH(F38,tb_MainDatabase[Link],0)),"")} -> 8857128011287 | H38: {=IF(F38<>"",INDEX(tb_MainDatabase[Grand],MATCH(F38,tb_MainDatabase[Link],0)),"")} -> EDP | I38: {=IF(F38<>"",INDEX(tb_MainDatabase[Size],MATCH(F38,tb_MainDatabase[Link],0)),"")} -> 50 ml. | J38: 1 | K38: {=IF(F38<>"",INDEX(tb_MainDatabase[ราคา],MATCH(F38,tb_MainDatabase[Link],0)),"")*J38} -> 1890 | L38: 400 | M38: =K38-(L38*J38) -> 1490 | N38: =SUMIF($D$3:D219,R38,$M$3:M219) -> 2190 | O38: K Shop | P38: 46214 | Q38: 0.76944444 | R38: =IF(COUNTIF(D$3:D38, D38)>1, 0, D38) -> EVSCS20260711016 | T38: Thai
A39: Jul-26 | B39: 46214 | C39: Aries, Chris | D39: EVSCS20260711016 | F39: Zeus10 ml. | G39: {=IF(F39<>"",INDEX(tb_MainDatabase[Barcode],MATCH(F39,tb_MainDatabase[Link],0)),"")} -> 8857128012041 | H39: {=IF(F39<>"",INDEX(tb_MainDatabase[Grand],MATCH(F39,tb_MainDatabase[Link],0)),"")} -> EDP | I39: {=IF(F39<>"",INDEX(tb_MainDatabase[Size],MATCH(F39,tb_MainDatabase[Link],0)),"")} -> 10 ml. | J39: 1 | K39: {=IF(F39<>"",INDEX(tb_MainDatabase[ราคา],MATCH(F39,tb_MainDatabase[Link],0)),"")*J39} -> 450 | L39: 100 | M39: =K39-(L39*J39) -> 350 | N39: =SUMIF($D$3:D220,R39,$M$3:M220) -> 0 | R39: =IF(COUNTIF(D$3:D39, D39)>1, 0, D39) -> 0
A40: Jul-26 | B40: 46214 | C40: Aries, Chris | D40: EVSCS20260711016 | F40: Passion10 ml. | G40: {=IF(F40<>"",INDEX(tb_MainDatabase[Barcode],MATCH(F40,tb_MainDatabase[Link],0)),"")} -> 8857128012157 | H40: {=IF(F40<>"",INDEX(tb_MainDatabase[Grand],MATCH(F40,tb_MainDatabase[Link],0)),"")} -> EDP | I40: {=IF(F40<>"",INDEX(tb_MainDatabase[Size],MATCH(F40,tb_MainDatabase[Link],0)),"")} -> 10 ml. | J40: 1 | K40: {=IF(F40<>"",INDEX(tb_MainDatabase[ราคา],MATCH(F40,tb_MainDatabase[Link],0)),"")*J40} -> 450 | L40: 100 | M40: =K40-(L40*J40) -> 350 | N40: =SUMIF($D$3:D221,R40,$M$3:M221) -> 0 | R40: =IF(COUNTIF(D$3:D40, D40)>1, 0, D40) -> 0
A41: Jul-26 | B41: 46214 | C41: Aries, Chris | D41: EVSCS20260711017 | F41: Rosarine30 ml. | G41: {=IF(F41<>"",INDEX(tb_MainDatabase[Barcode],MATCH(F41,tb_MainDatabase[Link],0)),"")} -> 8857128012159 | H41: {=IF(F41<>"",INDEX(tb_MainDatabase[Grand],MATCH(F41,tb_MainDatabase[Link],0)),"")} -> EDP | I41: {=IF(F41<>"",INDEX(tb_MainDatabase[Size],MATCH(F41,tb_MainDatabase[Link],0)),"")} -> 30 ml. | J41: 1 | K41: {=IF(F41<>"",INDEX(tb_MainDatabase[ราคา],MATCH(F41,tb_MainDatabase[Link],0)),"")*J41} -> 1290 | L41: 300 | M41: =K41-(L41*J41) -> 990 | N41: =SUMIF($D$3:D222,R41,$M$3:M222) -> 990 | O41: K Shop | P41: 46214 | Q41: 0.78541667 | R41: =IF(COUNTIF(D$3:D41, D41)>1, 0, D41) -> EVSCS20260711017 | T41: Thai
A42: Jul-26 | B42: 46214 | C42: Aries, Chris | D42: EVSCS20260711018 | F42: Blackest Black10 ml. | G42: {=IF(F42<>"",INDEX(tb_MainDatabase[Barcode],MATCH(F42,tb_MainDatabase[Link],0)),"")} -> 8857128012101 | H42: {=IF(F42<>"",INDEX(tb_MainDatabase[Grand],MATCH(F42,tb_MainDatabase[Link],0)),"")} -> EDP+ | I42: {=IF(F42<>"",INDEX(tb_MainDatabase[Size],MATCH(F42,tb_MainDatabase[Link],0)),"")} -> 10 ml. | J42: 2 | K42: {=IF(F42<>"",INDEX(tb_MainDatabase[ราคา],MATCH(F42,tb_MainDatabase[Link],0)),"")*J42} -> 1300 | L42: 100 | M42: =K42-(L42*J42) -> 1100 | N42: =SUMIF($D$3:D223,R42,$M$3:M223) -> 1850 | O42: K Shop | P42: 46214 | Q42: 0.78819444 | R42: =IF(COUNTIF(D$3:D42, D42)>1, 0, D42) -> EVSCS20260711018 | T42: Thai
A43: Jul-26 | B43: 46214 | C43: Aries, Chris | D43: EVSCS20260711018 | F43: Savoury10 ml. | G43: {=IF(F43<>"",INDEX(tb_MainDatabase[Barcode],MATCH(F43,tb_MainDatabase[Link],0)),"")} -> 8857128012118 | H43: {=IF(F43<>"",INDEX(tb_MainDatabase[Grand],MATCH(F43,tb_MainDatabase[Link],0)),"")} -> PARFUM | I43: {=IF(F43<>"",INDEX(tb_MainDatabase[Size],MATCH(F43,tb_MainDatabase[Link],0)),"")} -> 10 ml. | J43: 1 | K43: {=IF(F43<>"",INDEX(tb_MainDatabase[ราคา],MATCH(F43,tb_MainDatabase[Link],0)),"")*J43} -> 850 | L43: 100 | M43: =K43-(L43*J43) -> 750 | N43: =SUMIF($D$3:D224,R43,$M$3:M224) -> 0 | R43: =IF(COUNTIF(D$3:D43, D43)>1, 0, D43) -> 0
A44: Jul-26 | B44: 46214 | C44: Aries, Chris | D44: EVSCS20260711019 | F44: Secret of Peach10 ml. | G44: {=IF(F44<>"",INDEX(tb_MainDatabase[Barcode],MATCH(F44,tb_MainDatabase[Link],0)),"")} -> 8857128012037 | H44: {=IF(F44<>"",INDEX(tb_MainDatabase[Grand],MATCH(F44,tb_MainDatabase[Link],0)),"")} -> EDP | I44: {=IF(F44<>"",INDEX(tb_MainDatabase[Size],MATCH(F44,tb_MainDatabase[Link],0)),"")} -> 10 ml. | J44: 1 | K44: {=IF(F44<>"",INDEX(tb_MainDatabase[ราคา],MATCH(F44,tb_MainDatabase[Link],0)),"")*J44} -> 450 | L44: 100 | M44: =K44-(L44*J44) -> 350 | N44: =SUMIF($D$3:D225,R44,$M$3:M225) -> 350 | O44: K Shop | P44: 46214 | Q44: 0.80416667 | R44: =IF(COUNTIF(D$3:D44, D44)>1, 0, D44) -> EVSCS20260711019 | T44: Thai
A45: Jul-26 | B45: 46214 | C45: Aries, Chris | D45: EVSCS20260711020 | F45: Nouveau10 ml. | G45: {=IF(F45<>"",INDEX(tb_MainDatabase[Barcode],MATCH(F45,tb_MainDatabase[Link],0)),"")} -> 8857128012170 | H45: {=IF(F45<>"",INDEX(tb_MainDatabase[Grand],MATCH(F45,tb_MainDatabase[Link],0)),"")} -> EDP | I45: {=IF(F45<>"",INDEX(tb_MainDatabase[Size],MATCH(F45,tb_MainDatabase[Link],0)),"")} -> 10 ml. | J45: 1 | K45: {=IF(F45<>"",INDEX(tb_MainDatabase[ราคา],MATCH(F45,tb_MainDatabase[Link],0)),"")*J45} -> 450 | L45: 100 | M45: =K45-(L45*J45) -> 350 | N45: =SUMIF($D$3:D226,R45,$M$3:M226) -> 350 | O45: K Shop | P45: 46214 | Q45: 0.84930556 | R45: =IF(COUNTIF(D$3:D45, D45)>1, 0, D45) -> EVSCS20260711020 | T45: Thai
A46: Jul-26 | B46: 46214 | C46: Aries, Chris | D46: EVSCS20260711021 | F46: Secret of Peach10 ml. | G46: {=IF(F46<>"",INDEX(tb_MainDatabase[Barcode],MATCH(F46,tb_MainDatabase[Link],0)),"")} -> 8857128012037 | H46: {=IF(F46<>"",INDEX(tb_MainDatabase[Grand],MATCH(F46,tb_MainDatabase[Link],0)),"")} -> EDP | I46: {=IF(F46<>"",INDEX(tb_MainDatabase[Size],MATCH(F46,tb_MainDatabase[Link],0)),"")} -> 10 ml. | J46: 1 | K46: {=IF(F46<>"",INDEX(tb_MainDatabase[ราคา],MATCH(F46,tb_MainDatabase[Link],0)),"")*J46} -> 450 | L46: 100 | M46: =K46-(L46*J46) -> 350 | N46: =SUMIF($D$3:D227,R46,$M$3:M227) -> 350 | O46: K Shop | P46: 46214 | Q46: 0.85069444 | R46: =IF(COUNTIF(D$3:D46, D46)>1, 0, D46) -> EVSCS20260711021 | T46: Thai
A47: Jul-26 | B47: 46214 | C47: Aries, Chris | D47: EVSCS20260711022 | F47: La Belle30 ml. | G47: {=IF(F47<>"",INDEX(tb_MainDatabase[Barcode],MATCH(F47,tb_MainDatabase[Link],0)),"")} -> 8857128011904 | H47: {=IF(F47<>"",INDEX(tb_MainDatabase[Grand],MATCH(F47,tb_MainDatabase[Link],0)),"")} -> EDP | I47: {=IF(F47<>"",INDEX(tb_MainDatabase[Size],MATCH(F47,tb_MainDatabase[Link],0)),"")} -> 30 ml. | J47: 1 | K47: {=IF(F47<>"",INDEX(tb_MainDatabase[ราคา],MATCH(F47,tb_MainDatabase[Link],0)),"")*J47} -> 1290 | L47: 300 | M47: =K47-(L47*J47) -> 990 | N47: =SUMIF($D$3:D228,R47,$M$3:M228) -> 990 | O47: K Shop | P47: 46214 | Q47: 0.85902778 | R47: =IF(COUNTIF(D$3:D47, D47)>1, 0, D47) -> EVSCS20260711022 | T47: Thai
A48: Jul-26 | B48: 46215 | C48: Note, Beam | D48: EVSCS20260712001 | F48: Rosarine10 ml. | G48: {=IF(F48<>"",INDEX(tb_MainDatabase[Barcode],MATCH(F48,tb_MainDatabase[Link],0)),"")} -> 8857128012160 | H48: {=IF(F48<>"",INDEX(tb_MainDatabase[Grand],MATCH(F48,tb_MainDatabase[Link],0)),"")} -> EDP | I48: {=IF(F48<>"",INDEX(tb_MainDatabase[Size],MATCH(F48,tb_MainDatabase[Link],0)),"")} -> 10 ml. | J48: 1 | K48: {=IF(F48<>"",INDEX(tb_MainDatabase[ราคา],MATCH(F48,tb_MainDatabase[Link],0)),"")*J48} -> 450 | L48: 100 | M48: =K48-(L48*J48) -> 350 | N48: =SUMIF($D$3:D229,R48,$M$3:M229) -> 350 | O48: K Shop | P48: 46215 | Q48: 0.60555556 | R48: =IF(COUNTIF(D$3:D48, D48)>1, 0, D48) -> EVSCS20260712001 | T48: Thai
A49: Jul-26 | B49: 46215 | C49: Note, Beam | D49: EVSCS20260712002 | F49: Secret of Peach10 ml. | G49: {=IF(F49<>"",INDEX(tb_MainDatabase[Barcode],MATCH(F49,tb_MainDatabase[Link],0)),"")} -> 8857128012037 | H49: {=IF(F49<>"",INDEX(tb_MainDatabase[Grand],MATCH(F49,tb_MainDatabase[Link],0)),"")} -> EDP | I49: {=IF(F49<>"",INDEX(tb_MainDatabase[Size],MATCH(F49,tb_MainDatabase[Link],0)),"")} -> 10 ml. | J49: 1 | K49: {=IF(F49<>"",INDEX(tb_MainDatabase[ราคา],MATCH(F49,tb_MainDatabase[Link],0)),"")*J49} -> 450 | L49: 100 | M49: =K49-(L49*J49) -> 350 | N49: =SUMIF($D$3:D230,R49,$M$3:M230) -> 350 | O49: K Shop | P49: 46215 | Q49: 0.60625 | R49: =IF(COUNTIF(D$3:D49, D49)>1, 0, D49) -> EVSCS20260712002 | T49: Thai
A50: Jul-26 | B50: 46215 | C50: Note, Beam | D50: EVSCS20260712003 | F50: Secret of Peach10 ml. | G50: {=IF(F50<>"",INDEX(tb_MainDatabase[Barcode],MATCH(F50,tb_MainDatabase[Link],0)),"")} -> 8857128012037 | H50: {=IF(F50<>"",INDEX(tb_MainDatabase[Grand],MATCH(F50,tb_MainDatabase[Link],0)),"")} -> EDP | I50: {=IF(F50<>"",INDEX(tb_MainDatabase[Size],MATCH(F50,tb_MainDatabase[Link],0)),"")} -> 10 ml. | J50: 1 | K50: {=IF(F50<>"",INDEX(tb_MainDatabase[ราคา],MATCH(F50,tb_MainDatabase[Link],0)),"")*J50} -> 450 | L50: 100 | M50: =K50-(L50*J50) -> 350 | N50: =SUMIF($D$3:D231,R50,$M$3:M231) -> 350 | O50: K Shop | P50: 46215 | Q50: 0.6375 | R50: =IF(COUNTIF(D$3:D50, D50)>1, 0, D50) -> EVSCS20260712003 | T50: Thai
A51: Jul-26 | B51: 46215 | C51: Note, Beam | D51: EVSCS20260712005 | F51: Rosarine50 ml. | G51: {=IF(F51<>"",INDEX(tb_MainDatabase[Barcode],MATCH(F51,tb_MainDatabase[Link],0)),"")} -> 8857128011621 | H51: {=IF(F51<>"",INDEX(tb_MainDatabase[Grand],MATCH(F51,tb_MainDatabase[Link],0)),"")} -> EDP | I51: {=IF(F51<>"",INDEX(tb_MainDatabase[Size],MATCH(F51,tb_MainDatabase[Link],0)),"")} -> 50 ml. | J51: 3 | K51: {=IF(F51<>"",INDEX(tb_MainDatabase[ราคา],MATCH(F51,tb_MainDatabase[Link],0)),"")*J51} -> 5670 | L51: 400 | M51: =K51-(L51*J51) -> 4470 | N51: =SUMIF($D$3:D232,R51,$M$3:M232) -> 4470 | O51: K Shop | P51: 46215 | Q51: 0.65972222 | R51: =IF(COUNTIF(D$3:D51, D51)>1, 0, D51) -> EVSCS20260712005 | T51: Thai
A52: Jul-26 | B52: 46215 | C52: Note, Beam | D52: EVSCS20260712006 | F52: Secret of Peach50 ml. | G52: {=IF(F52<>"",INDEX(tb_MainDatabase[Barcode],MATCH(F52,tb_MainDatabase[Link],0)),"")} -> 8857128011119 | H52: {=IF(F52<>"",INDEX(tb_MainDatabase[Grand],MATCH(F52,tb_MainDatabase[Link],0)),"")} -> EDP | I52: {=IF(F52<>"",INDEX(tb_MainDatabase[Size],MATCH(F52,tb_MainDatabase[Link],0)),"")} -> 50 ml. | J52: 1 | K52: {=IF(F52<>"",INDEX(tb_MainDatabase[ราคา],MATCH(F52,tb_MainDatabase[Link],0)),"")*J52} -> 1890 | L52: 400 | M52: =K52-(L52*J52) -> 1490 | N52: =SUMIF($D$3:D233,R52,$M$3:M233) -> 1490 | O52: K Shop | P52: 46215 | Q52: 0.70694444 | R52: =IF(COUNTIF(D$3:D52, D52)>1, 0, D52) -> EVSCS20260712006 | T52: Thai
A53: Jul-26 | B53: 46215 | C53: Note, Beam | D53: EVSCS20260712008 | F53: Never Blue10 ml. | G53: {=IF(F53<>"",INDEX(tb_MainDatabase[Barcode],MATCH(F53,tb_MainDatabase[Link],0)),"")} -> 8857128012035 | H53: {=IF(F53<>"",INDEX(tb_MainDatabase[Grand],MATCH(F53,tb_MainDatabase[Link],0)),"")} -> EDP | I53: {=IF(F53<>"",INDEX(tb_MainDatabase[Size],MATCH(F53,tb_MainDatabase[Link],0)),"")} -> 10 ml. | J53: 1 | K53: {=IF(F53<>"",INDEX(tb_MainDatabase[ราคา],MATCH(F53,tb_MainDatabase[Link],0)),"")*J53} -> 450 | L53: 100 | M53: =K53-(L53*J53) -> 350 | N53: =SUMIF($D$3:D234,R53,$M$3:M234) -> 350 | O53: K Shop | P53: 46215 | Q53: 0.75069444 | R53: =IF(COUNTIF(D$3:D53, D53)>1, 0, D53) -> EVSCS20260712008 | T53: Thai
A54: Jul-26 | B54: 46215 | C54: Note, Beam | D54: EVSCS20260712009 | F54: Never Blue30 ml. | G54: {=IF(F54<>"",INDEX(tb_MainDatabase[Barcode],MATCH(F54,tb_MainDatabase[Link],0)),"")} -> 8857128011836 | H54: {=IF(F54<>"",INDEX(tb_MainDatabase[Grand],MATCH(F54,tb_MainDatabase[Link],0)),"")} -> EDP | I54: {=IF(F54<>"",INDEX(tb_MainDatabase[Size],MATCH(F54,tb_MainDatabase[Link],0)),"")} -> 30 ml. | J54: 1 | K54: {=IF(F54<>"",INDEX(tb_MainDatabase[ราคา],MATCH(F54,tb_MainDatabase[Link],0)),"")*J54} -> 1290 | L54: 300 | M54: =K54-(L54*J54) -> 990 | N54: =SUMIF($D$3:D235,R54,$M$3:M235) -> 990 | O54: K Shop | P54: 46215 | Q54: 0.75486111 | R54: =IF(COUNTIF(D$3:D54, D54)>1, 0, D54) -> EVSCS20260712009 | T54: Thai
A55: Jul-26 | B55: 46215 | C55: Note, Beam | D55: EVSCS20260712010 | F55: Nouveau30 ml. | G55: {=IF(F55<>"",INDEX(tb_MainDatabase[Barcode],MATCH(F55,tb_MainDatabase[Link],0)),"")} -> 8857128012169 | H55: {=IF(F55<>"",INDEX(tb_MainDatabase[Grand],MATCH(F55,tb_MainDatabase[Link],0)),"")} -> EDP | I55: {=IF(F55<>"",INDEX(tb_MainDatabase[Size],MATCH(F55,tb_MainDatabase[Link],0)),"")} -> 30 ml. | J55: 1 | K55: {=IF(F55<>"",INDEX(tb_MainDatabase[ราคา],MATCH(F55,tb_MainDatabase[Link],0)),"")*J55} -> 1290 | L55: 300 | M55: =K55-(L55*J55) -> 990 | N55: =SUMIF($D$3:D236,R55,$M$3:M236) -> 990 | O55: K Shop | P55: 46215 | Q55: 0.77013889 | R55: =IF(COUNTIF(D$3:D55, D55)>1, 0, D55) -> EVSCS20260712010 | T55: Thai
A56: Jul-26 | B56: 46215 | C56: Note, Beam | D56: EVSCS20260712011 | F56: Velvet Oud10 ml. | G56: {=IF(F56<>"",INDEX(tb_MainDatabase[Barcode],MATCH(F56,tb_MainDatabase[Link],0)),"")} -> 8857128012047 | H56: {=IF(F56<>"",INDEX(tb_MainDatabase[Grand],MATCH(F56,tb_MainDatabase[Link],0)),"")} -> EDP | I56: {=IF(F56<>"",INDEX(tb_MainDatabase[Size],MATCH(F56,tb_MainDatabase[Link],0)),"")} -> 10 ml. | J56: 1 | K56: {=IF(F56<>"",INDEX(tb_MainDatabase[ราคา],MATCH(F56,tb_MainDatabase[Link],0)),"")*J56} -> 450 | L56: 100 | M56: =K56-(L56*J56) -> 350 | N56: =SUMIF($D$3:D237,R56,$M$3:M237) -> 2390 | O56: K Shop | P56: 46216 | Q56: 0.49305556 | R56: =IF(COUNTIF(D$3:D56, D56)>1, 0, D56) -> EVSCS20260712011 | T56: Foreign
A57: Jul-26 | B57: 46215 | C57: Note, Beam | D57: EVSCS20260712011 | F57: Angel10 ml. | G57: {=IF(F57<>"",INDEX(tb_MainDatabase[Barcode],MATCH(F57,tb_MainDatabase[Link],0)),"")} -> 8857128012166 | H57: {=IF(F57<>"",INDEX(tb_MainDatabase[Grand],MATCH(F57,tb_MainDatabase[Link],0)),"")} -> EDP | I57: {=IF(F57<>"",INDEX(tb_MainDatabase[Size],MATCH(F57,tb_MainDatabase[Link],0)),"")} -> 10 ml. | J57: 1 | K57: {=IF(F57<>"",INDEX(tb_MainDatabase[ราคา],MATCH(F57,tb_MainDatabase[Link],0)),"")*J57} -> 450 | L57: 100 | M57: =K57-(L57*J57) -> 350 | N57: =SUMIF($D$3:D238,R57,$M$3:M238) -> 0 | R57: =IF(COUNTIF(D$3:D57, D57)>1, 0, D57) -> 0 | T57: Thai
A58: Jul-26 | B58: 46215 | C58: Note, Beam | D58: EVSCS20260712011 | F58: Dream Island10 ml. | G58: {=IF(F58<>"",INDEX(tb_MainDatabase[Barcode],MATCH(F58,tb_MainDatabase[Link],0)),"")} -> 8857128012030 | H58: {=IF(F58<>"",INDEX(tb_MainDatabase[Grand],MATCH(F58,tb_MainDatabase[Link],0)),"")} -> EDP | I58: {=IF(F58<>"",INDEX(tb_MainDatabase[Size],MATCH(F58,tb_MainDatabase[Link],0)),"")} -> 10 ml. | J58: 1 | K58: {=IF(F58<>"",INDEX(tb_MainDatabase[ราคา],MATCH(F58,tb_MainDatabase[Link],0)),"")*J58} -> 450 | L58: 100 | M58: =K58-(L58*J58) -> 350 | N58: =SUMIF($D$3:D239,R58,$M$3:M239) -> 0 | R58: =IF(COUNTIF(D$3:D58, D58)>1, 0, D58) -> 0 | T58: Thai
A59: Jul-26 | B59: 46215 | C59: Note, Beam | D59: EVSCS20260712011 | F59: Zeus10 ml. | G59: {=IF(F59<>"",INDEX(tb_MainDatabase[Barcode],MATCH(F59,tb_MainDatabase[Link],0)),"")} -> 8857128012041 | H59: {=IF(F59<>"",INDEX(tb_MainDatabase[Grand],MATCH(F59,tb_MainDatabase[Link],0)),"")} -> EDP | I59: {=IF(F59<>"",INDEX(tb_MainDatabase[Size],MATCH(F59,tb_MainDatabase[Link],0)),"")} -> 10 ml. | J59: 1 | K59: {=IF(F59<>"",INDEX(tb_MainDatabase[ราคา],MATCH(F59,tb_MainDatabase[Link],0)),"")*J59} -> 450 | L59: 100 | M59: =K59-(L59*J59) -> 350 | N59: =SUMIF($D$3:D240,R59,$M$3:M240) -> 0 | R59: =IF(COUNTIF(D$3:D59, D59)>1, 0, D59) -> 0 | T59: Thai
A60: Jul-26 | B60: 46215 | C60: Note, Beam | D60: EVSCS20260712011 | F60: Angel30 ml. | G60: {=IF(F60<>"",INDEX(tb_MainDatabase[Barcode],MATCH(F60,tb_MainDatabase[Link],0)),"")} -> 8857128012165 | H60: {=IF(F60<>"",INDEX(tb_MainDatabase[Grand],MATCH(F60,tb_MainDatabase[Link],0)),"")} -> EDP | I60: {=IF(F60<>"",INDEX(tb_MainDatabase[Size],MATCH(F60,tb_MainDatabase[Link],0)),"")} -> 30 ml. | J60: 1 | K60: {=IF(F60<>"",INDEX(tb_MainDatabase[ราคา],MATCH(F60,tb_MainDatabase[Link],0)),"")*J60} -> 1290 | L60: 300 | M60: =K60-(L60*J60) -> 990 | N60: =SUMIF($D$3:D241,R60,$M$3:M241) -> 0 | R60: =IF(COUNTIF(D$3:D60, D60)>1, 0, D60) -> 0 | T60: Foreign
A61: Jul-26 | B61: 46219 | C61: Jom, Beam | D61: EVSCS20260716001 | F61: Voyage50 ml. | G61: {=IF(F61<>"",INDEX(tb_MainDatabase[Barcode],MATCH(F61,tb_MainDatabase[Link],0)),"")} -> 8857128012019 | H61: {=IF(F61<>"",INDEX(tb_MainDatabase[Grand],MATCH(F61,tb_MainDatabase[Link],0)),"")} -> EDP | I61: {=IF(F61<>"",INDEX(tb_MainDatabase[Size],MATCH(F61,tb_MainDatabase[Link],0)),"")} -> 50 ml. | J61: 1 | K61: {=IF(F61<>"",INDEX(tb_MainDatabase[ราคา],MATCH(F61,tb_MainDatabase[Link],0)),"")*J61} -> 1890 | L61: 400 | M61: =K61-(L61*J61) -> 1490 | N61: =SUMIF($D$3:D242,R61,$M$3:M242) -> 1490 | O61: K Shop | P61: 46219 | Q61: 0.4875 | R61: =IF(COUNTIF(D$3:D61, D61)>1, 0, D61) -> EVSCS20260716001
A62: Jul-26 | B62: 46219 | C62: Jom, Beam | D62: EVSCS20260716002 | F62: Blackest Black50 ml. | G62: {=IF(F62<>"",INDEX(tb_MainDatabase[Barcode],MATCH(F62,tb_MainDatabase[Link],0)),"")} -> 8857128011669 | H62: {=IF(F62<>"",INDEX(tb_MainDatabase[Grand],MATCH(F62,tb_MainDatabase[Link],0)),"")} -> EDP+ | I62: {=IF(F62<>"",INDEX(tb_MainDatabase[Size],MATCH(F62,tb_MainDatabase[Link],0)),"")} -> 50 ml. | J62: 1 | K62: {=IF(F62<>"",INDEX(tb_MainDatabase[ราคา],MATCH(F62,tb_MainDatabase[Link],0)),"")*J62} -> 2890 | L62: 400 | M62: =K62-(L62*J62) -> 2490 | N62: =SUMIF($D$3:D243,R62,$M$3:M243) -> 6570 | O62: K Shop | P62: 46219 | Q62: 0.61736111 | R62: =IF(COUNTIF(D$3:D62, D62)>1, 0, D62) -> EVSCS20260716002
A63: Jul-26 | B63: 46219 | C63: Jom, Beam | D63: EVSCS20260716002 | F63: Blackest Black30 ml. | G63: {=IF(F63<>"",INDEX(tb_MainDatabase[Barcode],MATCH(F63,tb_MainDatabase[Link],0)),"")} -> 8857128012005 | H63: {=IF(F63<>"",INDEX(tb_MainDatabase[Grand],MATCH(F63,tb_MainDatabase[Link],0)),"")} -> EDP+ | I63: {=IF(F63<>"",INDEX(tb_MainDatabase[Size],MATCH(F63,tb_MainDatabase[Link],0)),"")} -> 30 ml. | J63: 1 | K63: {=IF(F63<>"",INDEX(tb_MainDatabase[ราคา],MATCH(F63,tb_MainDatabase[Link],0)),"")*J63} -> 1890 | L63: 300 | M63: =K63-(L63*J63) -> 1590 | N63: =SUMIF($D$3:D244,R63,$M$3:M244) -> 0 | R63: =IF(COUNTIF(D$3:D63, D63)>1, 0, D63) -> 0
A64: Jul-26 | B64: 46219 | C64: Jom, Beam | D64: EVSCS20260716002 | F64: Legend of Oud50 ml. | G64: {=IF(F64<>"",INDEX(tb_MainDatabase[Barcode],MATCH(F64,tb_MainDatabase[Link],0)),"")} -> 8857128011683 | H64: {=IF(F64<>"",INDEX(tb_MainDatabase[Grand],MATCH(F64,tb_MainDatabase[Link],0)),"")} -> EDP+ | I64: {=IF(F64<>"",INDEX(tb_MainDatabase[Size],MATCH(F64,tb_MainDatabase[Link],0)),"")} -> 50 ml. | J64: 1 | K64: {=IF(F64<>"",INDEX(tb_MainDatabase[ราคา],MATCH(F64,tb_MainDatabase[Link],0)),"")*J64} -> 2890 | L64: 400 | M64: =K64-(L64*J64) -> 2490 | N64: =SUMIF($D$3:D245,R64,$M$3:M245) -> 0 | R64: =IF(COUNTIF(D$3:D64, D64)>1, 0, D64) -> 0
A65: Jul-26 | B65: 46219 | C65: Jom, Beam | D65: EVSCS20260716002 | F65: La Belle10 ml. | G65: {=IF(F65<>"",INDEX(tb_MainDatabase[Barcode],MATCH(F65,tb_MainDatabase[Link],0)),"")} -> 8857128012034 | H65: {=IF(F65<>"",INDEX(tb_MainDatabase[Grand],MATCH(F65,tb_MainDatabase[Link],0)),"")} -> EDP | I65: {=IF(F65<>"",INDEX(tb_MainDatabase[Size],MATCH(F65,tb_MainDatabase[Link],0)),"")} -> 10 ml. | J65: 1 | K65: {=IF(F65<>"",INDEX(tb_MainDatabase[ราคา],MATCH(F65,tb_MainDatabase[Link],0)),"")*J65} -> 450 | L65: 450 | M65: =K65-(L65*J65) -> 0 | N65: =SUMIF($D$3:D246,R65,$M$3:M246) -> 0 | R65: =IF(COUNTIF(D$3:D65, D65)>1, 0, D65) -> 0
A66: Jul-26 | B66: 46219 | C66: Jom, Beam | D66: EVSCS20260716003 | F66: Dream Island50 ml. | G66: {=IF(F66<>"",INDEX(tb_MainDatabase[Barcode],MATCH(F66,tb_MainDatabase[Link],0)),"")} -> 8857128011300 | H66: {=IF(F66<>"",INDEX(tb_MainDatabase[Grand],MATCH(F66,tb_MainDatabase[Link],0)),"")} -> EDP | I66: {=IF(F66<>"",INDEX(tb_MainDatabase[Size],MATCH(F66,tb_MainDatabase[Link],0)),"")} -> 50 ml. | J66: 1 | K66: {=IF(F66<>"",INDEX(tb_MainDatabase[ราคา],MATCH(F66,tb_MainDatabase[Link],0)),"")*J66} -> 1890 | L66: 400 | M66: =K66-(L66*J66) -> 1490 | N66: =SUMIF($D$3:D247,R66,$M$3:M247) -> 1840 | O66: K Shop | P66: 46219 | Q66: 0.62361111 | R66: =IF(COUNTIF(D$3:D66, D66)>1, 0, D66) -> EVSCS20260716003
A67: Jul-26 | B67: 46219 | C67: Jom, Beam | D67: EVSCS20260716003 | F67: Passion10 ml. | G67: {=IF(F67<>"",INDEX(tb_MainDatabase[Barcode],MATCH(F67,tb_MainDatabase[Link],0)),"")} -> 8857128012157 | H67: {=IF(F67<>"",INDEX(tb_MainDatabase[Grand],MATCH(F67,tb_MainDatabase[Link],0)),"")} -> EDP | I67: {=IF(F67<>"",INDEX(tb_MainDatabase[Size],MATCH(F67,tb_MainDatabase[Link],0)),"")} -> 10 ml. | J67: 1 | K67: {=IF(F67<>"",INDEX(tb_MainDatabase[ราคา],MATCH(F67,tb_MainDatabase[Link],0)),"")*J67} -> 450 | L67: 100 | M67: =K67-(L67*J67) -> 350 | N67: =SUMIF($D$3:D248,R67,$M$3:M248) -> 0 | R67: =IF(COUNTIF(D$3:D67, D67)>1, 0, D67) -> 0
A68: Jul-26 | B68: 46219 | C68: Jom, Beam | D68: EVSCS20260716004 | F68: Secret of Peach30 ml. | G68: {=IF(F68<>"",INDEX(tb_MainDatabase[Barcode],MATCH(F68,tb_MainDatabase[Link],0)),"")} -> 8857128011850 | H68: {=IF(F68<>"",INDEX(tb_MainDatabase[Grand],MATCH(F68,tb_MainDatabase[Link],0)),"")} -> EDP | I68: {=IF(F68<>"",INDEX(tb_MainDatabase[Size],MATCH(F68,tb_MainDatabase[Link],0)),"")} -> 30 ml. | J68: 1 | K68: {=IF(F68<>"",INDEX(tb_MainDatabase[ราคา],MATCH(F68,tb_MainDatabase[Link],0)),"")*J68} -> 1290 | L68: 300 | M68: =K68-(L68*J68) -> 990 | N68: =SUMIF($D$3:D249,R68,$M$3:M249) -> 990 | O68: K Shop Credit Card | P68: 46219 | Q68: 0.70208333 | R68: =IF(COUNTIF(D$3:D68, D68)>1, 0, D68) -> EVSCS20260716004
A69: Jul-26 | B69: 46219 | C69: Jom, Beam | D69: EVSCS20260716005 | F69: Legend of Oud30 ml. | G69: {=IF(F69<>"",INDEX(tb_MainDatabase[Barcode],MATCH(F69,tb_MainDatabase[Link],0)),"")} -> 8857128012007 | H69: {=IF(F69<>"",INDEX(tb_MainDatabase[Grand],MATCH(F69,tb_MainDatabase[Link],0)),"")} -> EDP+ | I69: {=IF(F69<>"",INDEX(tb_MainDatabase[Size],MATCH(F69,tb_MainDatabase[Link],0)),"")} -> 30 ml. | J69: 1 | K69: {=IF(F69<>"",INDEX(tb_MainDatabase[ราคา],MATCH(F69,tb_MainDatabase[Link],0)),"")*J69} -> 1890 | L69: 300 | M69: =K69-(L69*J69) -> 1590 | N69: =SUMIF($D$3:D250,R69,$M$3:M250) -> 1590 | O69: K Shop | P69: 46219 | Q69: 0.76944444 | R69: =IF(COUNTIF(D$3:D69, D69)>1, 0, D69) -> EVSCS20260716005
A70: Jul-26 | B70: 46220 | C70: Note, Beam | D70: EVSCS20260717001 | F70: Queen10 ml. | G70: {=IF(F70<>"",INDEX(tb_MainDatabase[Barcode],MATCH(F70,tb_MainDatabase[Link],0)),"")} -> 8857128012116 | H70: {=IF(F70<>"",INDEX(tb_MainDatabase[Grand],MATCH(F70,tb_MainDatabase[Link],0)),"")} -> PARFUM | I70: {=IF(F70<>"",INDEX(tb_MainDatabase[Size],MATCH(F70,tb_MainDatabase[Link],0)),"")} -> 10 ml. | J70: 1 | K70: {=IF(F70<>"",INDEX(tb_MainDatabase[ราคา],MATCH(F70,tb_MainDatabase[Link],0)),"")*J70} -> 850 | L70: 100 | M70: =K70-(L70*J70) -> 750 | N70: =SUMIF($D$3:D251,R70,$M$3:M251) -> 750 | O70: K Shop | P70: 46220 | Q70: 0.76388889 | R70: =IF(COUNTIF(D$3:D70, D70)>1, 0, D70) -> EVSCS20260717001
A71: Jul-26 | B71: 46220 | C71: Note, Beam | D71: EVSCS20260717002 | F71: Aqua30 ml. | G71: {=IF(F71<>"",INDEX(tb_MainDatabase[Barcode],MATCH(F71,tb_MainDatabase[Link],0)),"")} -> 8857128012022 | H71: {=IF(F71<>"",INDEX(tb_MainDatabase[Grand],MATCH(F71,tb_MainDatabase[Link],0)),"")} -> EDP | I71: {=IF(F71<>"",INDEX(tb_MainDatabase[Size],MATCH(F71,tb_MainDatabase[Link],0)),"")} -> 30 ml. | J71: 1 | K71: {=IF(F71<>"",INDEX(tb_MainDatabase[ราคา],MATCH(F71,tb_MainDatabase[Link],0)),"")*J71} -> 1290 | L71: 300 | M71: =K71-(L71*J71) -> 990 | N71: =SUMIF($D$3:D252,R71,$M$3:M252) -> 990 | O71: K Shop | P71: 46220 | Q71: 0.78819444 | R71: =IF(COUNTIF(D$3:D71, D71)>1, 0, D71) -> EVSCS20260717002
A72: Jul-26 | B72: 46220 | C72: Note, Beam | D72: EVSCS20260717003 | F72: Zeus10 ml. | G72: {=IF(F72<>"",INDEX(tb_MainDatabase[Barcode],MATCH(F72,tb_MainDatabase[Link],0)),"")} -> 8857128012041 | H72: {=IF(F72<>"",INDEX(tb_MainDatabase[Grand],MATCH(F72,tb_MainDatabase[Link],0)),"")} -> EDP | I72: {=IF(F72<>"",INDEX(tb_MainDatabase[Size],MATCH(F72,tb_MainDatabase[Link],0)),"")} -> 10 ml. | J72: 1 | K72: {=IF(F72<>"",INDEX(tb_MainDatabase[ราคา],MATCH(F72,tb_MainDatabase[Link],0)),"")*J72} -> 450 | L72: 100 | M72: =K72-(L72*J72) -> 350 | N72: =SUMIF($D$3:D253,R72,$M$3:M253) -> 700 | O72: K Shop | P72: 46220 | Q72: 0.82569444 | R72: =IF(COUNTIF(D$3:D72, D72)>1, 0, D72) -> EVSCS20260717003
A73: Jul-26 | B73: 46220 | C73: Note, Beam | D73: EVSCS20260717003 | F73: Never Blue10 ml. | G73: {=IF(F73<>"",INDEX(tb_MainDatabase[Barcode],MATCH(F73,tb_MainDatabase[Link],0)),"")} -> 8857128012035 | H73: {=IF(F73<>"",INDEX(tb_MainDatabase[Grand],MATCH(F73,tb_MainDatabase[Link],0)),"")} -> EDP | I73: {=IF(F73<>"",INDEX(tb_MainDatabase[Size],MATCH(F73,tb_MainDatabase[Link],0)),"")} -> 10 ml. | J73: 1 | K73: {=IF(F73<>"",INDEX(tb_MainDatabase[ราคา],MATCH(F73,tb_MainDatabase[Link],0)),"")*J73} -> 450 | L73: 100 | M73: =K73-(L73*J73) -> 350 | N73: =SUMIF($D$3:D254,R73,$M$3:M254) -> 0 | R73: =IF(COUNTIF(D$3:D73, D73)>1, 0, D73) -> 0
A74: Jul-26 | B74: 46220 | C74: Note, Beam | D74: EVSCS20260717004 | F74: Never Blue10 ml. | G74: {=IF(F74<>"",INDEX(tb_MainDatabase[Barcode],MATCH(F74,tb_MainDatabase[Link],0)),"")} -> 8857128012035 | H74: {=IF(F74<>"",INDEX(tb_MainDatabase[Grand],MATCH(F74,tb_MainDatabase[Link],0)),"")} -> EDP | I74: {=IF(F74<>"",INDEX(tb_MainDatabase[Size],MATCH(F74,tb_MainDatabase[Link],0)),"")} -> 10 ml. | J74: 1 | K74: {=IF(F74<>"",INDEX(tb_MainDatabase[ราคา],MATCH(F74,tb_MainDatabase[Link],0)),"")*J74} -> 450 | L74: 100 | M74: =K74-(L74*J74) -> 350 | N74: =SUMIF($D$3:D255,R74,$M$3:M255) -> 700 | O74: K Shop | P74: 46220 | Q74: 0.84305556 | R74: =IF(COUNTIF(D$3:D74, D74)>1, 0, D74) -> EVSCS20260717004
A75: Jul-26 | B75: 46220 | C75: Note, Beam | D75: EVSCS20260717004 | F75: Nouveau10 ml. | G75: {=IF(F75<>"",INDEX(tb_MainDatabase[Barcode],MATCH(F75,tb_MainDatabase[Link],0)),"")} -> 8857128012170 | H75: {=IF(F75<>"",INDEX(tb_MainDatabase[Grand],MATCH(F75,tb_MainDatabase[Link],0)),"")} -> EDP | I75: {=IF(F75<>"",INDEX(tb_MainDatabase[Size],MATCH(F75,tb_MainDatabase[Link],0)),"")} -> 10 ml. | J75: 1 | K75: {=IF(F75<>"",INDEX(tb_MainDatabase[ราคา],MATCH(F75,tb_MainDatabase[Link],0)),"")*J75} -> 450 | L75: 100 | M75: =K75-(L75*J75) -> 350 | N75: =SUMIF($D$3:D256,R75,$M$3:M256) -> 0 | R75: =IF(COUNTIF(D$3:D75, D75)>1, 0, D75) -> 0
A76: Jul-26 | B76: 46221 | C76: Aries, Chris | D76: EVSCS20260718001 | F76: Secret of Peach10 ml. | G76: {=IF(F76<>"",INDEX(tb_MainDatabase[Barcode],MATCH(F76,tb_MainDatabase[Link],0)),"")} -> 8857128012037 | H76: {=IF(F76<>"",INDEX(tb_MainDatabase[Grand],MATCH(F76,tb_MainDatabase[Link],0)),"")} -> EDP | I76: {=IF(F76<>"",INDEX(tb_MainDatabase[Size],MATCH(F76,tb_MainDatabase[Link],0)),"")} -> 10 ml. | J76: 1 | K76: {=IF(F76<>"",INDEX(tb_MainDatabase[ราคา],MATCH(F76,tb_MainDatabase[Link],0)),"")*J76} -> 450 | L76: 100 | M76: =K76-(L76*J76) -> 350 | N76: =SUMIF($D$3:D257,R76,$M$3:M257) -> 350 | O76: K Shop | P76: 46221 | Q76: 0.50486111 | R76: =IF(COUNTIF(D$3:D76, D76)>1, 0, D76) -> EVSCS20260718001
A77: Jul-26 | B77: 46221 | C77: Aries, Chris | D77: EVSCS20260718002 | F77: Senorita10 ml. | G77: {=IF(F77<>"",INDEX(tb_MainDatabase[Barcode],MATCH(F77,tb_MainDatabase[Link],0)),"")} -> 8857128012039 | H77: {=IF(F77<>"",INDEX(tb_MainDatabase[Grand],MATCH(F77,tb_MainDatabase[Link],0)),"")} -> EDP | I77: {=IF(F77<>"",INDEX(tb_MainDatabase[Size],MATCH(F77,tb_MainDatabase[Link],0)),"")} -> 10 ml. | J77: 1 | K77: {=IF(F77<>"",INDEX(tb_MainDatabase[ราคา],MATCH(F77,tb_MainDatabase[Link],0)),"")*J77} -> 450 | L77: 100 | M77: =K77-(L77*J77) -> 350 | N77: =SUMIF($D$3:D258,R77,$M$3:M258) -> 350 | O77: K Shop | P77: 46221 | Q77: 0.50902778 | R77: =IF(COUNTIF(D$3:D77, D77)>1, 0, D77) -> EVSCS20260718002
A78: Jul-26 | B78: 46221 | C78: Aries, Chris | D78: EVSCS20260718003 | F78: Never Blue10 ml. | G78: {=IF(F78<>"",INDEX(tb_MainDatabase[Barcode],MATCH(F78,tb_MainDatabase[Link],0)),"")} -> 8857128012035 | H78: {=IF(F78<>"",INDEX(tb_MainDatabase[Grand],MATCH(F78,tb_MainDatabase[Link],0)),"")} -> EDP | I78: {=IF(F78<>"",INDEX(tb_MainDatabase[Size],MATCH(F78,tb_MainDatabase[Link],0)),"")} -> 10 ml. | J78: 1 | K78: {=IF(F78<>"",INDEX(tb_MainDatabase[ราคา],MATCH(F78,tb_MainDatabase[Link],0)),"")*J78} -> 450 | L78: 100 | M78: =K78-(L78*J78) -> 350 | N78: =SUMIF($D$3:D259,R78,$M$3:M259) -> 350 | O78: K Shop | P78: 46221 | Q78: 0.51527778 | R78: =IF(COUNTIF(D$3:D78, D78)>1, 0, D78) -> EVSCS20260718003
A79: Jul-26 | B79: 46221 | C79: Aries, Chris | D79: EVSCS20260718004 | F79: Secret of Peach10 ml. | G79: {=IF(F79<>"",INDEX(tb_MainDatabase[Barcode],MATCH(F79,tb_MainDatabase[Link],0)),"")} -> 8857128012037 | H79: {=IF(F79<>"",INDEX(tb_MainDatabase[Grand],MATCH(F79,tb_MainDatabase[Link],0)),"")} -> EDP | I79: {=IF(F79<>"",INDEX(tb_MainDatabase[Size],MATCH(F79,tb_MainDatabase[Link],0)),"")} -> 10 ml. | J79: 1 | K79: {=IF(F79<>"",INDEX(tb_MainDatabase[ราคา],MATCH(F79,tb_MainDatabase[Link],0)),"")*J79} -> 450 | L79: 100 | M79: =K79-(L79*J79) -> 350 | N79: =SUMIF($D$3:D260,R79,$M$3:M260) -> 1400 | O79: K Shop | P79: 46221 | Q79: 0.54583333 | R79: =IF(COUNTIF(D$3:D79, D79)>1, 0, D79) -> EVSCS20260718004
A80: Jul-26 | B80: 46221 | C80: Aries, Chris | D80: EVSCS20260718004 | F80: Never Blue10 ml. | G80: {=IF(F80<>"",INDEX(tb_MainDatabase[Barcode],MATCH(F80,tb_MainDatabase[Link],0)),"")} -> 8857128012035 | H80: {=IF(F80<>"",INDEX(tb_MainDatabase[Grand],MATCH(F80,tb_MainDatabase[Link],0)),"")} -> EDP | I80: {=IF(F80<>"",INDEX(tb_MainDatabase[Size],MATCH(F80,tb_MainDatabase[Link],0)),"")} -> 10 ml. | J80: 1 | K80: {=IF(F80<>"",INDEX(tb_MainDatabase[ราคา],MATCH(F80,tb_MainDatabase[Link],0)),"")*J80} -> 450 | L80: 100 | M80: =K80-(L80*J80) -> 350 | N80: =SUMIF($D$3:D261,R80,$M$3:M261) -> 0 | R80: =IF(COUNTIF(D$3:D80, D80)>1, 0, D80) -> 0
A81: Jul-26 | B81: 46221 | C81: Aries, Chris | D81: EVSCS20260718004 | F81: Rosarine10 ml. | G81: {=IF(F81<>"",INDEX(tb_MainDatabase[Barcode],MATCH(F81,tb_MainDatabase[Link],0)),"")} -> 8857128012160 | H81: {=IF(F81<>"",INDEX(tb_MainDatabase[Grand],MATCH(F81,tb_MainDatabase[Link],0)),"")} -> EDP | I81: {=IF(F81<>"",INDEX(tb_MainDatabase[Size],MATCH(F81,tb_MainDatabase[Link],0)),"")} -> 10 ml. | J81: 1 | K81: {=IF(F81<>"",INDEX(tb_MainDatabase[ราคา],MATCH(F81,tb_MainDatabase[Link],0)),"")*J81} -> 450 | L81: 100 | M81: =K81-(L81*J81) -> 350 | N81: =SUMIF($D$3:D262,R81,$M$3:M262) -> 0 | R81: =IF(COUNTIF(D$3:D81, D81)>1, 0, D81) -> 0
A82: Jul-26 | B82: 46221 | C82: Aries, Chris | D82: EVSCS20260718004 | F82: Nouveau10 ml. | G82: {=IF(F82<>"",INDEX(tb_MainDatabase[Barcode],MATCH(F82,tb_MainDatabase[Link],0)),"")} -> 8857128012170 | H82: {=IF(F82<>"",INDEX(tb_MainDatabase[Grand],MATCH(F82,tb_MainDatabase[Link],0)),"")} -> EDP | I82: {=IF(F82<>"",INDEX(tb_MainDatabase[Size],MATCH(F82,tb_MainDatabase[Link],0)),"")} -> 10 ml. | J82: 1 | K82: {=IF(F82<>"",INDEX(tb_MainDatabase[ราคา],MATCH(F82,tb_MainDatabase[Link],0)),"")*J82} -> 450 | L82: 100 | M82: =K82-(L82*J82) -> 350 | N82: =SUMIF($D$3:D263,R82,$M$3:M263) -> 0 | R82: =IF(COUNTIF(D$3:D82, D82)>1, 0, D82) -> 0
A83: Jul-26 | B83: 46221 | C83: Aries, Chris | D83: EVSCS20260718005 | F83: Voyage10 ml. | G83: {=IF(F83<>"",INDEX(tb_MainDatabase[Barcode],MATCH(F83,tb_MainDatabase[Link],0)),"")} -> 8857128012027 | H83: {=IF(F83<>"",INDEX(tb_MainDatabase[Grand],MATCH(F83,tb_MainDatabase[Link],0)),"")} -> EDP | I83: {=IF(F83<>"",INDEX(tb_MainDatabase[Size],MATCH(F83,tb_MainDatabase[Link],0)),"")} -> 10 ml. | J83: 2 | K83: {=IF(F83<>"",INDEX(tb_MainDatabase[ราคา],MATCH(F83,tb_MainDatabase[Link],0)),"")*J83} -> 900 | L83: 100 | M83: =K83-(L83*J83) -> 700 | N83: =SUMIF($D$3:D264,R83,$M$3:M264) -> 700 | O83: K Shop | P83: 46221 | Q83: 0.55833333 | R83: =IF(COUNTIF(D$3:D83, D83)>1, 0, D83) -> EVSCS20260718005
A84: Jul-26 | B84: 46221 | C84: Aries, Chris | D84: EVSCS20260718006 | F84: Queen10 ml. | G84: {=IF(F84<>"",INDEX(tb_MainDatabase[Barcode],MATCH(F84,tb_MainDatabase[Link],0)),"")} -> 8857128012116 | H84: {=IF(F84<>"",INDEX(tb_MainDatabase[Grand],MATCH(F84,tb_MainDatabase[Link],0)),"")} -> PARFUM | I84: {=IF(F84<>"",INDEX(tb_MainDatabase[Size],MATCH(F84,tb_MainDatabase[Link],0)),"")} -> 10 ml. | J84: 1 | K84: {=IF(F84<>"",INDEX(tb_MainDatabase[ราคา],MATCH(F84,tb_MainDatabase[Link],0)),"")*J84} -> 850 | L84: 100 | M84: =K84-(L84*J84) -> 750 | N84: =SUMIF($D$3:D265,R84,$M$3:M265) -> 1300 | O84: K Shop | P84: 46221 | Q84: 0.55208333 | R84: =IF(COUNTIF(D$3:D84, D84)>1, 0, D84) -> EVSCS20260718006
A85: Jul-26 | B85: 46221 | C85: Aries, Chris | D85: EVSCS20260718006 | F85: Blackest Black10 ml. | G85: {=IF(F85<>"",INDEX(tb_MainDatabase[Barcode],MATCH(F85,tb_MainDatabase[Link],0)),"")} -> 8857128012101 | H85: {=IF(F85<>"",INDEX(tb_MainDatabase[Grand],MATCH(F85,tb_MainDatabase[Link],0)),"")} -> EDP+ | I85: {=IF(F85<>"",INDEX(tb_MainDatabase[Size],MATCH(F85,tb_MainDatabase[Link],0)),"")} -> 10 ml. | J85: 1 | K85: {=IF(F85<>"",INDEX(tb_MainDatabase[ราคา],MATCH(F85,tb_MainDatabase[Link],0)),"")*J85} -> 650 | L85: 100 | M85: =K85-(L85*J85) -> 550 | N85: =SUMIF($D$3:D266,R85,$M$3:M266) -> 0 | R85: =IF(COUNTIF(D$3:D85, D85)>1, 0, D85) -> 0
A86: Jul-26 | B86: 46221 | C86: Aries, Chris | D86: EVSCS20260718007 | F86: Sparkling Mandarin10 ml. | G86: {=IF(F86<>"",INDEX(tb_MainDatabase[Barcode],MATCH(F86,tb_MainDatabase[Link],0)),"")} -> 8857128012108 | H86: {=IF(F86<>"",INDEX(tb_MainDatabase[Grand],MATCH(F86,tb_MainDatabase[Link],0)),"")} -> EDP+ | I86: {=IF(F86<>"",INDEX(tb_MainDatabase[Size],MATCH(F86,tb_MainDatabase[Link],0)),"")} -> 10 ml. | J86: 1 | K86: {=IF(F86<>"",INDEX(tb_MainDatabase[ราคา],MATCH(F86,tb_MainDatabase[Link],0)),"")*J86} -> 650 | L86: 100 | M86: =K86-(L86*J86) -> 550 | N86: =SUMIF($D$3:D267,R86,$M$3:M267) -> 550 | O86: K Shop | P86: 46221 | Q86: 0.56666667 | R86: =IF(COUNTIF(D$3:D86, D86)>1, 0, D86) -> EVSCS20260718007
A87: Jul-26 | B87: 46221 | C87: Aries, Chris | D87: EVSCS20260718008 | F87: Rosarine10 ml. | G87: {=IF(F87<>"",INDEX(tb_MainDatabase[Barcode],MATCH(F87,tb_MainDatabase[Link],0)),"")} -> 8857128012160 | H87: {=IF(F87<>"",INDEX(tb_MainDatabase[Grand],MATCH(F87,tb_MainDatabase[Link],0)),"")} -> EDP | I87: {=IF(F87<>"",INDEX(tb_MainDatabase[Size],MATCH(F87,tb_MainDatabase[Link],0)),"")} -> 10 ml. | J87: 1 | K87: {=IF(F87<>"",INDEX(tb_MainDatabase[ราคา],MATCH(F87,tb_MainDatabase[Link],0)),"")*J87} -> 450 | L87: 100 | M87: =K87-(L87*J87) -> 350 | N87: =SUMIF($D$3:D268,R87,$M$3:M268) -> 700 | O87: K Shop | P87: 46221 | Q87: 0.56319444 | R87: =IF(COUNTIF(D$3:D87, D87)>1, 0, D87) -> EVSCS20260718008
A88: Jul-26 | B88: 46221 | C88: Aries, Chris | D88: EVSCS20260718008 | F88: Senorita10 ml. | G88: {=IF(F88<>"",INDEX(tb_MainDatabase[Barcode],MATCH(F88,tb_MainDatabase[Link],0)),"")} -> 8857128012039 | H88: {=IF(F88<>"",INDEX(tb_MainDatabase[Grand],MATCH(F88,tb_MainDatabase[Link],0)),"")} -> EDP | I88: {=IF(F88<>"",INDEX(tb_MainDatabase[Size],MATCH(F88,tb_MainDatabase[Link],0)),"")} -> 10 ml. | J88: 1 | K88: {=IF(F88<>"",INDEX(tb_MainDatabase[ราคา],MATCH(F88,tb_MainDatabase[Link],0)),"")*J88} -> 450 | L88: 100 | M88: =K88-(L88*J88) -> 350 | N88: =SUMIF($D$3:D269,R88,$M$3:M269) -> 0 | R88: =IF(COUNTIF(D$3:D88, D88)>1, 0, D88) -> 0
A89: Jul-26 | B89: 46221 | C89: Aries, Chris | D89: EVSCS20260718009 | F89: La Belle10 ml. | G89: {=IF(F89<>"",INDEX(tb_MainDatabase[Barcode],MATCH(F89,tb_MainDatabase[Link],0)),"")} -> 8857128012034 | H89: {=IF(F89<>"",INDEX(tb_MainDatabase[Grand],MATCH(F89,tb_MainDatabase[Link],0)),"")} -> EDP | I89: {=IF(F89<>"",INDEX(tb_MainDatabase[Size],MATCH(F89,tb_MainDatabase[Link],0)),"")} -> 10 ml. | J89: 1 | K89: {=IF(F89<>"",INDEX(tb_MainDatabase[ราคา],MATCH(F89,tb_MainDatabase[Link],0)),"")*J89} -> 450 | L89: 100 | M89: =K89-(L89*J89) -> 350 | N89: =SUMIF($D$3:D270,R89,$M$3:M270) -> 350 | O89: K Shop Credit Card | P89: 46221 | Q89: 0.59583333 | R89: =IF(COUNTIF(D$3:D89, D89)>1, 0, D89) -> EVSCS20260718009
A90: Jul-26 | B90: 46221 | C90: Aries, Chris | D90: EVSCS20260718010 | F90: Senorita10 ml. | G90: {=IF(F90<>"",INDEX(tb_MainDatabase[Barcode],MATCH(F90,tb_MainDatabase[Link],0)),"")} -> 8857128012039 | H90: {=IF(F90<>"",INDEX(tb_MainDatabase[Grand],MATCH(F90,tb_MainDatabase[Link],0)),"")} -> EDP | I90: {=IF(F90<>"",INDEX(tb_MainDatabase[Size],MATCH(F90,tb_MainDatabase[Link],0)),"")} -> 10 ml. | J90: 1 | K90: {=IF(F90<>"",INDEX(tb_MainDatabase[ราคา],MATCH(F90,tb_MainDatabase[Link],0)),"")*J90} -> 450 | L90: 100 | M90: =K90-(L90*J90) -> 350 | N90: =SUMIF($D$3:D271,R90,$M$3:M271) -> 350 | O90: K Shop | P90: 46221 | Q90: 0.61319444 | R90: =IF(COUNTIF(D$3:D90, D90)>1, 0, D90) -> EVSCS20260718010
A91: Jul-26 | B91: 46221 | C91: Aries, Chris | D91: EVSCS20260718011 | F91: Angel30 ml. | G91: {=IF(F91<>"",INDEX(tb_MainDatabase[Barcode],MATCH(F91,tb_MainDatabase[Link],0)),"")} -> 8857128012165 | H91: {=IF(F91<>"",INDEX(tb_MainDatabase[Grand],MATCH(F91,tb_MainDatabase[Link],0)),"")} -> EDP | I91: {=IF(F91<>"",INDEX(tb_MainDatabase[Size],MATCH(F91,tb_MainDatabase[Link],0)),"")} -> 30 ml. | J91: 1 | K91: {=IF(F91<>"",INDEX(tb_MainDatabase[ราคา],MATCH(F91,tb_MainDatabase[Link],0)),"")*J91} -> 1290 | L91: 300 | M91: =K91-(L91*J91) -> 990 | N91: =SUMIF($D$3:D272,R91,$M$3:M272) -> 990 | O91: K Shop | P91: 46221 | Q91: 0.62291667 | R91: =IF(COUNTIF(D$3:D91, D91)>1, 0, D91) -> EVSCS20260718011
A92: Jul-26 | B92: 46221 | C92: Aries, Chris | D92: EVSCS20260718012 | F92: Never Blue50 ml. | G92: {=IF(F92<>"",INDEX(tb_MainDatabase[Barcode],MATCH(F92,tb_MainDatabase[Link],0)),"")} -> 8857128011287 | H92: {=IF(F92<>"",INDEX(tb_MainDatabase[Grand],MATCH(F92,tb_MainDatabase[Link],0)),"")} -> EDP | I92: {=IF(F92<>"",INDEX(tb_MainDatabase[Size],MATCH(F92,tb_MainDatabase[Link],0)),"")} -> 50 ml. | J92: 1 | K92: {=IF(F92<>"",INDEX(tb_MainDatabase[ราคา],MATCH(F92,tb_MainDatabase[Link],0)),"")*J92} -> 1890 | L92: 400 | M92: =K92-(L92*J92) -> 1490 | N92: =SUMIF($D$3:D273,R92,$M$3:M273) -> 1490 | O92: K Shop | P92: 46221 | Q92: 0.62638889 | R92: =IF(COUNTIF(D$3:D92, D92)>1, 0, D92) -> EVSCS20260718012
A93: Jul-26 | B93: 46221 | C93: Aries, Chris | D93: EVSCS20260718013 | F93: Rosarine50 ml. | G93: {=IF(F93<>"",INDEX(tb_MainDatabase[Barcode],MATCH(F93,tb_MainDatabase[Link],0)),"")} -> 8857128011621 | H93: {=IF(F93<>"",INDEX(tb_MainDatabase[Grand],MATCH(F93,tb_MainDatabase[Link],0)),"")} -> EDP | I93: {=IF(F93<>"",INDEX(tb_MainDatabase[Size],MATCH(F93,tb_MainDatabase[Link],0)),"")} -> 50 ml. | J93: 1 | K93: {=IF(F93<>"",INDEX(tb_MainDatabase[ราคา],MATCH(F93,tb_MainDatabase[Link],0)),"")*J93} -> 1890 | L93: 400 | M93: =K93-(L93*J93) -> 1490 | N93: =SUMIF($D$3:D274,R93,$M$3:M274) -> 2980 | O93: K Shop | P93: 46221 | Q93: 0.64236111 | R93: =IF(COUNTIF(D$3:D93, D93)>1, 0, D93) -> EVSCS20260718013
A94: Jul-26 | B94: 46221 | C94: Aries, Chris | D94: EVSCS20260718013 | F94: Voyage50 ml. | G94: {=IF(F94<>"",INDEX(tb_MainDatabase[Barcode],MATCH(F94,tb_MainDatabase[Link],0)),"")} -> 8857128012019 | H94: {=IF(F94<>"",INDEX(tb_MainDatabase[Grand],MATCH(F94,tb_MainDatabase[Link],0)),"")} -> EDP | I94: {=IF(F94<>"",INDEX(tb_MainDatabase[Size],MATCH(F94,tb_MainDatabase[Link],0)),"")} -> 50 ml. | J94: 1 | K94: {=IF(F94<>"",INDEX(tb_MainDatabase[ราคา],MATCH(F94,tb_MainDatabase[Link],0)),"")*J94} -> 1890 | L94: 400 | M94: =K94-(L94*J94) -> 1490 | N94: =SUMIF($D$3:D275,R94,$M$3:M275) -> 0 | R94: =IF(COUNTIF(D$3:D94, D94)>1, 0, D94) -> 0
A95: Jul-26 | B95: 46221 | C95: Aries, Chris | D95: EVSCS20260718014 | F95: Nouveau10 ml. | G95: {=IF(F95<>"",INDEX(tb_MainDatabase[Barcode],MATCH(F95,tb_MainDatabase[Link],0)),"")} -> 8857128012170 | H95: {=IF(F95<>"",INDEX(tb_MainDatabase[Grand],MATCH(F95,tb_MainDatabase[Link],0)),"")} -> EDP | I95: {=IF(F95<>"",INDEX(tb_MainDatabase[Size],MATCH(F95,tb_MainDatabase[Link],0)),"")} -> 10 ml. | J95: 1 | K95: {=IF(F95<>"",INDEX(tb_MainDatabase[ราคา],MATCH(F95,tb_MainDatabase[Link],0)),"")*J95} -> 450 | L95: 100 | M95: =K95-(L95*J95) -> 350 | N95: =SUMIF($D$3:D276,R95,$M$3:M276) -> 1250 | O95: K Shop | P95: 46221 | Q95: 0.63472222 | R95: =IF(COUNTIF(D$3:D95, D95)>1, 0, D95) -> EVSCS20260718014
A96: Jul-26 | B96: 46221 | C96: Aries, Chris | D96: EVSCS20260718014 | F96: Velvet Oud10 ml. | G96: {=IF(F96<>"",INDEX(tb_MainDatabase[Barcode],MATCH(F96,tb_MainDatabase[Link],0)),"")} -> 8857128012047 | H96: {=IF(F96<>"",INDEX(tb_MainDatabase[Grand],MATCH(F96,tb_MainDatabase[Link],0)),"")} -> EDP | I96: {=IF(F96<>"",INDEX(tb_MainDatabase[Size],MATCH(F96,tb_MainDatabase[Link],0)),"")} -> 10 ml. | J96: 1 | K96: {=IF(F96<>"",INDEX(tb_MainDatabase[ราคา],MATCH(F96,tb_MainDatabase[Link],0)),"")*J96} -> 450 | L96: 100 | M96: =K96-(L96*J96) -> 350 | N96: =SUMIF($D$3:D277,R96,$M$3:M277) -> 0 | R96: =IF(COUNTIF(D$3:D96, D96)>1, 0, D96) -> 0
A97: Jul-26 | B97: 46221 | C97: Aries, Chris | D97: EVSCS20260718014 | F97: Legend of Oud10 ml. | G97: {=IF(F97<>"",INDEX(tb_MainDatabase[Barcode],MATCH(F97,tb_MainDatabase[Link],0)),"")} -> 8857128012110 | H97: {=IF(F97<>"",INDEX(tb_MainDatabase[Grand],MATCH(F97,tb_MainDatabase[Link],0)),"")} -> EDP+ | I97: {=IF(F97<>"",INDEX(tb_MainDatabase[Size],MATCH(F97,tb_MainDatabase[Link],0)),"")} -> 10 ml. | J97: 1 | K97: {=IF(F97<>"",INDEX(tb_MainDatabase[ราคา],MATCH(F97,tb_MainDatabase[Link],0)),"")*J97} -> 650 | L97: 100 | M97: =K97-(L97*J97) -> 550 | N97: =SUMIF($D$3:D278,R97,$M$3:M278) -> 0 | R97: =IF(COUNTIF(D$3:D97, D97)>1, 0, D97) -> 0
A98: Jul-26 | B98: 46221 | C98: Aries, Chris | D98: EVSCS20260718015 | F98: Nouveau10 ml. | G98: {=IF(F98<>"",INDEX(tb_MainDatabase[Barcode],MATCH(F98,tb_MainDatabase[Link],0)),"")} -> 8857128012170 | H98: {=IF(F98<>"",INDEX(tb_MainDatabase[Grand],MATCH(F98,tb_MainDatabase[Link],0)),"")} -> EDP | I98: {=IF(F98<>"",INDEX(tb_MainDatabase[Size],MATCH(F98,tb_MainDatabase[Link],0)),"")} -> 10 ml. | J98: 1 | K98: {=IF(F98<>"",INDEX(tb_MainDatabase[ราคา],MATCH(F98,tb_MainDatabase[Link],0)),"")*J98} -> 450 | L98: 100 | M98: =K98-(L98*J98) -> 350 | N98: =SUMIF($D$3:D279,R98,$M$3:M279) -> 350 | O98: K Shop | P98: 46221 | Q98: 0.65555556 | R98: =IF(COUNTIF(D$3:D98, D98)>1, 0, D98) -> EVSCS20260718015
A99: Jul-26 | B99: 46221 | C99: Aries, Chris | D99: EVSCS20260718016 | F99: La Belle30 ml. | G99: {=IF(F99<>"",INDEX(tb_MainDatabase[Barcode],MATCH(F99,tb_MainDatabase[Link],0)),"")} -> 8857128011904 | H99: {=IF(F99<>"",INDEX(tb_MainDatabase[Grand],MATCH(F99,tb_MainDatabase[Link],0)),"")} -> EDP | I99: {=IF(F99<>"",INDEX(tb_MainDatabase[Size],MATCH(F99,tb_MainDatabase[Link],0)),"")} -> 30 ml. | J99: 1 | K99: {=IF(F99<>"",INDEX(tb_MainDatabase[ราคา],MATCH(F99,tb_MainDatabase[Link],0)),"")*J99} -> 1290 | L99: 300 | M99: =K99-(L99*J99) -> 990 | N99: =SUMIF($D$3:D280,R99,$M$3:M280) -> 990 | O99: K Shop | P99: 46221 | Q99: 0.66527778 | R99: =IF(COUNTIF(D$3:D99, D99)>1, 0, D99) -> EVSCS20260718016
A100: Jul-26 | B100: 46221 | C100: Aries, Chris | D100: EVSCS20260718017 | F100: Nouveau30 ml. | G100: {=IF(F100<>"",INDEX(tb_MainDatabase[Barcode],MATCH(F100,tb_MainDatabase[Link],0)),"")} -> 8857128012169 | H100: {=IF(F100<>"",INDEX(tb_MainDatabase[Grand],MATCH(F100,tb_MainDatabase[Link],0)),"")} -> EDP | I100: {=IF(F100<>"",INDEX(tb_MainDatabase[Size],MATCH(F100,tb_MainDatabase[Link],0)),"")} -> 30 ml. | J100: 1 | K100: {=IF(F100<>"",INDEX(tb_MainDatabase[ราคา],MATCH(F100,tb_MainDatabase[Link],0)),"")*J100} -> 1290 | L100: 300 | M100: =K100-(L100*J100) -> 990 | N100: =SUMIF($D$3:D281,R100,$M$3:M281) -> 990 | O100: K Shop | P100: 46221 | Q100: 0.67222222 | R100: =IF(COUNTIF(D$3:D100, D100)>1, 0, D100) -> EVSCS20260718017
A101: Jul-26 | B101: 46221 | C101: Aries, Chris | D101: EVSCS20260718018 | F101: Rosarine10 ml. | G101: {=IF(F101<>"",INDEX(tb_MainDatabase[Barcode],MATCH(F101,tb_MainDatabase[Link],0)),"")} -> 8857128012160 | H101: {=IF(F101<>"",INDEX(tb_MainDatabase[Grand],MATCH(F101,tb_MainDatabase[Link],0)),"")} -> EDP | I101: {=IF(F101<>"",INDEX(tb_MainDatabase[Size],MATCH(F101,tb_MainDatabase[Link],0)),"")} -> 10 ml. | J101: 1 | K101: {=IF(F101<>"",INDEX(tb_MainDatabase[ราคา],MATCH(F101,tb_MainDatabase[Link],0)),"")*J101} -> 450 | L101: 100 | M101: =K101-(L101*J101) -> 350 | N101: =SUMIF($D$3:D282,R101,$M$3:M282) -> 350 | O101: K Shop | P101: 46221 | Q101: 0.67847222 | R101: =IF(COUNTIF(D$3:D101, D101)>1, 0, D101) -> EVSCS20260718018
...

Sheet PO List Lab Parfumo
B1: *** | C1: *** | D1: *** | E1: *** | G1: *** | J1: *** | K1: ***
A3: Order | B3: Date | C3: PO Order Number | D3: PO Order Version | E3: Branch | F3: Branches | G3: Barcode | H3: Scent | I3: Size | J3: จำนวน | K3: Delivery Number | L3: Phone | M3: Shipping Name | N3: Address | O3: Remark
A4: =IF(C4="","",ROW()-ROW(tb_PO[[#HEADERS],[Order]])) -> 1 | B4: 45981 | C4: WPO251120001 | D4: WPO251120001-2 | E4: 01_CTW - Central World | F4: {=IF(E4<>"",INDEX(tb_Address[Branch],MATCH(E4,tb_Address[Branch Code],0)),"")} -> สาขาที่ 00001 | G4: 8857128011188 | H4: {=IF(G4<>"",INDEX(tb_MainDatabase[Scent],MATCH(G4,tb_MainDatabase[Barcode],0)),"")} -> 1000 Thousand | I4: {=IF(G4<>"",INDEX(tb_MainDatabase[Size],MATCH(G4,tb_MainDatabase[Barcode],0)),"")} -> 50 ml. | J4: 5 | L4: {=IFERROR(IF(C4=C3,IF(C4="","","-"),INDEX(tb_Address[Store Tel.],MATCH(F4,tb_Address[Branch],0))),"")} -> - | M4: {=IFERROR(IF(C4=C3,IF(C4="","","-"),INDEX(tb_Address[ชื่อผู้รับสินค้า],MATCH(F4,tb_Address[Branch],0))),"")} -> - | N4: {=IFERROR(IF(C4=C3,IF(C4="","","-"),INDEX(tb_Address[ที่อยู่ Store],MATCH(F4,tb_Address[Branch],0))),"")} -> -
A5: =IF(C5="","",ROW()-ROW(tb_PO[[#HEADERS],[Order]])) -> 2 | B5: 45981 | C5: WPO251120001 | D5: WPO251120001-2 | E5: 01_CTW - Central World | F5: {=IF(E5<>"",INDEX(tb_Address[Branch],MATCH(E5,tb_Address[Branch Code],0)),"")} -> สาขาที่ 00001 | G5: 8857128011669 | H5: {=IF(G5<>"",INDEX(tb_MainDatabase[Scent],MATCH(G5,tb_MainDatabase[Barcode],0)),"")} -> Blackest Black | I5: {=IF(G5<>"",INDEX(tb_MainDatabase[Size],MATCH(G5,tb_MainDatabase[Barcode],0)),"")} -> 50 ml. | J5: 2 | L5: {=IFERROR(IF(C5=C4,IF(C5="","","-"),INDEX(tb_Address[Store Tel.],MATCH(F5,tb_Address[Branch],0))),"")} -> - | M5: {=IFERROR(IF(C5=C4,IF(C5="","","-"),INDEX(tb_Address[ชื่อผู้รับสินค้า],MATCH(F5,tb_Address[Branch],0))),"")} -> - | N5: {=IFERROR(IF(C5=C4,IF(C5="","","-"),INDEX(tb_Address[ที่อยู่ Store],MATCH(F5,tb_Address[Branch],0))),"")} -> -
A6: =IF(C6="","",ROW()-ROW(tb_PO[[#HEADERS],[Order]])) -> 3 | B6: 45981 | C6: WPO251120001 | D6: WPO251120001-2 | E6: 01_CTW - Central World | F6: {=IF(E6<>"",INDEX(tb_Address[Branch],MATCH(E6,tb_Address[Branch Code],0)),"")} -> สาขาที่ 00001 | G6: 8857128011225 | H6: {=IF(G6<>"",INDEX(tb_MainDatabase[Scent],MATCH(G6,tb_MainDatabase[Barcode],0)),"")} -> Blind Magnolia | I6: {=IF(G6<>"",INDEX(tb_MainDatabase[Size],MATCH(G6,tb_MainDatabase[Barcode],0)),"")} -> 50 ml. | J6: 5 | L6: {=IFERROR(IF(C6=C5,IF(C6="","","-"),INDEX(tb_Address[Store Tel.],MATCH(F6,tb_Address[Branch],0))),"")} -> - | M6: {=IFERROR(IF(C6=C5,IF(C6="","","-"),INDEX(tb_Address[ชื่อผู้รับสินค้า],MATCH(F6,tb_Address[Branch],0))),"")} -> - | N6: {=IFERROR(IF(C6=C5,IF(C6="","","-"),INDEX(tb_Address[ที่อยู่ Store],MATCH(F6,tb_Address[Branch],0))),"")} -> -
A7: =IF(C7="","",ROW()-ROW(tb_PO[[#HEADERS],[Order]])) -> 4 | B7: 45981 | C7: WPO251120001 | D7: WPO251120001-2 | E7: 01_CTW - Central World | F7: {=IF(E7<>"",INDEX(tb_Address[Branch],MATCH(E7,tb_Address[Branch Code],0)),"")} -> สาขาที่ 00001 | G7: 8857128012021 | H7: {=IF(G7<>"",INDEX(tb_MainDatabase[Scent],MATCH(G7,tb_MainDatabase[Barcode],0)),"")} -> Buoyant | I7: {=IF(G7<>"",INDEX(tb_MainDatabase[Size],MATCH(G7,tb_MainDatabase[Barcode],0)),"")} -> 50 ml. | J7: 5 | L7: {=IFERROR(IF(C7=C6,IF(C7="","","-"),INDEX(tb_Address[Store Tel.],MATCH(F7,tb_Address[Branch],0))),"")} -> - | M7: {=IFERROR(IF(C7=C6,IF(C7="","","-"),INDEX(tb_Address[ชื่อผู้รับสินค้า],MATCH(F7,tb_Address[Branch],0))),"")} -> - | N7: {=IFERROR(IF(C7=C6,IF(C7="","","-"),INDEX(tb_Address[ที่อยู่ Store],MATCH(F7,tb_Address[Branch],0))),"")} -> -
A8: =IF(C8="","",ROW()-ROW(tb_PO[[#HEADERS],[Order]])) -> 5 | B8: 45981 | C8: WPO251120001 | D8: WPO251120001-2 | E8: 01_CTW - Central World | F8: {=IF(E8<>"",INDEX(tb_Address[Branch],MATCH(E8,tb_Address[Branch Code],0)),"")} -> สาขาที่ 00001 | G8: 8857128011331 | H8: {=IF(G8<>"",INDEX(tb_MainDatabase[Scent],MATCH(G8,tb_MainDatabase[Barcode],0)),"")} -> Dionysus X | I8: {=IF(G8<>"",INDEX(tb_MainDatabase[Size],MATCH(G8,tb_MainDatabase[Barcode],0)),"")} -> 50 ml. | J8: 5 | L8: {=IFERROR(IF(C8=C7,IF(C8="","","-"),INDEX(tb_Address[Store Tel.],MATCH(F8,tb_Address[Branch],0))),"")} -> - | M8: {=IFERROR(IF(C8=C7,IF(C8="","","-"),INDEX(tb_Address[ชื่อผู้รับสินค้า],MATCH(F8,tb_Address[Branch],0))),"")} -> - | N8: {=IFERROR(IF(C8=C7,IF(C8="","","-"),INDEX(tb_Address[ที่อยู่ Store],MATCH(F8,tb_Address[Branch],0))),"")} -> -
A9: =IF(C9="","",ROW()-ROW(tb_PO[[#HEADERS],[Order]])) -> 6 | B9: 45981 | C9: WPO251120001 | D9: WPO251120001-2 | E9: 01_CTW - Central World | F9: {=IF(E9<>"",INDEX(tb_Address[Branch],MATCH(E9,tb_Address[Branch Code],0)),"")} -> สาขาที่ 00001 | G9: 8857128011300 | H9: {=IF(G9<>"",INDEX(tb_MainDatabase[Scent],MATCH(G9,tb_MainDatabase[Barcode],0)),"")} -> Dream Island | I9: {=IF(G9<>"",INDEX(tb_MainDatabase[Size],MATCH(G9,tb_MainDatabase[Barcode],0)),"")} -> 50 ml. | J9: 20 | L9: {=IFERROR(IF(C9=C8,IF(C9="","","-"),INDEX(tb_Address[Store Tel.],MATCH(F9,tb_Address[Branch],0))),"")} -> - | M9: {=IFERROR(IF(C9=C8,IF(C9="","","-"),INDEX(tb_Address[ชื่อผู้รับสินค้า],MATCH(F9,tb_Address[Branch],0))),"")} -> - | N9: {=IFERROR(IF(C9=C8,IF(C9="","","-"),INDEX(tb_Address[ที่อยู่ Store],MATCH(F9,tb_Address[Branch],0))),"")} -> -
A10: =IF(C10="","",ROW()-ROW(tb_PO[[#HEADERS],[Order]])) -> 7 | B10: 45981 | C10: WPO251120001 | D10: WPO251120001-2 | E10: 01_CTW - Central World | F10: {=IF(E10<>"",INDEX(tb_Address[Branch],MATCH(E10,tb_Address[Branch Code],0)),"")} -> สาขาที่ 00001 | G10: 8857128011317 | H10: {=IF(G10<>"",INDEX(tb_MainDatabase[Scent],MATCH(G10,tb_MainDatabase[Barcode],0)),"")} -> Eden | I10: {=IF(G10<>"",INDEX(tb_MainDatabase[Size],MATCH(G10,tb_MainDatabase[Barcode],0)),"")} -> 50 ml. | J10: 10 | L10: {=IFERROR(IF(C10=C9,IF(C10="","","-"),INDEX(tb_Address[Store Tel.],MATCH(F10,tb_Address[Branch],0))),"")} -> - | M10: {=IFERROR(IF(C10=C9,IF(C10="","","-"),INDEX(tb_Address[ชื่อผู้รับสินค้า],MATCH(F10,tb_Address[Branch],0))),"")} -> - | N10: {=IFERROR(IF(C10=C9,IF(C10="","","-"),INDEX(tb_Address[ที่อยู่ Store],MATCH(F10,tb_Address[Branch],0))),"")} -> -
A11: =IF(C11="","",ROW()-ROW(tb_PO[[#HEADERS],[Order]])) -> 8 | B11: 45981 | C11: WPO251120001 | D11: WPO251120001-2 | E11: 01_CTW - Central World | F11: {=IF(E11<>"",INDEX(tb_Address[Branch],MATCH(E11,tb_Address[Branch Code],0)),"")} -> สาขาที่ 00001 | G11: 8857128011133 | H11: {=IF(G11<>"",INDEX(tb_MainDatabase[Scent],MATCH(G11,tb_MainDatabase[Barcode],0)),"")} -> Excalibur (EDP) | I11: {=IF(G11<>"",INDEX(tb_MainDatabase[Size],MATCH(G11,tb_MainDatabase[Barcode],0)),"")} -> 50 ml. | J11: 5 | L11: {=IFERROR(IF(C11=C10,IF(C11="","","-"),INDEX(tb_Address[Store Tel.],MATCH(F11,tb_Address[Branch],0))),"")} -> - | M11: {=IFERROR(IF(C11=C10,IF(C11="","","-"),INDEX(tb_Address[ชื่อผู้รับสินค้า],MATCH(F11,tb_Address[Branch],0))),"")} -> - | N11: {=IFERROR(IF(C11=C10,IF(C11="","","-"),INDEX(tb_Address[ที่อยู่ Store],MATCH(F11,tb_Address[Branch],0))),"")} -> -
A12: =IF(C12="","",ROW()-ROW(tb_PO[[#HEADERS],[Order]])) -> 9 | B12: 45981 | C12: WPO251120001 | D12: WPO251120001-2 | E12: 01_CTW - Central World | F12: {=IF(E12<>"",INDEX(tb_Address[Branch],MATCH(E12,tb_Address[Branch Code],0)),"")} -> สาขาที่ 00001 | G12: 8857128011591 | H12: {=IF(G12<>"",INDEX(tb_MainDatabase[Scent],MATCH(G12,tb_MainDatabase[Barcode],0)),"")} -> Gambling34+35 | I12: {=IF(G12<>"",INDEX(tb_MainDatabase[Size],MATCH(G12,tb_MainDatabase[Barcode],0)),"")} -> 50 ml. | J12: 5 | L12: {=IFERROR(IF(C12=#REF!,IF(C12="","","-"),INDEX(tb_Address[Store Tel.],MATCH(F12,tb_Address[Branch],0))),"")} | M12: {=IFERROR(IF(C12=#REF!,IF(C12="","","-"),INDEX(tb_Address[ชื่อผู้รับสินค้า],MATCH(F12,tb_Address[Branch],0))),"")} | N12: {=IFERROR(IF(C12=#REF!,IF(C12="","","-"),INDEX(tb_Address[ที่อยู่ Store],MATCH(F12,tb_Address[Branch],0))),"")}
A13: =IF(C13="","",ROW()-ROW(tb_PO[[#HEADERS],[Order]])) -> 10 | B13: 45981 | C13: WPO251120001 | D13: WPO251120001-2 | E13: 01_CTW - Central World | F13: {=IF(E13<>"",INDEX(tb_Address[Branch],MATCH(E13,tb_Address[Branch Code],0)),"")} -> สาขาที่ 00001 | G13: 8857128011287 | H13: {=IF(G13<>"",INDEX(tb_MainDatabase[Scent],MATCH(G13,tb_MainDatabase[Barcode],0)),"")} -> Never Blue | I13: {=IF(G13<>"",INDEX(tb_MainDatabase[Size],MATCH(G13,tb_MainDatabase[Barcode],0)),"")} -> 50 ml. | J13: 20 | L13: {=IFERROR(IF(C13=C12,IF(C13="","","-"),INDEX(tb_Address[Store Tel.],MATCH(F13,tb_Address[Branch],0))),"")} -> - | M13: {=IFERROR(IF(C13=C12,IF(C13="","","-"),INDEX(tb_Address[ชื่อผู้รับสินค้า],MATCH(F13,tb_Address[Branch],0))),"")} -> - | N13: {=IFERROR(IF(C13=C12,IF(C13="","","-"),INDEX(tb_Address[ที่อยู่ Store],MATCH(F13,tb_Address[Branch],0))),"")} -> -
A14: =IF(C14="","",ROW()-ROW(tb_PO[[#HEADERS],[Order]])) -> 11 | B14: 45981 | C14: WPO251120001 | D14: WPO251120001-2 | E14: 01_CTW - Central World | F14: {=IF(E14<>"",INDEX(tb_Address[Branch],MATCH(E14,tb_Address[Branch Code],0)),"")} -> สาขาที่ 00001 | G14: 8857128011119 | H14: {=IF(G14<>"",INDEX(tb_MainDatabase[Scent],MATCH(G14,tb_MainDatabase[Barcode],0)),"")} -> Secret of Peach | I14: {=IF(G14<>"",INDEX(tb_MainDatabase[Size],MATCH(G14,tb_MainDatabase[Barcode],0)),"")} -> 50 ml. | J14: 20 | L14: {=IFERROR(IF(C14=C13,IF(C14="","","-"),INDEX(tb_Address[Store Tel.],MATCH(F14,tb_Address[Branch],0))),"")} -> - | M14: {=IFERROR(IF(C14=C13,IF(C14="","","-"),INDEX(tb_Address[ชื่อผู้รับสินค้า],MATCH(F14,tb_Address[Branch],0))),"")} -> - | N14: {=IFERROR(IF(C14=C13,IF(C14="","","-"),INDEX(tb_Address[ที่อยู่ Store],MATCH(F14,tb_Address[Branch],0))),"")} -> -
A15: =IF(C15="","",ROW()-ROW(tb_PO[[#HEADERS],[Order]])) -> 12 | B15: 45981 | C15: WPO251120001 | D15: WPO251120001-2 | E15: 01_CTW - Central World | F15: {=IF(E15<>"",INDEX(tb_Address[Branch],MATCH(E15,tb_Address[Branch Code],0)),"")} -> สาขาที่ 00001 | G15: 8857128011171 | H15: {=IF(G15<>"",INDEX(tb_MainDatabase[Scent],MATCH(G15,tb_MainDatabase[Barcode],0)),"")} -> Senorita | I15: {=IF(G15<>"",INDEX(tb_MainDatabase[Size],MATCH(G15,tb_MainDatabase[Barcode],0)),"")} -> 50 ml. | J15: 20 | L15: {=IFERROR(IF(C15=C14,IF(C15="","","-"),INDEX(tb_Address[Store Tel.],MATCH(F15,tb_Address[Branch],0))),"")} -> - | M15: {=IFERROR(IF(C15=C14,IF(C15="","","-"),INDEX(tb_Address[ชื่อผู้รับสินค้า],MATCH(F15,tb_Address[Branch],0))),"")} -> - | N15: {=IFERROR(IF(C15=C14,IF(C15="","","-"),INDEX(tb_Address[ที่อยู่ Store],MATCH(F15,tb_Address[Branch],0))),"")} -> -
A16: =IF(C16="","",ROW()-ROW(tb_PO[[#HEADERS],[Order]])) -> 13 | B16: 45981 | C16: WPO251120001 | D16: WPO251120001-2 | E16: 01_CTW - Central World | F16: {=IF(E16<>"",INDEX(tb_Address[Branch],MATCH(E16,tb_Address[Branch Code],0)),"")} -> สาขาที่ 00001 | G16: 8857128011294 | H16: {=IF(G16<>"",INDEX(tb_MainDatabase[Scent],MATCH(G16,tb_MainDatabase[Barcode],0)),"")} -> Shadow De Bacci Light | I16: {=IF(G16<>"",INDEX(tb_MainDatabase[Size],MATCH(G16,tb_MainDatabase[Barcode],0)),"")} -> 50 ml. | J16: 5 | L16: {=IFERROR(IF(C16=C15,IF(C16="","","-"),INDEX(tb_Address[Store Tel.],MATCH(F16,tb_Address[Branch],0))),"")} -> - | M16: {=IFERROR(IF(C16=C15,IF(C16="","","-"),INDEX(tb_Address[ชื่อผู้รับสินค้า],MATCH(F16,tb_Address[Branch],0))),"")} -> - | N16: {=IFERROR(IF(C16=C15,IF(C16="","","-"),INDEX(tb_Address[ที่อยู่ Store],MATCH(F16,tb_Address[Branch],0))),"")} -> -
A17: =IF(C17="","",ROW()-ROW(tb_PO[[#HEADERS],[Order]])) -> 14 | B17: 45981 | C17: WPO251120001 | D17: WPO251120001-2 | E17: 01_CTW - Central World | F17: {=IF(E17<>"",INDEX(tb_Address[Branch],MATCH(E17,tb_Address[Branch Code],0)),"")} -> สาขาที่ 00001 | G17: 8857128011140 | H17: {=IF(G17<>"",INDEX(tb_MainDatabase[Scent],MATCH(G17,tb_MainDatabase[Barcode],0)),"")} -> Sicilia | I17: {=IF(G17<>"",INDEX(tb_MainDatabase[Size],MATCH(G17,tb_MainDatabase[Barcode],0)),"")} -> 50 ml. | J17: 10 | L17: {=IFERROR(IF(C17=C16,IF(C17="","","-"),INDEX(tb_Address[Store Tel.],MATCH(F17,tb_Address[Branch],0))),"")} -> - | M17: {=IFERROR(IF(C17=C16,IF(C17="","","-"),INDEX(tb_Address[ชื่อผู้รับสินค้า],MATCH(F17,tb_Address[Branch],0))),"")} -> - | N17: {=IFERROR(IF(C17=C16,IF(C17="","","-"),INDEX(tb_Address[ที่อยู่ Store],MATCH(F17,tb_Address[Branch],0))),"")} -> -
A18: =IF(C18="","",ROW()-ROW(tb_PO[[#HEADERS],[Order]])) -> 15 | B18: 45981 | C18: WPO251120001 | D18: WPO251120001-2 | E18: 01_CTW - Central World | F18: {=IF(E18<>"",INDEX(tb_Address[Branch],MATCH(E18,tb_Address[Branch Code],0)),"")} -> สาขาที่ 00001 | G18: 8857128011713 | H18: {=IF(G18<>"",INDEX(tb_MainDatabase[Scent],MATCH(G18,tb_MainDatabase[Barcode],0)),"")} -> Sparkling Mandarin | I18: {=IF(G18<>"",INDEX(tb_MainDatabase[Size],MATCH(G18,tb_MainDatabase[Barcode],0)),"")} -> 50 ml. | J18: 2 | L18: {=IFERROR(IF(C18=C17,IF(C18="","","-"),INDEX(tb_Address[Store Tel.],MATCH(F18,tb_Address[Branch],0))),"")} -> - | M18: {=IFERROR(IF(C18=C17,IF(C18="","","-"),INDEX(tb_Address[ชื่อผู้รับสินค้า],MATCH(F18,tb_Address[Branch],0))),"")} -> - | N18: {=IFERROR(IF(C18=C17,IF(C18="","","-"),INDEX(tb_Address[ที่อยู่ Store],MATCH(F18,tb_Address[Branch],0))),"")} -> -
A19: =IF(C19="","",ROW()-ROW(tb_PO[[#HEADERS],[Order]])) -> 16 | B19: 45981 | C19: WPO251120001 | D19: WPO251120001-2 | E19: 01_CTW - Central World | F19: {=IF(E19<>"",INDEX(tb_Address[Branch],MATCH(E19,tb_Address[Branch Code],0)),"")} -> สาขาที่ 00001 | G19: 8857128011096 | H19: {=IF(G19<>"",INDEX(tb_MainDatabase[Scent],MATCH(G19,tb_MainDatabase[Barcode],0)),"")} -> Teenage Dream | I19: {=IF(G19<>"",INDEX(tb_MainDatabase[Size],MATCH(G19,tb_MainDatabase[Barcode],0)),"")} -> 50 ml. | J19: 5 | L19: {=IFERROR(IF(C19=C18,IF(C19="","","-"),INDEX(tb_Address[Store Tel.],MATCH(F19,tb_Address[Branch],0))),"")} -> - | M19: {=IFERROR(IF(C19=C18,IF(C19="","","-"),INDEX(tb_Address[ชื่อผู้รับสินค้า],MATCH(F19,tb_Address[Branch],0))),"")} -> - | N19: {=IFERROR(IF(C19=C18,IF(C19="","","-"),INDEX(tb_Address[ที่อยู่ Store],MATCH(F19,tb_Address[Branch],0))),"")} -> -
A20: =IF(C20="","",ROW()-ROW(tb_PO[[#HEADERS],[Order]])) -> 17 | B20: 45981 | C20: WPO251120001 | D20: WPO251120001-2 | E20: 01_CTW - Central World | F20: {=IF(E20<>"",INDEX(tb_Address[Branch],MATCH(E20,tb_Address[Branch Code],0)),"")} -> สาขาที่ 00001 | G20: 8857128011522 | H20: {=IF(G20<>"",INDEX(tb_MainDatabase[Scent],MATCH(G20,tb_MainDatabase[Barcode],0)),"")} -> Velvet Oud | I20: {=IF(G20<>"",INDEX(tb_MainDatabase[Size],MATCH(G20,tb_MainDatabase[Barcode],0)),"")} -> 50 ml. | J20: 10 | L20: {=IFERROR(IF(C20=C19,IF(C20="","","-"),INDEX(tb_Address[Store Tel.],MATCH(F20,tb_Address[Branch],0))),"")} -> - | M20: {=IFERROR(IF(C20=C19,IF(C20="","","-"),INDEX(tb_Address[ชื่อผู้รับสินค้า],MATCH(F20,tb_Address[Branch],0))),"")} -> - | N20: {=IFERROR(IF(C20=C19,IF(C20="","","-"),INDEX(tb_Address[ที่อยู่ Store],MATCH(F20,tb_Address[Branch],0))),"")} -> -
A21: =IF(C21="","",ROW()-ROW(tb_PO[[#HEADERS],[Order]])) -> 18 | B21: 45981 | C21: WPO251120001 | D21: WPO251120001-2 | E21: 01_CTW - Central World | F21: {=IF(E21<>"",INDEX(tb_Address[Branch],MATCH(E21,tb_Address[Branch Code],0)),"")} -> สาขาที่ 00001 | G21: 8857128011256 | H21: {=IF(G21<>"",INDEX(tb_MainDatabase[Scent],MATCH(G21,tb_MainDatabase[Barcode],0)),"")} -> Virgin X | I21: {=IF(G21<>"",INDEX(tb_MainDatabase[Size],MATCH(G21,tb_MainDatabase[Barcode],0)),"")} -> 50 ml. | J21: 10 | L21: {=IFERROR(IF(C21=C20,IF(C21="","","-"),INDEX(tb_Address[Store Tel.],MATCH(F21,tb_Address[Branch],0))),"")} -> - | M21: {=IFERROR(IF(C21=C20,IF(C21="","","-"),INDEX(tb_Address[ชื่อผู้รับสินค้า],MATCH(F21,tb_Address[Branch],0))),"")} -> - | N21: {=IFERROR(IF(C21=C20,IF(C21="","","-"),INDEX(tb_Address[ที่อยู่ Store],MATCH(F21,tb_Address[Branch],0))),"")} -> -
A22: =IF(C22="","",ROW()-ROW(tb_PO[[#HEADERS],[Order]])) -> 19 | B22: 45981 | C22: WPO251120001 | D22: WPO251120001-2 | E22: 01_CTW - Central World | F22: {=IF(E22<>"",INDEX(tb_Address[Branch],MATCH(E22,tb_Address[Branch Code],0)),"")} -> สาขาที่ 00001 | G22: 8857128011072 | H22: {=IF(G22<>"",INDEX(tb_MainDatabase[Scent],MATCH(G22,tb_MainDatabase[Barcode],0)),"")} -> Beyond | I22: {=IF(G22<>"",INDEX(tb_MainDatabase[Size],MATCH(G22,tb_MainDatabase[Barcode],0)),"")} -> 50 ml. | J22: 10 | L22: {=IFERROR(IF(C22=C21,IF(C22="","","-"),INDEX(tb_Address[Store Tel.],MATCH(F22,tb_Address[Branch],0))),"")} -> - | M22: {=IFERROR(IF(C22=C21,IF(C22="","","-"),INDEX(tb_Address[ชื่อผู้รับสินค้า],MATCH(F22,tb_Address[Branch],0))),"")} -> - | N22: {=IFERROR(IF(C22=C21,IF(C22="","","-"),INDEX(tb_Address[ที่อยู่ Store],MATCH(F22,tb_Address[Branch],0))),"")} -> -
A23: =IF(C23="","",ROW()-ROW(tb_PO[[#HEADERS],[Order]])) -> 20 | B23: 45981 | C23: WPO251120001 | D23: WPO251120001-2 | E23: 01_CTW - Central World | F23: {=IF(E23<>"",INDEX(tb_Address[Branch],MATCH(E23,tb_Address[Branch Code],0)),"")} -> สาขาที่ 00001 | G23: 8857128011010 | H23: {=IF(G23<>"",INDEX(tb_MainDatabase[Scent],MATCH(G23,tb_MainDatabase[Barcode],0)),"")} -> Dynasty | I23: {=IF(G23<>"",INDEX(tb_MainDatabase[Size],MATCH(G23,tb_MainDatabase[Barcode],0)),"")} -> 50 ml. | J23: 5 | L23: {=IFERROR(IF(C23=C22,IF(C23="","","-"),INDEX(tb_Address[Store Tel.],MATCH(F23,tb_Address[Branch],0))),"")} -> - | M23: {=IFERROR(IF(C23=C22,IF(C23="","","-"),INDEX(tb_Address[ชื่อผู้รับสินค้า],MATCH(F23,tb_Address[Branch],0))),"")} -> - | N23: {=IFERROR(IF(C23=C22,IF(C23="","","-"),INDEX(tb_Address[ที่อยู่ Store],MATCH(F23,tb_Address[Branch],0))),"")} -> -
A24: =IF(C24="","",ROW()-ROW(tb_PO[[#HEADERS],[Order]])) -> 21 | B24: 45981 | C24: WPO251120001 | D24: WPO251120001-2 | E24: 01_CTW - Central World | F24: {=IF(E24<>"",INDEX(tb_Address[Branch],MATCH(E24,tb_Address[Branch Code],0)),"")} -> สาขาที่ 00001 | G24: 8857128011034 | H24: {=IF(G24<>"",INDEX(tb_MainDatabase[Scent],MATCH(G24,tb_MainDatabase[Barcode],0)),"")} -> Hercules | I24: {=IF(G24<>"",INDEX(tb_MainDatabase[Size],MATCH(G24,tb_MainDatabase[Barcode],0)),"")} -> 50 ml. | J24: 5 | L24: {=IFERROR(IF(C24=C23,IF(C24="","","-"),INDEX(tb_Address[Store Tel.],MATCH(F24,tb_Address[Branch],0))),"")} -> - | M24: {=IFERROR(IF(C24=C23,IF(C24="","","-"),INDEX(tb_Address[ชื่อผู้รับสินค้า],MATCH(F24,tb_Address[Branch],0))),"")} -> - | N24: {=IFERROR(IF(C24=C23,IF(C24="","","-"),INDEX(tb_Address[ที่อยู่ Store],MATCH(F24,tb_Address[Branch],0))),"")} -> -
... A129: =IF(C129="","",ROW()-ROW(tb_PO[[#HEADERS],[Order]])) -> 126 | B129: 46021 | C129: WP0251230001 | D129: WP0251230001-1 | E129: 01_CTW - Central World | F129: {=IF(E129<>"",INDEX(tb_Address[Branch],MATCH(E129,tb_Address[Branch Code],0)),"")} -> สาขาที่ 00001 | G129: 8857128012145 | H129: {=IF(G129<>"",INDEX(tb_MainDatabase[Scent],MATCH(G129,tb_MainDatabase[Barcode],0)),"")} -> Soir | I129: {=IF(G129<>"",INDEX(tb_MainDatabase[Size],MATCH(G129,tb_MainDatabase[Barcode],0)),"")} -> 30 ml. | J129: 5 | L129: {=IFERROR(IF(C129=C128,IF(C129="","","-"),INDEX(tb_Address[Store Tel.],MATCH(F129,tb_Address[Branch],0))),"")} -> - | M129: {=IFERROR(IF(C129=C128,IF(C129="","","-"),INDEX(tb_Address[ชื่อผู้รับสินค้า],MATCH(F129,tb_Address[Branch],0))),"")} -> - | N129: {=IFERROR(IF(C129=C128,IF(C129="","","-"),INDEX(tb_Address[ที่อยู่ Store],MATCH(F129,tb_Address[Branch],0))),"")} -> -
A130: =IF(C130="","",ROW()-ROW(tb_PO[[#HEADERS],[Order]])) -> 127 | B130: 46021 | C130: WP0251230001 | D130: WP0251230001-1 | E130: 01_CTW - Central World | F130: {=IF(E130<>"",INDEX(tb_Address[Branch],MATCH(E130,tb_Address[Branch Code],0)),"")} -> สาขาที่ 00001 | G130: GER50 | H130: {=IF(G130<>"",INDEX(tb_MainDatabase[Scent],MATCH(G130,tb_MainDatabase[Barcode],0)),"")} -> Gentle Elixir TRY ME! | I130: {=IF(G130<>"",INDEX(tb_MainDatabase[Size],MATCH(G130,tb_MainDatabase[Barcode],0)),"")} -> 50 ml. | J130: 1 | L130: {=IFERROR(IF(C130=C129,IF(C130="","","-"),INDEX(tb_Address[Store Tel.],MATCH(F130,tb_Address[Branch],0))),"")} -> - | M130: {=IFERROR(IF(C130=C129,IF(C130="","","-"),INDEX(tb_Address[ชื่อผู้รับสินค้า],MATCH(F130,tb_Address[Branch],0))),"")} -> - | N130: {=IFERROR(IF(C130=C129,IF(C130="","","-"),INDEX(tb_Address[ที่อยู่ Store],MATCH(F130,tb_Address[Branch],0))),"")} -> -
A131: =IF(C131="","",ROW()-ROW(tb_PO[[#HEADERS],[Order]])) -> 128 | B131: 46021 | C131: WP0251230001 | D131: WP0251230001-1 | E131: 01_CTW - Central World | F131: {=IF(E131<>"",INDEX(tb_Address[Branch],MATCH(E131,tb_Address[Branch Code],0)),"")} -> สาขาที่ 00001 | G131: SOM50 | H131: {=IF(G131<>"",INDEX(tb_MainDatabase[Scent],MATCH(G131,tb_MainDatabase[Barcode],0)),"")} -> Soir TRY ME! | I131: {=IF(G131<>"",INDEX(tb_MainDatabase[Size],MATCH(G131,tb_MainDatabase[Barcode],0)),"")} -> 50 ml. | J131: 1 | L131: {=IFERROR(IF(C131=C130,IF(C131="","","-"),INDEX(tb_Address[Store Tel.],MATCH(F131,tb_Address[Branch],0))),"")} -> - | M131: {=IFERROR(IF(C131=C130,IF(C131="","","-"),INDEX(tb_Address[ชื่อผู้รับสินค้า],MATCH(F131,tb_Address[Branch],0))),"")} -> - | N131: {=IFERROR(IF(C131=C130,IF(C131="","","-"),INDEX(tb_Address[ที่อยู่ Store],MATCH(F131,tb_Address[Branch],0))),"")} -> -
A132: =IF(C132="","",ROW()-ROW(tb_PO[[#HEADERS],[Order]])) -> 129 | B132: 46021 | C132: WP0251230001 | D132: WP0251230001-1 | E132: 01_CTW - Central World | F132: {=IF(E132<>"",INDEX(tb_Address[Branch],MATCH(E132,tb_Address[Branch Code],0)),"")} -> สาขาที่ 00001 | G132: SEM50 | H132: {=IF(G132<>"",INDEX(tb_MainDatabase[Scent],MATCH(G132,tb_MainDatabase[Barcode],0)),"")} -> Senorita TRY ME! | I132: {=IF(G132<>"",INDEX(tb_MainDatabase[Size],MATCH(G132,tb_MainDatabase[Barcode],0)),"")} -> 50 ml. | J132: 1 | L132: {=IFERROR(IF(C132=C131,IF(C132="","","-"),INDEX(tb_Address[Store Tel.],MATCH(F132,tb_Address[Branch],0))),"")} -> - | M132: {=IFERROR(IF(C132=C131,IF(C132="","","-"),INDEX(tb_Address[ชื่อผู้รับสินค้า],MATCH(F132,tb_Address[Branch],0))),"")} -> - | N132: {=IFERROR(IF(C132=C131,IF(C132="","","-"),INDEX(tb_Address[ที่อยู่ Store],MATCH(F132,tb_Address[Branch],0))),"")} -> -
A133: =IF(C133="","",ROW()-ROW(tb_PO[[#HEADERS],[Order]])) -> 130 | B133: 46021 | C133: WP0251230001 | D133: WP0251230001-1 | E133: 01_CTW - Central World | F133: {=IF(E133<>"",INDEX(tb_Address[Branch],MATCH(E133,tb_Address[Branch Code],0)),"")} -> สาขาที่ 00001 | G133: 8857128012130 | H133: {=IF(G133<>"",INDEX(tb_MainDatabase[Scent],MATCH(G133,tb_MainDatabase[Barcode],0)),"")} -> Tumbler CYOC (White) | I133: {=IF(G133<>"",INDEX(tb_MainDatabase[Size],MATCH(G133,tb_MainDatabase[Barcode],0)),"")} -> White | J133: 10 | L133: {=IFERROR(IF(C133=C132,IF(C133="","","-"),INDEX(tb_Address[Store Tel.],MATCH(F133,tb_Address[Branch],0))),"")} -> - | M133: {=IFERROR(IF(C133=C132,IF(C133="","","-"),INDEX(tb_Address[ชื่อผู้รับสินค้า],MATCH(F133,tb_Address[Branch],0))),"")} -> - | N133: {=IFERROR(IF(C133=C132,IF(C133="","","-"),INDEX(tb_Address[ที่อยู่ Store],MATCH(F133,tb_Address[Branch],0))),"")} -> -
A134: =IF(C134="","",ROW()-ROW(tb_PO[[#HEADERS],[Order]])) -> 131 | B134: 46021 | C134: WP0251230001 | D134: WP0251230001-1 | E134: 01_CTW - Central World | F134: {=IF(E134<>"",INDEX(tb_Address[Branch],MATCH(E134,tb_Address[Branch Code],0)),"")} -> สาขาที่ 00001 | G134: 8857128012132 | H134: {=IF(G134<>"",INDEX(tb_MainDatabase[Scent],MATCH(G134,tb_MainDatabase[Barcode],0)),"")} -> Cloth BAG CYOC | I134: {=IF(G134<>"",INDEX(tb_MainDatabase[Size],MATCH(G134,tb_MainDatabase[Barcode],0)),"")} -> Size M | J134: 20 | L134: {=IFERROR(IF(C134=C133,IF(C134="","","-"),INDEX(tb_Address[Store Tel.],MATCH(F134,tb_Address[Branch],0))),"")} -> - | M134: {=IFERROR(IF(C134=C133,IF(C134="","","-"),INDEX(tb_Address[ชื่อผู้รับสินค้า],MATCH(F134,tb_Address[Branch],0))),"")} -> - | N134: {=IFERROR(IF(C134=C133,IF(C134="","","-"),INDEX(tb_Address[ที่อยู่ Store],MATCH(F134,tb_Address[Branch],0))),"")} -> -
A135: =IF(C135="","",ROW()-ROW(tb_PO[[#HEADERS],[Order]])) -> 132 | B135: 46025 | C135: WP0260103001 | D135: WP0260103001-1 | E135: 01_CTW - Central World | G135: 8857128012130 | H135: {=IF(G135<>"",INDEX(tb_MainDatabase[Scent],MATCH(G135,tb_MainDatabase[Barcode],0)),"")} -> Tumbler CYOC (White) | I135: {=IF(G135<>"",INDEX(tb_MainDatabase[Size],MATCH(G135,tb_MainDatabase[Barcode],0)),"")} -> White | J135: 6 | L135: {=IFERROR(IF(C135=C134,IF(C135="","","-"),INDEX(tb_Address[Store Tel.],MATCH(F135,tb_Address[Branch],0))),"")} | M135: {=IFERROR(IF(C135=C134,IF(C135="","","-"),INDEX(tb_Address[ชื่อผู้รับสินค้า],MATCH(F135,tb_Address[Branch],0))),"")} | N135: {=IFERROR(IF(C135=C134,IF(C135="","","-"),INDEX(tb_Address[ที่อยู่ Store],MATCH(F135,tb_Address[Branch],0))),"")}
A136: =IF(C136="","",ROW()-ROW(tb_PO[[#HEADERS],[Order]])) -> 133 | B136: 46025 | C136: WP0260103001 | D136: WP0260103001-1 | E136: 01_CTW - Central World | G136: 8857128012132 | H136: {=IF(G136<>"",INDEX(tb_MainDatabase[Scent],MATCH(G136,tb_MainDatabase[Barcode],0)),"")} -> Cloth BAG CYOC | I136: {=IF(G136<>"",INDEX(tb_MainDatabase[Size],MATCH(G136,tb_MainDatabase[Barcode],0)),"")} -> Size M | J136: 10 | L136: {=IFERROR(IF(C136=C135,IF(C136="","","-"),INDEX(tb_Address[Store Tel.],MATCH(F136,tb_Address[Branch],0))),"")} -> - | M136: {=IFERROR(IF(C136=C135,IF(C136="","","-"),INDEX(tb_Address[ชื่อผู้รับสินค้า],MATCH(F136,tb_Address[Branch],0))),"")} -> - | N136: {=IFERROR(IF(C136=C135,IF(C136="","","-"),INDEX(tb_Address[ที่อยู่ Store],MATCH(F136,tb_Address[Branch],0))),"")} -> -
A137: =IF(C137="","",ROW()-ROW(tb_PO[[#HEADERS],[Order]])) -> 134 | B137: 46025 | C137: WP0260103001 | D137: WP0260103001-1 | E137: 01_CTW - Central World | F137: {=IF(E137<>"",INDEX(tb_Address[Branch],MATCH(E137,tb_Address[Branch Code],0)),"")} -> สาขาที่ 00001 | G137: 8857128012017 | H137: {=IF(G137<>"",INDEX(tb_MainDatabase[Scent],MATCH(G137,tb_MainDatabase[Barcode],0)),"")} -> Zeus | I137: {=IF(G137<>"",INDEX(tb_MainDatabase[Size],MATCH(G137,tb_MainDatabase[Barcode],0)),"")} -> 4 ml. | J137: 10 | L137: {=IFERROR(IF(C137=C136,IF(C137="","","-"),INDEX(tb_Address[Store Tel.],MATCH(F137,tb_Address[Branch],0))),"")} -> - | M137: {=IFERROR(IF(C137=C136,IF(C137="","","-"),INDEX(tb_Address[ชื่อผู้รับสินค้า],MATCH(F137,tb_Address[Branch],0))),"")} -> - | N137: {=IFERROR(IF(C137=C136,IF(C137="","","-"),INDEX(tb_Address[ที่อยู่ Store],MATCH(F137,tb_Address[Branch],0))),"")} -> -
A138: =IF(C138="","",ROW()-ROW(tb_PO[[#HEADERS],[Order]])) -> 135 | B138: 46025 | C138: WP0260103001 | D138: WP0260103001-1 | E138: 01_CTW - Central World | F138: {=IF(E138<>"",INDEX(tb_Address[Branch],MATCH(E138,tb_Address[Branch Code],0)),"")} -> สาขาที่ 00001 | G138: 8857128012016 | H138: {=IF(G138<>"",INDEX(tb_MainDatabase[Scent],MATCH(G138,tb_MainDatabase[Barcode],0)),"")} -> La Belle | I138: {=IF(G138<>"",INDEX(tb_MainDatabase[Size],MATCH(G138,tb_MainDatabase[Barcode],0)),"")} -> 4 ml. | J138: 10 | L138: {=IFERROR(IF(C138=C137,IF(C138="","","-"),INDEX(tb_Address[Store Tel.],MATCH(F138,tb_Address[Branch],0))),"")} -> - | M138: {=IFERROR(IF(C138=C137,IF(C138="","","-"),INDEX(tb_Address[ชื่อผู้รับสินค้า],MATCH(F138,tb_Address[Branch],0))),"")} -> - | N138: {=IFERROR(IF(C138=C137,IF(C138="","","-"),INDEX(tb_Address[ที่อยู่ Store],MATCH(F138,tb_Address[Branch],0))),"")} -> -
A139: =IF(C139="","",ROW()-ROW(tb_PO[[#HEADERS],[Order]])) -> 136 | B139: 46025 | C139: WP0260103001 | D139: WP0260103001-1 | E139: 01_CTW - Central World | F139: {=IF(E139<>"",INDEX(tb_Address[Branch],MATCH(E139,tb_Address[Branch Code],0)),"")} -> สาขาที่ 00001 | G139: 8857128012071 | H139: {=IF(G139<>"",INDEX(tb_MainDatabase[Scent],MATCH(G139,tb_MainDatabase[Barcode],0)),"")} -> Teenage Dream | I139: {=IF(G139<>"",INDEX(tb_MainDatabase[Size],MATCH(G139,tb_MainDatabase[Barcode],0)),"")} -> 4 ml. | J139: 10 | L139: {=IFERROR(IF(C139=C138,IF(C139="","","-"),INDEX(tb_Address[Store Tel.],MATCH(F139,tb_Address[Branch],0))),"")} -> - | M139: {=IFERROR(IF(C139=C138,IF(C139="","","-"),INDEX(tb_Address[ชื่อผู้รับสินค้า],MATCH(F139,tb_Address[Branch],0))),"")} -> - | N139: {=IFERROR(IF(C139=C138,IF(C139="","","-"),INDEX(tb_Address[ที่อยู่ Store],MATCH(F139,tb_Address[Branch],0))),"")} -> -
A140: =IF(C140="","",ROW()-ROW(tb_PO[[#HEADERS],[Order]])) -> 137 | B140: 46025 | C140: WP0260103001 | D140: WP0260103001-1 | E140: 01_CTW - Central World | F140: {=IF(E140<>"",INDEX(tb_Address[Branch],MATCH(E140,tb_Address[Branch Code],0)),"")} -> สาขาที่ 00001 | G140: 8857128012033 | H140: {=IF(G140<>"",INDEX(tb_MainDatabase[Scent],MATCH(G140,tb_MainDatabase[Barcode],0)),"")} -> Beyond | I140: {=IF(G140<>"",INDEX(tb_MainDatabase[Size],MATCH(G140,tb_MainDatabase[Barcode],0)),"")} -> 4 ml. | J140: 10 | L140: {=IFERROR(IF(C140=C139,IF(C140="","","-"),INDEX(tb_Address[Store Tel.],MATCH(F140,tb_Address[Branch],0))),"")} -> - | M140: {=IFERROR(IF(C140=C139,IF(C140="","","-"),INDEX(tb_Address[ชื่อผู้รับสินค้า],MATCH(F140,tb_Address[Branch],0))),"")} -> - | N140: {=IFERROR(IF(C140=C139,IF(C140="","","-"),INDEX(tb_Address[ที่อยู่ Store],MATCH(F140,tb_Address[Branch],0))),"")} -> -
A141: =IF(C141="","",ROW()-ROW(tb_PO[[#HEADERS],[Order]])) -> 138 | B141: 46025 | C141: WP0260103001 | D141: WP0260103001-1 | E141: 01_CTW - Central World | F141: {=IF(E141<>"",INDEX(tb_Address[Branch],MATCH(E141,tb_Address[Branch Code],0)),"")} -> สาขาที่ 00001 | G141: 8857128012134 | H141: {=IF(G141<>"",INDEX(tb_MainDatabase[Scent],MATCH(G141,tb_MainDatabase[Barcode],0)),"")} -> ถุงกระดาษ Size M | I141: {=IF(G141<>"",INDEX(tb_MainDatabase[Size],MATCH(G141,tb_MainDatabase[Barcode],0)),"")} -> Size M | J141: 40 | L141: {=IFERROR(IF(C141=C140,IF(C141="","","-"),INDEX(tb_Address[Store Tel.],MATCH(F141,tb_Address[Branch],0))),"")} -> - | M141: {=IFERROR(IF(C141=C140,IF(C141="","","-"),INDEX(tb_Address[ชื่อผู้รับสินค้า],MATCH(F141,tb_Address[Branch],0))),"")} -> - | N141: {=IFERROR(IF(C141=C140,IF(C141="","","-"),INDEX(tb_Address[ที่อยู่ Store],MATCH(F141,tb_Address[Branch],0))),"")} -> -
A142: =IF(C142="","",ROW()-ROW(tb_PO[[#HEADERS],[Order]])) -> 139 | B142: 46035 | C142: WP0260113001 | D142: WP0260113001-1 | E142: 01_CTW - Central World | F142: {=IF(E142<>"",INDEX(tb_Address[Branch],MATCH(E142,tb_Address[Branch Code],0)),"")} -> สาขาที่ 00001 | G142: 8857128012018 | H142: {=IF(G142<>"",INDEX(tb_MainDatabase[Scent],MATCH(G142,tb_MainDatabase[Barcode],0)),"")} -> Aqua | I142: {=IF(G142<>"",INDEX(tb_MainDatabase[Size],MATCH(G142,tb_MainDatabase[Barcode],0)),"")} -> 50 ml. | J142: 5 | L142: {=IFERROR(IF(C142=C141,IF(C142="","","-"),INDEX(tb_Address[Store Tel.],MATCH(F142,tb_Address[Branch],0))),"")} -> - | M142: {=IFERROR(IF(C142=C141,IF(C142="","","-"),INDEX(tb_Address[ชื่อผู้รับสินค้า],MATCH(F142,tb_Address[Branch],0))),"")} -> - | N142: {=IFERROR(IF(C142=C141,IF(C142="","","-"),INDEX(tb_Address[ที่อยู่ Store],MATCH(F142,tb_Address[Branch],0))),"")} -> -
A143: =IF(C143="","",ROW()-ROW(tb_PO[[#HEADERS],[Order]])) -> 140 | B143: 46035 | C143: WP0260113001 | D143: WP0260113001-1 | E143: 01_CTW - Central World | F143: {=IF(E143<>"",INDEX(tb_Address[Branch],MATCH(E143,tb_Address[Branch Code],0)),"")} -> สาขาที่ 00001 | G143: 8857128011669 | H143: {=IF(G143<>"",INDEX(tb_MainDatabase[Scent],MATCH(G143,tb_MainDatabase[Barcode],0)),"")} -> Blackest Black | I143: {=IF(G143<>"",INDEX(tb_MainDatabase[Size],MATCH(G143,tb_MainDatabase[Barcode],0)),"")} -> 50 ml. | J143: 2 | L143: {=IFERROR(IF(C143=C142,IF(C143="","","-"),INDEX(tb_Address[Store Tel.],MATCH(F143,tb_Address[Branch],0))),"")} -> - | M143: {=IFERROR(IF(C143=C142,IF(C143="","","-"),INDEX(tb_Address[ชื่อผู้รับสินค้า],MATCH(F143,tb_Address[Branch],0))),"")} -> - | N143: {=IFERROR(IF(C143=C142,IF(C143="","","-"),INDEX(tb_Address[ที่อยู่ Store],MATCH(F143,tb_Address[Branch],0))),"")} -> -
A144: =IF(C144="","",ROW()-ROW(tb_PO[[#HEADERS],[Order]])) -> 141 | B144: 46035 | C144: WP0260113001 | D144: WP0260113001-1 | E144: 01_CTW - Central World | F144: {=IF(E144<>"",INDEX(tb_Address[Branch],MATCH(E144,tb_Address[Branch Code],0)),"")} -> สาขาที่ 00001 | G144: 8857128011683 | H144: {=IF(G144<>"",INDEX(tb_MainDatabase[Scent],MATCH(G144,tb_MainDatabase[Barcode],0)),"")} -> Legend of Oud | I144: {=IF(G144<>"",INDEX(tb_MainDatabase[Size],MATCH(G144,tb_MainDatabase[Barcode],0)),"")} -> 50 ml. | J144: 2 | L144: {=IFERROR(IF(C144=C143,IF(C144="","","-"),INDEX(tb_Address[Store Tel.],MATCH(F144,tb_Address[Branch],0))),"")} -> - | M144: {=IFERROR(IF(C144=C143,IF(C144="","","-"),INDEX(tb_Address[ชื่อผู้รับสินค้า],MATCH(F144,tb_Address[Branch],0))),"")} -> - | N144: {=IFERROR(IF(C144=C143,IF(C144="","","-"),INDEX(tb_Address[ที่อยู่ Store],MATCH(F144,tb_Address[Branch],0))),"")} -> -
A145: =IF(C145="","",ROW()-ROW(tb_PO[[#HEADERS],[Order]])) -> 142 | B145: 46035 | C145: WP0260113001 | D145: WP0260113001-1 | E145: 01_CTW - Central World | F145: {=IF(E145<>"",INDEX(tb_Address[Branch],MATCH(E145,tb_Address[Branch Code],0)),"")} -> สาขาที่ 00001 | G145: 8857128012007 | H145: {=IF(G145<>"",INDEX(tb_MainDatabase[Scent],MATCH(G145,tb_MainDatabase[Barcode],0)),"")} -> Legend of Oud | I145: {=IF(G145<>"",INDEX(tb_MainDatabase[Size],MATCH(G145,tb_MainDatabase[Barcode],0)),"")} -> 30 ml. | J145: 2 | L145: {=IFERROR(IF(C145=C144,IF(C145="","","-"),INDEX(tb_Address[Store Tel.],MATCH(F145,tb_Address[Branch],0))),"")} -> - | M145: {=IFERROR(IF(C145=C144,IF(C145="","","-"),INDEX(tb_Address[ชื่อผู้รับสินค้า],MATCH(F145,tb_Address[Branch],0))),"")} -> - | N145: {=IFERROR(IF(C145=C144,IF(C145="","","-"),INDEX(tb_Address[ที่อยู่ Store],MATCH(F145,tb_Address[Branch],0))),"")} -> -
A146: =IF(C146="","",ROW()-ROW(tb_PO[[#HEADERS],[Order]])) -> 143 | B146: 46035 | C146: WP0260113001 | D146: WP0260113001-1 | E146: 01_CTW - Central World | F146: {=IF(E146<>"",INDEX(tb_Address[Branch],MATCH(E146,tb_Address[Branch Code],0)),"")} -> สาขาที่ 00001 | G146: 8857128011607 | H146: {=IF(G146<>"",INDEX(tb_MainDatabase[Scent],MATCH(G146,tb_MainDatabase[Barcode],0)),"")} -> Queen | I146: {=IF(G146<>"",INDEX(tb_MainDatabase[Size],MATCH(G146,tb_MainDatabase[Barcode],0)),"")} -> 50 ml. | J146: 2 | L146: {=IFERROR(IF(C146=C145,IF(C146="","","-"),INDEX(tb_Address[Store Tel.],MATCH(F146,tb_Address[Branch],0))),"")} -> - | M146: {=IFERROR(IF(C146=C145,IF(C146="","","-"),INDEX(tb_Address[ชื่อผู้รับสินค้า],MATCH(F146,tb_Address[Branch],0))),"")} -> - | N146: {=IFERROR(IF(C146=C145,IF(C146="","","-"),INDEX(tb_Address[ที่อยู่ Store],MATCH(F146,tb_Address[Branch],0))),"")} -> -
A147: =IF(C147="","",ROW()-ROW(tb_PO[[#HEADERS],[Order]])) -> 144 | B147: 46035 | C147: WP0260113001 | D147: WP0260113001-1 | E147: 01_CTW - Central World | F147: {=IF(E147<>"",INDEX(tb_Address[Branch],MATCH(E147,tb_Address[Branch Code],0)),"")} -> สาขาที่ 00001 | G147: 8857128011713 | H147: {=IF(G147<>"",INDEX(tb_MainDatabase[Scent],MATCH(G147,tb_MainDatabase[Barcode],0)),"")} -> Sparkling Mandarin | I147: {=IF(G147<>"",INDEX(tb_MainDatabase[Size],MATCH(G147,tb_MainDatabase[Barcode],0)),"")} -> 50 ml. | J147: 2 | L147: {=IFERROR(IF(C147=C146,IF(C147="","","-"),INDEX(tb_Address[Store Tel.],MATCH(F147,tb_Address[Branch],0))),"")} -> - | M147: {=IFERROR(IF(C147=C146,IF(C147="","","-"),INDEX(tb_Address[ชื่อผู้รับสินค้า],MATCH(F147,tb_Address[Branch],0))),"")} -> - | N147: {=IFERROR(IF(C147=C146,IF(C147="","","-"),INDEX(tb_Address[ที่อยู่ Store],MATCH(F147,tb_Address[Branch],0))),"")} -> -
A148: =IF(C148="","",ROW()-ROW(tb_PO[[#HEADERS],[Order]])) -> 145 | B148: 46035 | C148: WP0260113001 | D148: WP0260113001-1 | E148: 01_CTW - Central World | F148: {=IF(E148<>"",INDEX(tb_Address[Branch],MATCH(E148,tb_Address[Branch Code],0)),"")} -> สาขาที่ 00001 | G148: 8857128012030 | H148: {=IF(G148<>"",INDEX(tb_MainDatabase[Scent],MATCH(G148,tb_MainDatabase[Barcode],0)),"")} -> Dream Island | I148: {=IF(G148<>"",INDEX(tb_MainDatabase[Size],MATCH(G148,tb_MainDatabase[Barcode],0)),"")} -> 10 ml. | J148: 10 | L148: {=IFERROR(IF(C148=C147,IF(C148="","","-"),INDEX(tb_Address[Store Tel.],MATCH(F148,tb_Address[Branch],0))),"")} -> - | M148: {=IFERROR(IF(C148=C147,IF(C148="","","-"),INDEX(tb_Address[ชื่อผู้รับสินค้า],MATCH(F148,tb_Address[Branch],0))),"")} -> - | N148: {=IFERROR(IF(C148=C147,IF(C148="","","-"),INDEX(tb_Address[ที่อยู่ Store],MATCH(F148,tb_Address[Branch],0))),"")} -> -
... A188: =IF(C188="","",ROW()-ROW(tb_PO[[#HEADERS],[Order]])) -> 185 | B188: 46060 | C188: WP0260207001 | D188: WP0260207001-1 | E188: 01_CTW - Central World | F188: {=IF(E188<>"",INDEX(tb_Address[Branch],MATCH(E188,tb_Address[Branch Code],0)),"")} -> สาขาที่ 00001 | G188: 8857128012101 | H188: {=IF(G188<>"",INDEX(tb_MainDatabase[Scent],MATCH(G188,tb_MainDatabase[Barcode],0)),"")} -> Blackest Black | I188: {=IF(G188<>"",INDEX(tb_MainDatabase[Size],MATCH(G188,tb_MainDatabase[Barcode],0)),"")} -> 10 ml. | J188: 5 | L188: {=IFERROR(IF(C188=C187,IF(C188="","","-"),INDEX(tb_Address[Store Tel.],MATCH(F188,tb_Address[Branch],0))),"")} -> - | M188: {=IFERROR(IF(C188=C187,IF(C188="","","-"),INDEX(tb_Address[ชื่อผู้รับสินค้า],MATCH(F188,tb_Address[Branch],0))),"")} -> - | N188: {=IFERROR(IF(C188=C187,IF(C188="","","-"),INDEX(tb_Address[ที่อยู่ Store],MATCH(F188,tb_Address[Branch],0))),"")} -> -
A189: =IF(C189="","",ROW()-ROW(tb_PO[[#HEADERS],[Order]])) -> 186 | B189: 46060 | C189: WP0260207001 | D189: WP0260207001-1 | E189: 01_CTW - Central World | F189: {=IF(E189<>"",INDEX(tb_Address[Branch],MATCH(E189,tb_Address[Branch Code],0)),"")} -> สาขาที่ 00001 | G189: DIM50 | H189: {=IF(G189<>"",INDEX(tb_MainDatabase[Scent],MATCH(G189,tb_MainDatabase[Barcode],0)),"")} -> Dream Island TRY ME! | I189: {=IF(G189<>"",INDEX(tb_MainDatabase[Size],MATCH(G189,tb_MainDatabase[Barcode],0)),"")} -> 50 ml. | J189: 1 | L189: {=IFERROR(IF(C189=C188,IF(C189="","","-"),INDEX(tb_Address[Store Tel.],MATCH(F189,tb_Address[Branch],0))),"")} -> - | M189: {=IFERROR(IF(C189=C188,IF(C189="","","-"),INDEX(tb_Address[ชื่อผู้รับสินค้า],MATCH(F189,tb_Address[Branch],0))),"")} -> - | N189: {=IFERROR(IF(C189=C188,IF(C189="","","-"),INDEX(tb_Address[ที่อยู่ Store],MATCH(F189,tb_Address[Branch],0))),"")} -> -
A190: =IF(C190="","",ROW()-ROW(tb_PO[[#HEADERS],[Order]])) -> 187 | B190: 46060 | C190: WP0260207001 | D190: WP0260207001-1 | E190: 01_CTW - Central World | F190: {=IF(E190<>"",INDEX(tb_Address[Branch],MATCH(E190,tb_Address[Branch Code],0)),"")} -> สาขาที่ 00001 | G190: EDM50 | H190: {=IF(G190<>"",INDEX(tb_MainDatabase[Scent],MATCH(G190,tb_MainDatabase[Barcode],0)),"")} -> Eden TRY ME! | I190: {=IF(G190<>"",INDEX(tb_MainDatabase[Size],MATCH(G190,tb_MainDatabase[Barcode],0)),"")} -> 50 ml. | J190: 1 | L190: {=IFERROR(IF(C190=C189,IF(C190="","","-"),INDEX(tb_Address[Store Tel.],MATCH(F190,tb_Address[Branch],0))),"")} -> - | M190: {=IFERROR(IF(C190=C189,IF(C190="","","-"),INDEX(tb_Address[ชื่อผู้รับสินค้า],MATCH(F190,tb_Address[Branch],0))),"")} -> - | N190: {=IFERROR(IF(C190=C189,IF(C190="","","-"),INDEX(tb_Address[ที่อยู่ Store],MATCH(F190,tb_Address[Branch],0))),"")} -> -
A191: =IF(C191="","",ROW()-ROW(tb_PO[[#HEADERS],[Order]])) -> 188 | B191: 46060 | C191: WP0260207001 | D191: WP0260207001-1 | E191: 01_CTW - Central World | F191: {=IF(E191<>"",INDEX(tb_Address[Branch],MATCH(E191,tb_Address[Branch Code],0)),"")} -> สาขาที่ 00001 | G191: SPM50 | H191: {=IF(G191<>"",INDEX(tb_MainDatabase[Scent],MATCH(G191,tb_MainDatabase[Barcode],0)),"")} -> Secret of Peach TRY ME! | I191: {=IF(G191<>"",INDEX(tb_MainDatabase[Size],MATCH(G191,tb_MainDatabase[Barcode],0)),"")} -> 50 ml. | J191: 1 | L191: {=IFERROR(IF(C191=C190,IF(C191="","","-"),INDEX(tb_Address[Store Tel.],MATCH(F191,tb_Address[Branch],0))),"")} -> - | M191: {=IFERROR(IF(C191=C190,IF(C191="","","-"),INDEX(tb_Address[ชื่อผู้รับสินค้า],MATCH(F191,tb_Address[Branch],0))),"")} -> - | N191: {=IFERROR(IF(C191=C190,IF(C191="","","-"),INDEX(tb_Address[ที่อยู่ Store],MATCH(F191,tb_Address[Branch],0))),"")} -> -
A192: =IF(C192="","",ROW()-ROW(tb_PO[[#HEADERS],[Order]])) -> 189 | B192: 46060 | C192: WP0260207001 | D192: WP0260207001-1 | E192: 01_CTW - Central World | F192: {=IF(E192<>"",INDEX(tb_Address[Branch],MATCH(E192,tb_Address[Branch Code],0)),"")} -> สาขาที่ 00001 | G192: SEM50 | H192: {=IF(G192<>"",INDEX(tb_MainDatabase[Scent],MATCH(G192,tb_MainDatabase[Barcode],0)),"")} -> Senorita TRY ME! | I192: {=IF(G192<>"",INDEX(tb_MainDatabase[Size],MATCH(G192,tb_MainDatabase[Barcode],0)),"")} -> 50 ml. | J192: 1 | L192: {=IFERROR(IF(C192=C191,IF(C192="","","-"),INDEX(tb_Address[Store Tel.],MATCH(F192,tb_Address[Branch],0))),"")} -> - | M192: {=IFERROR(IF(C192=C191,IF(C192="","","-"),INDEX(tb_Address[ชื่อผู้รับสินค้า],MATCH(F192,tb_Address[Branch],0))),"")} -> - | N192: {=IFERROR(IF(C192=C191,IF(C192="","","-"),INDEX(tb_Address[ที่อยู่ Store],MATCH(F192,tb_Address[Branch],0))),"")} -> -
A193: =IF(C193="","",ROW()-ROW(tb_PO[[#HEADERS],[Order]])) -> 190 | B193: 46066 | C193: WP0260213001 | D193: WP0260213001-1 | E193: 01_CTW - Central World | F193: {=IF(E193<>"",INDEX(tb_Address[Branch],MATCH(E193,tb_Address[Branch Code],0)),"")} -> สาขาที่ 00001 | G193: 8857128011560 | H193: {=IF(G193<>"",INDEX(tb_MainDatabase[Scent],MATCH(G193,tb_MainDatabase[Barcode],0)),"")} -> Cherry Shade | I193: {=IF(G193<>"",INDEX(tb_MainDatabase[Size],MATCH(G193,tb_MainDatabase[Barcode],0)),"")} -> 50 ml. | J193: 10 | L193: {=IFERROR(IF(C193=C192,IF(C193="","","-"),INDEX(tb_Address[Store Tel.],MATCH(F193,tb_Address[Branch],0))),"")} -> - | M193: {=IFERROR(IF(C193=C192,IF(C193="","","-"),INDEX(tb_Address[ชื่อผู้รับสินค้า],MATCH(F193,tb_Address[Branch],0))),"")} -> - | N193: {=IFERROR(IF(C193=C192,IF(C193="","","-"),INDEX(tb_Address[ที่อยู่ Store],MATCH(F193,tb_Address[Branch],0))),"")} -> -
A194: =IF(C194="","",ROW()-ROW(tb_PO[[#HEADERS],[Order]])) -> 191 | B194: 46066 | C194: WP0260213001 | D194: WP0260213001-1 | E194: 01_CTW - Central World | F194: {=IF(E194<>"",INDEX(tb_Address[Branch],MATCH(E194,tb_Address[Branch Code],0)),"")} -> สาขาที่ 00001 | G194: 8857128012153 | H194: {=IF(G194<>"",INDEX(tb_MainDatabase[Scent],MATCH(G194,tb_MainDatabase[Barcode],0)),"")} -> Cherry Shade | I194: {=IF(G194<>"",INDEX(tb_MainDatabase[Size],MATCH(G194,tb_MainDatabase[Barcode],0)),"")} -> 30 ml. | J194: 10 | L194: {=IFERROR(IF(C194=C193,IF(C194="","","-"),INDEX(tb_Address[Store Tel.],MATCH(F194,tb_Address[Branch],0))),"")} -> - | M194: {=IFERROR(IF(C194=C193,IF(C194="","","-"),INDEX(tb_Address[ชื่อผู้รับสินค้า],MATCH(F194,tb_Address[Branch],0))),"")} -> - | N194: {=IFERROR(IF(C194=C193,IF(C194="","","-"),INDEX(tb_Address[ที่อยู่ Store],MATCH(F194,tb_Address[Branch],0))),"")} -> -
A195: =IF(C195="","",ROW()-ROW(tb_PO[[#HEADERS],[Order]])) -> 192 | B195: 46066 | C195: WP0260213001 | D195: WP0260213001-1 | E195: 01_CTW - Central World | F195: {=IF(E195<>"",INDEX(tb_Address[Branch],MATCH(E195,tb_Address[Branch Code],0)),"")} -> สาขาที่ 00001 | G195: 8857128011584 | H195: {=IF(G195<>"",INDEX(tb_MainDatabase[Scent],MATCH(G195,tb_MainDatabase[Barcode],0)),"")} -> Passion | I195: {=IF(G195<>"",INDEX(tb_MainDatabase[Size],MATCH(G195,tb_MainDatabase[Barcode],0)),"")} -> 50 ml. | J195: 10 | L195: {=IFERROR(IF(C195=C194,IF(C195="","","-"),INDEX(tb_Address[Store Tel.],MATCH(F195,tb_Address[Branch],0))),"")} -> - | M195: {=IFERROR(IF(C195=C194,IF(C195="","","-"),INDEX(tb_Address[ชื่อผู้รับสินค้า],MATCH(F195,tb_Address[Branch],0))),"")} -> - | N195: {=IFERROR(IF(C195=C194,IF(C195="","","-"),INDEX(tb_Address[ที่อยู่ Store],MATCH(F195,tb_Address[Branch],0))),"")} -> -
A196: =IF(C196="","",ROW()-ROW(tb_PO[[#HEADERS],[Order]])) -> 193 | B196: 46066 | C196: WP0260213001 | D196: WP0260213001-1 | E196: 01_CTW - Central World | F196: {=IF(E196<>"",INDEX(tb_Address[Branch],MATCH(E196,tb_Address[Branch Code],0)),"")} -> สาขาที่ 00001 | G196: 8857128012156 | H196: {=IF(G196<>"",INDEX(tb_MainDatabase[Scent],MATCH(G196,tb_MainDatabase[Barcode],0)),"")} -> Passion | I196: {=IF(G196<>"",INDEX(tb_MainDatabase[Size],MATCH(G196,tb_MainDatabase[Barcode],0)),"")} -> 30 ml. | J196: 10 | L196: {=IFERROR(IF(C196=C195,IF(C196="","","-"),INDEX(tb_Address[Store Tel.],MATCH(F196,tb_Address[Branch],0))),"")} -> - | M196: {=IFERROR(IF(C196=C195,IF(C196="","","-"),INDEX(tb_Address[ชื่อผู้รับสินค้า],MATCH(F196,tb_Address[Branch],0))),"")} -> - | N196: {=IFERROR(IF(C196=C195,IF(C196="","","-"),INDEX(tb_Address[ที่อยู่ Store],MATCH(F196,tb_Address[Branch],0))),"")} -> -
A197: =IF(C197="","",ROW()-ROW(tb_PO[[#HEADERS],[Order]])) -> 194 | B197: 46066 | C197: WP0260213001 | D197: WP0260213001-1 | E197: 01_CTW - Central World | F197: {=IF(E197<>"",INDEX(tb_Address[Branch],MATCH(E197,tb_Address[Branch Code],0)),"")} -> สาขาที่ 00001 | G197: 8857128011621 | H197: {=IF(G197<>"",INDEX(tb_MainDatabase[Scent],MATCH(G197,tb_MainDatabase[Barcode],0)),"")} -> Rosarine | I197: {=IF(G197<>"",INDEX(tb_MainDatabase[Size],MATCH(G197,tb_MainDatabase[Barcode],0)),"")} -> 50 ml. | J197: 10 | L197: {=IFERROR(IF(C197=C196,IF(C197="","","-"),INDEX(tb_Address[Store Tel.],MATCH(F197,tb_Address[Branch],0))),"")} -> - | M197: {=IFERROR(IF(C197=C196,IF(C197="","","-"),INDEX(tb_Address[ชื่อผู้รับสินค้า],MATCH(F197,tb_Address[Branch],0))),"")} -> - | N197: {=IFERROR(IF(C197=C196,IF(C197="","","-"),INDEX(tb_Address[ที่อยู่ Store],MATCH(F197,tb_Address[Branch],0))),"")} -> -
A198: =IF(C198="","",ROW()-ROW(tb_PO[[#HEADERS],[Order]])) -> 195 | B198: 46066 | C198: WP0260213001 | D198: WP0260213001-1 | E198: 01_CTW - Central World | F198: {=IF(E198<>"",INDEX(tb_Address[Branch],MATCH(E198,tb_Address[Branch Code],0)),"")} -> สาขาที่ 00001 | G198: 8857128012159 | H198: {=IF(G198<>"",INDEX(tb_MainDatabase[Scent],MATCH(G198,tb_MainDatabase[Barcode],0)),"")} -> Rosarine | I198: {=IF(G198<>"",INDEX(tb_MainDatabase[Size],MATCH(G198,tb_MainDatabase[Barcode],0)),"")} -> 30 ml. | J198: 10 | L198: {=IFERROR(IF(C198=C197,IF(C198="","","-"),INDEX(tb_Address[Store Tel.],MATCH(F198,tb_Address[Branch],0))),"")} -> - | M198: {=IFERROR(IF(C198=C197,IF(C198="","","-"),INDEX(tb_Address[ชื่อผู้รับสินค้า],MATCH(F198,tb_Address[Branch],0))),"")} -> - | N198: {=IFERROR(IF(C198=C197,IF(C198="","","-"),INDEX(tb_Address[ที่อยู่ Store],MATCH(F198,tb_Address[Branch],0))),"")} -> -
A199: =IF(C199="","",ROW()-ROW(tb_PO[[#HEADERS],[Order]])) -> 196 | B199: 46066 | C199: WP0260213001 | D199: WP0260213001-1 | E199: 01_CTW - Central World | F199: {=IF(E199<>"",INDEX(tb_Address[Branch],MATCH(E199,tb_Address[Branch Code],0)),"")} -> สาขาที่ 00001 | G199: 8857128011638 | H199: {=IF(G199<>"",INDEX(tb_MainDatabase[Scent],MATCH(G199,tb_MainDatabase[Barcode],0)),"")} -> Silver | I199: {=IF(G199<>"",INDEX(tb_MainDatabase[Size],MATCH(G199,tb_MainDatabase[Barcode],0)),"")} -> 50 ml. | J199: 10 | L199: {=IFERROR(IF(C199=C198,IF(C199="","","-"),INDEX(tb_Address[Store Tel.],MATCH(F199,tb_Address[Branch],0))),"")} -> - | M199: {=IFERROR(IF(C199=C198,IF(C199="","","-"),INDEX(tb_Address[ชื่อผู้รับสินค้า],MATCH(F199,tb_Address[Branch],0))),"")} -> - | N199: {=IFERROR(IF(C199=C198,IF(C199="","","-"),INDEX(tb_Address[ที่อยู่ Store],MATCH(F199,tb_Address[Branch],0))),"")} -> -
A200: =IF(C200="","",ROW()-ROW(tb_PO[[#HEADERS],[Order]])) -> 197 | B200: 46066 | C200: WP0260213001 | D200: WP0260213001-1 | E200: 01_CTW - Central World | F200: {=IF(E200<>"",INDEX(tb_Address[Branch],MATCH(E200,tb_Address[Branch Code],0)),"")} -> สาขาที่ 00001 | G200: 8857128012162 | H200: {=IF(G200<>"",INDEX(tb_MainDatabase[Scent],MATCH(G200,tb_MainDatabase[Barcode],0)),"")} -> Silver | I200: {=IF(G200<>"",INDEX(tb_MainDatabase[Size],MATCH(G200,tb_MainDatabase[Barcode],0)),"")} -> 30 ml. | J200: 10 | L200: {=IFERROR(IF(C200=C199,IF(C200="","","-"),INDEX(tb_Address[Store Tel.],MATCH(F200,tb_Address[Branch],0))),"")} -> - | M200: {=IFERROR(IF(C200=C199,IF(C200="","","-"),INDEX(tb_Address[ชื่อผู้รับสินค้า],MATCH(F200,tb_Address[Branch],0))),"")} -> - | N200: {=IFERROR(IF(C200=C199,IF(C200="","","-"),INDEX(tb_Address[ที่อยู่ Store],MATCH(F200,tb_Address[Branch],0))),"")} -> -
A201: =IF(C201="","",ROW()-ROW(tb_PO[[#HEADERS],[Order]])) -> 198 | B201: 46066 | C201: WP0260213001 | D201: WP0260213001-1 | E201: 01_CTW - Central World | F201: {=IF(E201<>"",INDEX(tb_Address[Branch],MATCH(E201,tb_Address[Branch Code],0)),"")} -> สาขาที่ 00001 | G201: CRS50 | H201: {=IF(G201<>"",INDEX(tb_MainDatabase[Scent],MATCH(G201,tb_MainDatabase[Barcode],0)),"")} -> Cherry Shade TRY ME! | I201: {=IF(G201<>"",INDEX(tb_MainDatabase[Size],MATCH(G201,tb_MainDatabase[Barcode],0)),"")} -> 50 ml. | J201: 1 | L201: {=IFERROR(IF(C201=C200,IF(C201="","","-"),INDEX(tb_Address[Store Tel.],MATCH(F201,tb_Address[Branch],0))),"")} -> - | M201: {=IFERROR(IF(C201=C200,IF(C201="","","-"),INDEX(tb_Address[ชื่อผู้รับสินค้า],MATCH(F201,tb_Address[Branch],0))),"")} -> - | N201: {=IFERROR(IF(C201=C200,IF(C201="","","-"),INDEX(tb_Address[ที่อยู่ Store],MATCH(F201,tb_Address[Branch],0))),"")} -> -
A202: =IF(C202="","",ROW()-ROW(tb_PO[[#HEADERS],[Order]])) -> 199 | B202: 46066 | C202: WP0260213001 | D202: WP0260213001-1 | E202: 01_CTW - Central World | F202: {=IF(E202<>"",INDEX(tb_Address[Branch],MATCH(E202,tb_Address[Branch Code],0)),"")} -> สาขาที่ 00001 | G202: PSS50 | H202: {=IF(G202<>"",INDEX(tb_MainDatabase[Scent],MATCH(G202,tb_MainDatabase[Barcode],0)),"")} -> Passion TRY ME! | I202: {=IF(G202<>"",INDEX(tb_MainDatabase[Size],MATCH(G202,tb_MainDatabase[Barcode],0)),"")} -> 50 ml. | J202: 1 | L202: {=IFERROR(IF(C202=C201,IF(C202="","","-"),INDEX(tb_Address[Store Tel.],MATCH(F202,tb_Address[Branch],0))),"")} -> - | M202: {=IFERROR(IF(C202=C201,IF(C202="","","-"),INDEX(tb_Address[ชื่อผู้รับสินค้า],MATCH(F202,tb_Address[Branch],0))),"")} -> - | N202: {=IFERROR(IF(C202=C201,IF(C202="","","-"),INDEX(tb_Address[ที่อยู่ Store],MATCH(F202,tb_Address[Branch],0))),"")} -> -
A203: =IF(C203="","",ROW()-ROW(tb_PO[[#HEADERS],[Order]])) -> 200 | B203: 46066 | C203: WP0260213001 | D203: WP0260213001-1 | E203: 01_CTW - Central World | F203: {=IF(E203<>"",INDEX(tb_Address[Branch],MATCH(E203,tb_Address[Branch Code],0)),"")} -> สาขาที่ 00001 | G203: ROS50 | H203: {=IF(G203<>"",INDEX(tb_MainDatabase[Scent],MATCH(G203,tb_MainDatabase[Barcode],0)),"")} -> Rosarine TRY ME! | I203: {=IF(G203<>"",INDEX(tb_MainDatabase[Size],MATCH(G203,tb_MainDatabase[Barcode],0)),"")} -> 50 ml. | J203: 1 | L203: {=IFERROR(IF(C203=C202,IF(C203="","","-"),INDEX(tb_Address[Store Tel.],MATCH(F203,tb_Address[Branch],0))),"")} -> - | M203: {=IFERROR(IF(C203=C202,IF(C203="","","-"),INDEX(tb_Address[ชื่อผู้รับสินค้า],MATCH(F203,tb_Address[Branch],0))),"")} -> - | N203: {=IFERROR(IF(C203=C202,IF(C203="","","-"),INDEX(tb_Address[ที่อยู่ Store],MATCH(F203,tb_Address[Branch],0))),"")} -> -
A204: =IF(C204="","",ROW()-ROW(tb_PO[[#HEADERS],[Order]])) -> 201 | B204: 46066 | C204: WP0260213001 | D204: WP0260213001-1 | E204: 01_CTW - Central World | F204: {=IF(E204<>"",INDEX(tb_Address[Branch],MATCH(E204,tb_Address[Branch Code],0)),"")} -> สาขาที่ 00001 | G204: SIL50 | H204: {=IF(G204<>"",INDEX(tb_MainDatabase[Scent],MATCH(G204,tb_MainDatabase[Barcode],0)),"")} -> Silver TRY ME! | I204: {=IF(G204<>"",INDEX(tb_MainDatabase[Size],MATCH(G204,tb_MainDatabase[Barcode],0)),"")} -> 50 ml. | J204: 1 | L204: {=IFERROR(IF(C204=C203,IF(C204="","","-"),INDEX(tb_Address[Store Tel.],MATCH(F204,tb_Address[Branch],0))),"")} -> - | M204: {=IFERROR(IF(C204=C203,IF(C204="","","-"),INDEX(tb_Address[ชื่อผู้รับสินค้า],MATCH(F204,tb_Address[Branch],0))),"")} -> - | N204: {=IFERROR(IF(C204=C203,IF(C204="","","-"),INDEX(tb_Address[ที่อยู่ Store],MATCH(F204,tb_Address[Branch],0))),"")} -> -
A205: =IF(C205="","",ROW()-ROW(tb_PO[[#HEADERS],[Order]])) -> 202 | B205: 46066 | C205: WP0260213001 | D205: WP0260213001-1 | E205: 01_CTW - Central World | F205: {=IF(E205<>"",INDEX(tb_Address[Branch],MATCH(E205,tb_Address[Branch Code],0)),"")} -> สาขาที่ 00001 | G205: DIM50 | H205: {=IF(G205<>"",INDEX(tb_MainDatabase[Scent],MATCH(G205,tb_MainDatabase[Barcode],0)),"")} -> Dream Island TRY ME! | I205: {=IF(G205<>"",INDEX(tb_MainDatabase[Size],MATCH(G205,tb_MainDatabase[Barcode],0)),"")} -> 50 ml. | J205: 1 | L205: {=IFERROR(IF(C205=C204,IF(C205="","","-"),INDEX(tb_Address[Store Tel.],MATCH(F205,tb_Address[Branch],0))),"")} -> - | M205: {=IFERROR(IF(C205=C204,IF(C205="","","-"),INDEX(tb_Address[ชื่อผู้รับสินค้า],MATCH(F205,tb_Address[Branch],0))),"")} -> - | N205: {=IFERROR(IF(C205=C204,IF(C205="","","-"),INDEX(tb_Address[ที่อยู่ Store],MATCH(F205,tb_Address[Branch],0))),"")} -> -
A206: =IF(C206="","",ROW()-ROW(tb_PO[[#HEADERS],[Order]])) -> 203 | B206: 46066 | C206: WP0260213001 | D206: WP0260213001-1 | E206: 01_CTW - Central World | F206: {=IF(E206<>"",INDEX(tb_Address[Branch],MATCH(E206,tb_Address[Branch Code],0)),"")} -> สาขาที่ 00001 | G206: SPM50 | H206: {=IF(G206<>"",INDEX(tb_MainDatabase[Scent],MATCH(G206,tb_MainDatabase[Barcode],0)),"")} -> Secret of Peach TRY ME! | I206: {=IF(G206<>"",INDEX(tb_MainDatabase[Size],MATCH(G206,tb_MainDatabase[Barcode],0)),"")} -> 50 ml. | J206: 1 | L206: {=IFERROR(IF(C206=C205,IF(C206="","","-"),INDEX(tb_Address[Store Tel.],MATCH(F206,tb_Address[Branch],0))),"")} -> - | M206: {=IFERROR(IF(C206=C205,IF(C206="","","-"),INDEX(tb_Address[ชื่อผู้รับสินค้า],MATCH(F206,tb_Address[Branch],0))),"")} -> - | N206: {=IFERROR(IF(C206=C205,IF(C206="","","-"),INDEX(tb_Address[ที่อยู่ Store],MATCH(F206,tb_Address[Branch],0))),"")} -> -
A207: =IF(C207="","",ROW()-ROW(tb_PO[[#HEADERS],[Order]])) -> 204 | B207: 46066 | C207: WP0260213001 | D207: WP0260213001-1 | E207: 01_CTW - Central World | F207: {=IF(E207<>"",INDEX(tb_Address[Branch],MATCH(E207,tb_Address[Branch Code],0)),"")} -> สาขาที่ 00001 | G207: VYM50 | H207: {=IF(G207<>"",INDEX(tb_MainDatabase[Scent],MATCH(G207,tb_MainDatabase[Barcode],0)),"")} -> Victory TRY ME! | I207: {=IF(G207<>"",INDEX(tb_MainDatabase[Size],MATCH(G207,tb_MainDatabase[Barcode],0)),"")} -> 50 ml. | J207: 1 | L207: {=IFERROR(IF(C207=C206,IF(C207="","","-"),INDEX(tb_Address[Store Tel.],MATCH(F207,tb_Address[Branch],0))),"")} -> - | M207: {=IFERROR(IF(C207=C206,IF(C207="","","-"),INDEX(tb_Address[ชื่อผู้รับสินค้า],MATCH(F207,tb_Address[Branch],0))),"")} -> - | N207: {=IFERROR(IF(C207=C206,IF(C207="","","-"),INDEX(tb_Address[ที่อยู่ Store],MATCH(F207,tb_Address[Branch],0))),"")} -> -
A208: =IF(C208="","",ROW()-ROW(tb_PO[[#HEADERS],[Order]])) -> 205 | B208: 46066 | C208: WP0260213001 | D208: WP0260213001-1 | E208: 01_CTW - Central World | F208: {=IF(E208<>"",INDEX(tb_Address[Branch],MATCH(E208,tb_Address[Branch Code],0)),"")} -> สาขาที่ 00001 | G208: EDM50 | H208: {=IF(G208<>"",INDEX(tb_MainDatabase[Scent],MATCH(G208,tb_MainDatabase[Barcode],0)),"")} -> Eden TRY ME! | I208: {=IF(G208<>"",INDEX(tb_MainDatabase[Size],MATCH(G208,tb_MainDatabase[Barcode],0)),"")} -> 50 ml. | J208: 1 | L208: {=IFERROR(IF(C208=C207,IF(C208="","","-"),INDEX(tb_Address[Store Tel.],MATCH(F208,tb_Address[Branch],0))),"")} -> - | M208: {=IFERROR(IF(C208=C207,IF(C208="","","-"),INDEX(tb_Address[ชื่อผู้รับสินค้า],MATCH(F208,tb_Address[Branch],0))),"")} -> - | N208: {=IFERROR(IF(C208=C207,IF(C208="","","-"),INDEX(tb_Address[ที่อยู่ Store],MATCH(F208,tb_Address[Branch],0))),"")} -> -
A209: =IF(C209="","",ROW()-ROW(tb_PO[[#HEADERS],[Order]])) -> 206 | B209: 46066 | C209: WP0260213001 | D209: WP0260213001-1 | E209: 01_CTW - Central World | F209: {=IF(E209<>"",INDEX(tb_Address[Branch],MATCH(E209,tb_Address[Branch Code],0)),"")} -> สาขาที่ 00001 | G209: SEM50 | H209: {=IF(G209<>"",INDEX(tb_MainDatabase[Scent],MATCH(G209,tb_MainDatabase[Barcode],0)),"")} -> Senorita TRY ME! | I209: {=IF(G209<>"",INDEX(tb_MainDatabase[Size],MATCH(G209,tb_MainDatabase[Barcode],0)),"")} -> 50 ml. | J209: 1 | L209: {=IFERROR(IF(C209=C208,IF(C209="","","-"),INDEX(tb_Address[Store Tel.],MATCH(F209,tb_Address[Branch],0))),"")} -> - | M209: {=IFERROR(IF(C209=C208,IF(C209="","","-"),INDEX(tb_Address[ชื่อผู้รับสินค้า],MATCH(F209,tb_Address[Branch],0))),"")} -> - | N209: {=IFERROR(IF(C209=C208,IF(C209="","","-"),INDEX(tb_Address[ที่อยู่ Store],MATCH(F209,tb_Address[Branch],0))),"")} -> -
A210: =IF(C210="","",ROW()-ROW(tb_PO[[#HEADERS],[Order]])) -> 207 | B210: 46066 | C210: WP0260213001 | D210: WP0260213001-1 | E210: 01_CTW - Central World | F210: {=IF(E210<>"",INDEX(tb_Address[Branch],MATCH(E210,tb_Address[Branch Code],0)),"")} -> สาขาที่ 00001 | G210: 8857128012061 | H210: {=IF(G210<>"",INDEX(tb_MainDatabase[Scent],MATCH(G210,tb_MainDatabase[Barcode],0)),"")} -> Vivid | I210: {=IF(G210<>"",INDEX(tb_MainDatabase[Size],MATCH(G210,tb_MainDatabase[Barcode],0)),"")} -> 4 ml. | J210: 10 | L210: {=IFERROR(IF(C210=C209,IF(C210="","","-"),INDEX(tb_Address[Store Tel.],MATCH(F210,tb_Address[Branch],0))),"")} -> - | M210: {=IFERROR(IF(C210=C209,IF(C210="","","-"),INDEX(tb_Address[ชื่อผู้รับสินค้า],MATCH(F210,tb_Address[Branch],0))),"")} -> - | N210: {=IFERROR(IF(C210=C209,IF(C210="","","-"),INDEX(tb_Address[ที่อยู่ Store],MATCH(F210,tb_Address[Branch],0))),"")} -> -
A211: =IF(C211="","",ROW()-ROW(tb_PO[[#HEADERS],[Order]])) -> 208 | B211: 46066 | C211: WP0260213001 | D211: WP0260213001-1 | E211: 01_CTW - Central World | F211: {=IF(E211<>"",INDEX(tb_Address[Branch],MATCH(E211,tb_Address[Branch Code],0)),"")} -> สาขาที่ 00001 | G211: 8857128012056 | H211: {=IF(G211<>"",INDEX(tb_MainDatabase[Scent],MATCH(G211,tb_MainDatabase[Barcode],0)),"")} -> Sicilia | I211: {=IF(G211<>"",INDEX(tb_MainDatabase[Size],MATCH(G211,tb_MainDatabase[Barcode],0)),"")} -> 4 ml. | J211: 10 | L211: {=IFERROR(IF(C211=C210,IF(C211="","","-"),INDEX(tb_Address[Store Tel.],MATCH(F211,tb_Address[Branch],0))),"")} -> - | M211: {=IFERROR(IF(C211=C210,IF(C211="","","-"),INDEX(tb_Address[ชื่อผู้รับสินค้า],MATCH(F211,tb_Address[Branch],0))),"")} -> - | N211: {=IFERROR(IF(C211=C210,IF(C211="","","-"),INDEX(tb_Address[ที่อยู่ Store],MATCH(F211,tb_Address[Branch],0))),"")} -> -
A212: =IF(C212="","",ROW()-ROW(tb_PO[[#HEADERS],[Order]])) -> 209 | B212: 46071 | C212: WP0260218001 | D212: WP0260218001-1 | E212: 01_CTW - Central World | F212: {=IF(E212<>"",INDEX(tb_Address[Branch],MATCH(E212,tb_Address[Branch Code],0)),"")} -> สาขาที่ 00001 | G212: 8857128012154 | H212: {=IF(G212<>"",INDEX(tb_MainDatabase[Scent],MATCH(G212,tb_MainDatabase[Barcode],0)),"")} -> Cherry Shade | I212: {=IF(G212<>"",INDEX(tb_MainDatabase[Size],MATCH(G212,tb_MainDatabase[Barcode],0)),"")} -> 10 ml. | J212: 5 | L212: {=IFERROR(IF(C212=C211,IF(C212="","","-"),INDEX(tb_Address[Store Tel.],MATCH(F212,tb_Address[Branch],0))),"")} -> - | M212: {=IFERROR(IF(C212=C211,IF(C212="","","-"),INDEX(tb_Address[ชื่อผู้รับสินค้า],MATCH(F212,tb_Address[Branch],0))),"")} -> - | N212: {=IFERROR(IF(C212=C211,IF(C212="","","-"),INDEX(tb_Address[ที่อยู่ Store],MATCH(F212,tb_Address[Branch],0))),"")} -> -
A213: =IF(C213="","",ROW()-ROW(tb_PO[[#HEADERS],[Order]])) -> 210 | B213: 46071 | C213: WP0260218001 | D213: WP0260218001-1 | E213: 01_CTW - Central World | F213: {=IF(E213<>"",INDEX(tb_Address[Branch],MATCH(E213,tb_Address[Branch Code],0)),"")} -> สาขาที่ 00001 | G213: 8857128012157 | H213: {=IF(G213<>"",INDEX(tb_MainDatabase[Scent],MATCH(G213,tb_MainDatabase[Barcode],0)),"")} -> Passion | I213: {=IF(G213<>"",INDEX(tb_MainDatabase[Size],MATCH(G213,tb_MainDatabase[Barcode],0)),"")} -> 10 ml. | J213: 5 | L213: {=IFERROR(IF(C213=C212,IF(C213="","","-"),INDEX(tb_Address[Store Tel.],MATCH(F213,tb_Address[Branch],0))),"")} -> - | M213: {=IFERROR(IF(C213=C212,IF(C213="","","-"),INDEX(tb_Address[ชื่อผู้รับสินค้า],MATCH(F213,tb_Address[Branch],0))),"")} -> - | N213: {=IFERROR(IF(C213=C212,IF(C213="","","-"),INDEX(tb_Address[ที่อยู่ Store],MATCH(F213,tb_Address[Branch],0))),"")} -> -
A214: =IF(C214="","",ROW()-ROW(tb_PO[[#HEADERS],[Order]])) -> 211 | B214: 46071 | C214: WP0260218001 | D214: WP0260218001-1 | E214: 01_CTW - Central World | F214: {=IF(E214<>"",INDEX(tb_Address[Branch],MATCH(E214,tb_Address[Branch Code],0)),"")} -> สาขาที่ 00001 | G214: 8857128012160 | H214: {=IF(G214<>"",INDEX(tb_MainDatabase[Scent],MATCH(G214,tb_MainDatabase[Barcode],0)),"")} -> Rosarine | I214: {=IF(G214<>"",INDEX(tb_MainDatabase[Size],MATCH(G214,tb_MainDatabase[Barcode],0)),"")} -> 10 ml. | J214: 5 | L214: {=IFERROR(IF(C214=C213,IF(C214="","","-"),INDEX(tb_Address[Store Tel.],MATCH(F214,tb_Address[Branch],0))),"")} -> - | M214: {=IFERROR(IF(C214=C213,IF(C214="","","-"),INDEX(tb_Address[ชื่อผู้รับสินค้า],MATCH(F214,tb_Address[Branch],0))),"")} -> - | N214: {=IFERROR(IF(C214=C213,IF(C214="","","-"),INDEX(tb_Address[ที่อยู่ Store],MATCH(F214,tb_Address[Branch],0))),"")} -> -
A215: =IF(C215="","",ROW()-ROW(tb_PO[[#HEADERS],[Order]])) -> 212 | B215: 46071 | C215: WP0260218001 | D215: WP0260218001-1 | E215: 01_CTW - Central World | F215: {=IF(E215<>"",INDEX(tb_Address[Branch],MATCH(E215,tb_Address[Branch Code],0)),"")} -> สาขาที่ 00001 | G215: 8857128012163 | H215: {=IF(G215<>"",INDEX(tb_MainDatabase[Scent],MATCH(G215,tb_MainDatabase[Barcode],0)),"")} -> Silver | I215: {=IF(G215<>"",INDEX(tb_MainDatabase[Size],MATCH(G215,tb_MainDatabase[Barcode],0)),"")} -> 10 ml. | J215: 5 | L215: {=IFERROR(IF(C215=C214,IF(C215="","","-"),INDEX(tb_Address[Store Tel.],MATCH(F215,tb_Address[Branch],0))),"")} -> - | M215: {=IFERROR(IF(C215=C214,IF(C215="","","-"),INDEX(tb_Address[ชื่อผู้รับสินค้า],MATCH(F215,tb_Address[Branch],0))),"")} -> - | N215: {=IFERROR(IF(C215=C214,IF(C215="","","-"),INDEX(tb_Address[ที่อยู่ Store],MATCH(F215,tb_Address[Branch],0))),"")} -> -
A216: =IF(C216="","",ROW()-ROW(tb_PO[[#HEADERS],[Order]])) -> 213 | B216: 46071 | C216: WP0260218001 | D216: WP0260218001-1 | E216: 01_CTW - Central World | F216: {=IF(E216<>"",INDEX(tb_Address[Branch],MATCH(E216,tb_Address[Branch Code],0)),"")} -> สาขาที่ 00001 | G216: 8857128012030 | H216: {=IF(G216<>"",INDEX(tb_MainDatabase[Scent],MATCH(G216,tb_MainDatabase[Barcode],0)),"")} -> Dream Island | I216: {=IF(G216<>"",INDEX(tb_MainDatabase[Size],MATCH(G216,tb_MainDatabase[Barcode],0)),"")} -> 10 ml. | J216: 10 | L216: {=IFERROR(IF(C216=C215,IF(C216="","","-"),INDEX(tb_Address[Store Tel.],MATCH(F216,tb_Address[Branch],0))),"")} -> - | M216: {=IFERROR(IF(C216=C215,IF(C216="","","-"),INDEX(tb_Address[ชื่อผู้รับสินค้า],MATCH(F216,tb_Address[Branch],0))),"")} -> - | N216: {=IFERROR(IF(C216=C215,IF(C216="","","-"),INDEX(tb_Address[ที่อยู่ Store],MATCH(F216,tb_Address[Branch],0))),"")} -> -
A217: =IF(C217="","",ROW()-ROW(tb_PO[[#HEADERS],[Order]])) -> 214 | B217: 46071 | C217: WP0260218001 | D217: WP0260218001-1 | E217: 01_CTW - Central World | F217: {=IF(E217<>"",INDEX(tb_Address[Branch],MATCH(E217,tb_Address[Branch Code],0)),"")} -> สาขาที่ 00001 | G217: 8857128012058 | H217: {=IF(G217<>"",INDEX(tb_MainDatabase[Scent],MATCH(G217,tb_MainDatabase[Barcode],0)),"")} -> Eden | I217: {=IF(G217<>"",INDEX(tb_MainDatabase[Size],MATCH(G217,tb_MainDatabase[Barcode],0)),"")} -> 10 ml. | J217: 5 | L217: {=IFERROR(IF(C217=C216,IF(C217="","","-"),INDEX(tb_Address[Store Tel.],MATCH(F217,tb_Address[Branch],0))),"")} -> - | M217: {=IFERROR(IF(C217=C216,IF(C217="","","-"),INDEX(tb_Address[ชื่อผู้รับสินค้า],MATCH(F217,tb_Address[Branch],0))),"")} -> - | N217: {=IFERROR(IF(C217=C216,IF(C217="","","-"),INDEX(tb_Address[ที่อยู่ Store],MATCH(F217,tb_Address[Branch],0))),"")} -> -
A218: =IF(C218="","",ROW()-ROW(tb_PO[[#HEADERS],[Order]])) -> 215 | B218: 46071 | C218: WP0260218001 | D218: WP0260218001-1 | E218: 01_CTW - Central World | F218: {=IF(E218<>"",INDEX(tb_Address[Branch],MATCH(E218,tb_Address[Branch Code],0)),"")} -> สาขาที่ 00001 | G218: 8857128012039 | H218: {=IF(G218<>"",INDEX(tb_MainDatabase[Scent],MATCH(G218,tb_MainDatabase[Barcode],0)),"")} -> Senorita | I218: {=IF(G218<>"",INDEX(tb_MainDatabase[Size],MATCH(G218,tb_MainDatabase[Barcode],0)),"")} -> 10 ml. | J218: 5 | L218: {=IFERROR(IF(C218=C217,IF(C218="","","-"),INDEX(tb_Address[Store Tel.],MATCH(F218,tb_Address[Branch],0))),"")} -> - | M218: {=IFERROR(IF(C218=C217,IF(C218="","","-"),INDEX(tb_Address[ชื่อผู้รับสินค้า],MATCH(F218,tb_Address[Branch],0))),"")} -> - | N218: {=IFERROR(IF(C218=C217,IF(C218="","","-"),INDEX(tb_Address[ที่อยู่ Store],MATCH(F218,tb_Address[Branch],0))),"")} -> -
